Workbook

Sheet Abs. - L&T
B2: APPLICATION FOR INTERIM PAYMENT
B3: ABSTRACT SHEET
B4: Interim Payment Application No. : | D4: IPA - 34 | G4: Bill date : | H4: =TODAY()-1 -> 46285
B5: Type of Work : | D5: ='Abs. - PMC (For Print)'!D5 -> Main Works & Price Adjustment
B6: Period of bill : | D6: ='Abs. - PMC (For Print)'!D6 -> 1st Jul'26 to 31st Jul'26
B7: EPC Contractor : | D7: Larsen and Toubro Limited
B8: Address: | D8: L&T Construction, Majirgaon Palashbari - Sualkuchi Bridge Project, Dag No. 268 & 269, Patta No. 43 & 168, Revenue Village - Santala, Revenue Circle - Palashbari, Kamrup District, Assam - 781125.
B9: Employer : | D9: The Chief Engineer (EAP), Public Works Roads Department (PWRD), Assam
B10: Employer's Representative : | D10: Rodic Consultants Private Limited in JV with Intercontinental Consultants and Technocrats Private Limited
B11: LOA Ref. No. : | D11: CE/EAP/ABP-II/EPC/OCB/2023/35 | G11: Contract Value (INR) : | H11: =26885400000 -> 26885400000
B12: Work Order No : | D12: Contract Agreement signed on 01-Mar-24 | G12: Financial Progress: | H12: ='Breakup-Summary'!$F$23 -> 0.75762732
B13: Name of Work : | D13: Construction of 4-lane Extradosed PSC Bridge over river Brahmaputra connecting Palashbari and Sualkuchi including Viaduct, Approaches and River Training works etc on EPC mode
B14: S.No. | C14: Description | E14: Currency | F14: Amount
F15: Cumulative Bill | G15: Up to Previous Bill | H15: This Bill
B16: A | C16: Work Done
B17: a | C17: Amount for the works executed under Sub-Clause 14.3 of the General Conditions | E17: =_xlfn.UNICHAR(8377) -> ₹ | F17: =('Detailed breakup'!N531/1.18) -> 1.7226391e+10 | G17: =('Detailed breakup'!P531/1.18) -> 1.1013076e+10 | H17: =F17-G17 -> 6.2133151e+09
B18: b | C18: Amount for the Provisional Sum under Sub-Clause 13.4 of the General Conditions | E18: ₹ | F18: =('Detailed breakup'!N532/1.18) -> 1369786.4 | G18: =('Detailed breakup'!P532/1.18) -> 1369786.4 | H18: =F18-G18 -> 0
B19: c | C19: Amount reflecting Changes in Cost under Sub-Clause 13.7 of the General Conditions | E19: ₹ | F19: =('Price Adj.'!V75/1.18) -> 3.1668907e+08 | G19: =('Price Adj.'!V76/1.18) -> 60193167 | H19: =F19-G19 -> 2.564959e+08
B20: d | C20: Amount of Variation Order executed under Sub-Clause 13.3 of the General Conditions | E20: ₹ | F20: 0 | G20: 0 | H20: =F20-G20 -> 0
B21: e | C21: Amount reflecting Change in Law under Sub-Clause 13.6 of the General Conditions | E21: ₹ | F21: 0 | G21: 0 | H21: =F21-G21 -> 0
B22: f1 | C22: CGST @ 9% on [Aa to Ae] | E22: ₹ | F22: =(SUM($F$17:$F$21)*9%) -> 1.5790005e+09 | G22: =(SUM($G$17:$G$21)*9%) -> 9.9671747e+08 | H22: =ROUND(SUM($H$17:$H$21)*9%,0) -> 582282989
B23: f2 | C23: SGST @ 9% on [Aa to Ae] | E23: ₹ | F23: =(SUM($F$17:$F$21)*9%) -> 1.5790005e+09 | G23: =(SUM($G$17:$G$21)*9%) -> 9.9671747e+08 | H23: =ROUND(SUM($H$17:$H$21)*9%,0) -> 582282989
C24: Total Work Done (A) = (Aa+Ab+Ac+Ad+Ae+Af1+Af2) | E24: ₹ | F24: =SUM(F17:F23) -> 2.070245e+10 | G24: =SUM(G17:G23) -> 13068073432 | H24: =SUM(H17:H23) -> 7.634377e+09
C25: Total Work Done (Excl. of taxes) (A1) = (A/1.18) | E25: ₹ | F25: =F24/1.18 -> 1.7544449e+10 | G25: =G24/1.18 -> 1.1074639e+10 | H25: =H24/1.18 -> 6.469811e+09
B26: B | C26: Advances
B27: a | C27: Mobilization Advance under Sub-Clause 14.2 of General Condidtions - 1st Installment | E27: ₹ | F27: =G27+H27 -> 1.1392119e+09 | G27: =(H11*5%/1.18) -> 1.1392119e+09 | H27: 0
B28: b | C28: Mobilization Advance under Sub-Clause 14.2 of General Condidtions - 2nd Installment | E28: ₹ | F28: =H28+G28 -> 1.1392119e+09 | G28: =(H11*5%/1.18) -> 1.1392119e+09 | H28: 0
B29: c1 | C29: CGST @ 9% on [Ba to Bb] | E29: ₹ | F29: =(SUM($F$27:$F$28)*9%) -> 2.0505814e+08 | G29: =(SUM($G$27:$G$28)*9%) -> 2.0505814e+08 | H29: =SUM($H$27:$H$28)*9% -> 0
B30: c2 | C30: SGST @ 9% on [Ba to Bb] | E30: ₹ | F30: =ROUND(SUM($F$27:$F$28)*9%,0) -> 205058136 | G30: =(SUM($G$27:$G$28)*9%) -> 2.0505814e+08 | H30: =SUM($H$27:$H$28)*9% -> 0
C31: Total Advances (B) = (Ba+Bb+Bc1+Bc2) | E31: ₹ | F31: =SUM(F27:F30) -> 2.68854e+09 | G31: =SUM(G27:G30) -> 2688540000 | H31: =SUM(H27:H30) -> 0
C32: Gross Amount (Incl. Advances) (B1) = (A+B) | E32: ₹ | F32: =F31+F24 -> 2.339099e+10 | G32: =G31+G24 -> 15756613432 | H32: =H31+H24 -> 7.634377e+09
C33: Gross Amount (Excl. Taxes) (B2) = (B1/1.18) | E33: ₹ | F33: =ROUND(F32/1.18,0) -> 19822873220 | G33: =ROUND(G32/1.18,0) -> 13353062231 | H33: =ROUND(H32/1.18,0) -> 6469810989
B34: C | C34: Recoveries
B35: a | C35: Mobilization Advance under Sub-Clause 14.2 of General Condidtions @ 15% on [A1] | E35: ₹ | F35: =G35+H35 -> 2.5841641e+09 | G35: =(SUM(G17:G18)*15%) -> 1.6521668e+09 | H35: =(SUM(H17:H18)*15%) -> 9.3199726e+08
B36: b1 | C36: CGST @ 9% on [Ca] | E36: ₹ | F36: =SUM($F$35:$F$35)*9% -> 2.3257477e+08 | G36: =(SUM($G$35:$G$35)*9%) -> 1.4869501e+08 | H36: =(SUM($H$35:$H$35)*9%) -> 83879754
B37: b2 | C37: SGST @ 9% on [Ca] | E37: ₹ | F37: =SUM($F$35:$F$35)*9% -> 2.3257477e+08 | G37: =(SUM($G$35:$G$35)*9%) -> 1.4869501e+08 | H37: =(SUM($H$35:$H$35)*9%) -> 83879754
C38: Total Recoveries (C) = (Ca+Cb1+Cb2) | E38: ₹ | F38: =SUM(F35:F37) -> 3.0493136e+09 | G38: =SUM(G35:G37) -> 1.9495568e+09 | H38: =SUM(H35:H37) -> 1.0997568e+09
B39: D | C39: Withheld / Release
B40: a | C40: Retention Amount @ 6% upto 5% of Contract Value on [A] | E40: ₹ | F40: =IF((G40+H40)<="5%*$H$11",(G40+H40),5%*$H$11) -> 1.242147e+09 | G40: =G24*6% -> 7.8408441e+08 | H40: =H24*6% -> 4.5806262e+08
B41: b | C41: Release of Retention Amount | E41: ₹ | F41: =G41+H41 -> -605998256 | G41: =-'Retention Release'!$G$39 -> -605998256 | H41: =-'Retention Release'!$G$40 -> 0
B42: c | C42: Withhled Amount | E42: ₹ | F42: =G42+H42 -> 497964247 | G42: ='Withheld-Release'!$M$47 -> 497964247 | H42: ='Withheld-Release'!$M$48 -> 0
B43: d | C43: Release of Withheld Amount | E43: ₹ | F43: =G43+H43 -> -497964247 | G43: =-'Withheld-Release'!R47 -> -497964247 | H43: =-'Withheld-Release'!R48 -> 0
B44: e | C44: Adjustment in Forest Royalty payments by the Contractor | E44: ₹ | F44: =G44+H44 -> -1.3773904e+08 | G44: =-'Royalty Details'!O63 -> -1.2731212e+08 | H44: =-'Royalty Details'!O64 -> -10426919
C45: Total Withhled / Release (D) = (Da+Db+Dc+Dd+De) | E45: ₹ | F45: =SUM(F40:F44) -> 4.9840973e+08 | G45: =SUM(G40:G44) -> 50774027 | H45: =SUM(H40:H44) -> 4.476357e+08
C47: Taxable Amount (D1) = ((A+B-C)/1.18) | E47: ₹ | F47: =(F24+F31-F38)/1.18 -> 1.7238709e+10 | G47: =(G24+G31-G38)/1.18 -> 1.1700895e+10 | H47: =(H24+H31-H38)/1.18 -> 5.5378137e+09
B48: E | C48: Deductions
B49: a | C49: Income Tax @ 2% on [D1/(1.01*1.02)] | E49: ₹ | F49: =$F$47/(1.01*1.02)*2% -> 3.3466723e+08 | G49: =ROUND(($G$47*2%),0) -> 234017909 | H49: =F49-G49 -> 1.0064932e+08
B50: b | C50: Forest Royalty @ 2% on [(Aa+Ab)/1.02] | E50: ₹ | F50: =ROUND((SUM(F17:F18)/1.02*2%),0) -> 337799224 | G50: =ROUND((SUM(G17:G18)/1.02*2%),0) -> 215969516 | H50: =F50-G50 -> 121829708
B51: c | C51: Income tax @ 2.5% on Forest Royalty [Eb] | E51: ₹ | F51: =ROUND(($F$50*2.5%),0) -> 8444981 | G51: =ROUND((G50*2.5%),0) -> 5399238 | H51: =F51-G51 -> 3045743
B52: d | C52: Mines and Mineral Development, Restoration and Rehabilitation Fund @ 10% on [Eb] | E52: ₹ | F52: =ROUND(($F$50*10%),0) -> 33779922 | G52: =ROUND((G50*10%),0) -> 21596952 | H52: =F52-G52 -> 12182970
B53: e | C53: District Foundation Fund Trust @ 10% on [Eb] | E53: ₹ | F53: =ROUND(($F$50*10%),0) -> 33779922 | G53: =ROUND((G50*10%),0) -> 21596952 | H53: =F53-G53 -> 12182970
B54: f | C54: State Mineral Exploration Trust @ 2% on [Eb] | E54: ₹ | F54: =G54+H54 -> 2606924.6 | G54: =8516520*2% -> 170330.4 | H54: =$H$50*2% -> 2436594.2
B55: g | C55: CGST - TDS @ 1% on [D1] | E55: ₹ | F55: =ROUND($F$47*1%,0) -> 172387092 | G55: =ROUND(($G$47*1%),0) -> 117008954 | H55: =F55-G55 -> 55378138
B56: h | C56: SGST - TDS @ 1% on [D1] | E56: ₹ | F56: =ROUND($F$47*1%,0) -> 172387092 | G56: =ROUND(($G$47*1%),0) -> 117008954 | H56: =F56-G56 -> 55378138
B57: i | C57: Labour Cess @ 1% on [A1/1.01] | E57: ₹ | F57: =ROUND($F$25/1.01*1%,0) -> 173707421 | G57: =ROUND(G24*1%,0)+2 -> 130680736 | H57: =F57-G57 -> 43026685
C58: Total Deductions (E) = (Ea+Eb+Ec+Ed+Ee+Ef+Eg+Eh+Ei) | E58: ₹ | F58: =SUM(F49:F57) -> 1.2695598e+09 | G58: =SUM(G49:G57) -> 8.6344954e+08 | H58: =SUM(H49:H57) -> 4.0611027e+08
D59: Amount Payable (F) = (A+B-C-D-E) | E59: ₹ | F59: =ROUND(F24+F31-F38-F58-F45,0) -> 18573707267 | G59: =ROUND(G24+G31-G38-G58-G45,0) -> 12892833039 | H59: =ROUND(H24+H31-H38-H58-H45,0) -> 5680874228
B60: Amount Payable (In Words) - | D60: =J65 -> Rupees Sixty Eight Crores Eight Lakhs Seventy Four Thousand Two Hundred and Twenty Eight Only
J61: =CHOOSE(IF(VALUE(RIGHT(ROUNDDOWN(H59/10000000,0),2))>9,IF(LEFT(RIGHT(ROUNDDOWN(H59/10000000,0),2),1)="1",VALUE(RIGHT(ROUNDDOWN(H59/10000000,0),1))+2,VALUE(LEFT(RIGHT(ROUNDDOWN(H59/10000000,0),2),1))+10),1),"","Ten","Eleven","Twelve","Thirteen","Fourteen","Fifteen","Sixteen","Seventeen","Eighteen","Ninteen","Twenty","Thirty","Forty","Fifty","Sixty","Seventy","Eighty","Ninety")&CHOOSE(IF(AND(VALUE(RIGHT(ROUNDDOWN(H59/10000000,0),2))<20,VALUE(RIGHT(ROUNDDOWN(H59/10000000,0),2))>10),1,VALUE(RIGHT(ROUNDDOWN(H59/10000000,0),1))+1),""," One"," Two"," Three"," Four"," Five"," Six"," Seven"," Eight"," Nine")& IF(VALUE(RIGHT(ROUNDDOWN(H59/10000000,0),2))>0," Crores ","") -> Sixty Eight Crores
J62: =CHOOSE(IF(VALUE(RIGHT(ROUNDDOWN(H59/100000,0),2))>9,IF(LEFT(RIGHT(ROUNDDOWN(H59/100000,0),2),1)="1",VALUE(RIGHT(ROUNDDOWN(H59/100000,0),1))+2,VALUE(LEFT(RIGHT(ROUNDDOWN(H59/100000,0),2),1))+10),1),"","Ten","Eleven","Twelve","Thirteen","Fourteen","Fifteen","Sixteen","Seventeen","Eighteen","Ninteen","Twenty","Thirty","Forty","Fifty","Sixty","Seventy","Eighty","Ninety")&CHOOSE(IF(AND(VALUE(RIGHT(ROUNDDOWN(H59/100000,0),2))<20,VALUE(RIGHT(ROUNDDOWN(H59/100000,0),2))>10),1,VALUE(RIGHT(ROUNDDOWN(H59/100000,0),1))+1),""," One"," Two"," Three"," Four"," Five"," Six"," Seven"," Eight"," Nine")& IF(VALUE(RIGHT(ROUNDDOWN(H59/100000,0),2))>0," Lakhs ","") -> Eight Lakhs
J63: =CHOOSE(IF(VALUE(RIGHT(ROUNDDOWN(H59/1000,0),2))>9,IF(LEFT(RIGHT(ROUNDDOWN(H59/1000,0),2),1)="1",VALUE(RIGHT(ROUNDDOWN(H59/1000,0),1))+2,VALUE(LEFT(RIGHT(ROUNDDOWN(H59/1000,0),2),1))+10),1),"","Ten","Eleven","Twelve","Thirteen","Fourteen","Fifteen","Sixteen","Seventeen","Eighteen","Ninteen","Twenty","Thirty","Forty","Fifty","Sixty","Seventy","Eighty","Ninety")&CHOOSE(IF(AND(VALUE(RIGHT(ROUNDDOWN(H59/1000,0),2))<20,VALUE(RIGHT(ROUNDDOWN(H59/1000,0),2))>10),1,VALUE(RIGHT(ROUNDDOWN(H59/1000,0),1))+1),""," One"," Two"," Three"," Four"," Five"," Six"," Seven"," Eight"," Nine")& IF(VALUE(RIGHT(ROUNDDOWN(H59/1000,0),2))>0," Thousand ","") -> Seventy Four Thousand
J64: =CHOOSE(VALUE(RIGHT(ROUNDDOWN(H59/100,0),1))+1,"","One","Two","Three","Four","Five","Six","Seven","Eight","Nine")& IF(VALUE(RIGHT(ROUNDDOWN(H59/100,0),1))>0," Hundred and ","")&CHOOSE(IF(VALUE(RIGHT(ROUNDDOWN(H59,0),2))>9,IF(LEFT(RIGHT(ROUNDDOWN(H59,0),2),1)="1",VALUE(RIGHT(ROUNDDOWN(H59,0),1))+2,VALUE(LEFT(RIGHT(ROUNDDOWN(H59,0),2),1))+10),1),"","Ten","Eleven","Twelve","Thirteen","Fourteen","Fifteen","Sixteen","Seventeen","Eighteen","Ninteen","Twenty","Thirty","Forty","Fifty","Sixty","Seventy","Eighty","Ninety")&CHOOSE(IF(AND(VALUE(RIGHT(ROUNDDOWN(H59,0),2))<20,VALUE(RIGHT(ROUNDDOWN(H59,0),2))>10),1,VALUE(RIGHT(ROUNDDOWN(H59,0),1))+1),""," One"," Two"," Three"," Four"," Five"," Six"," Seven"," Eight"," Nine") -> Two Hundred and Twenty Eight
J65: ="Rupees " &J61&J62&J63&J64&" Only" -> Rupees Sixty Eight Crores Eight Lakhs Seventy Four Thousand Two Hundred and Twenty Eight Only

Sheet Abs. - PMC
B2: INTERIM PAYMENT CERTIFICATION
B3: ABSTRACT SHEET
B4: Interim Payment Certificate No. : | D4: IPC - 15 | G4: Bill date : | H4: 45799
B5: Type of Work : | D5: Main Works and Price Adjustment
B6: Period of bill : | D6: ='Abs. - L&T'!D6 -> 1st Jul'26 to 31st Jul'26
B7: EPC Contractor : | D7: Larsen and Toubro Limited
B8: Address: | D8: L&T Construction, Majirgaon Palashbari - Sualkuchi Bridge Project, Dag No. 268 & 269, Patta No. 43 & 168, Revenue Village - Santala, Revenue Circle - Palashbari, Kamrup District, Assam - 781125.
B9: Employer : | D9: The Chief Engineer (EAP), Public Works Roads Department (PWRD), Assam
B10: Employer's Representative : | D10: Rodic Consultants Private Limited in JV with Intercontinental Consultants and Technocrats Private Limited
B11: LOA Ref. No. : | D11: CE/EAP/ABP-II/EPC/OCB/2023/35 | G11: Contract Value (INR) : | H11: =26885400000 -> 26885400000
B12: Work Order No : | D12: Contract Agreement signed on 01-Mar-24 | G12: Financial Progress: | H12: =F17/H11 -> 0.75606615
B13: Name of Work : | D13: Construction of 4-lane Extradosed PSC Bridge over river Brahmaputra connecting Palashbari and Sualkuchi including Viaduct, Approaches and River Training works etc on EPC mode
B14: S.No. | C14: Description | E14: Currency | F14: Amount
F15: Cumulative Bill | G15: Up to Previous Bill | H15: This Bill
B16: A | C16: Work Done
B17: a | C17: Amount for the works executed under Sub-Clause 14.3 of the General Conditions | E17: =_xlfn.UNICHAR(8377) -> ₹ | F17: ='Detailed breakup'!N531 -> 20327140948 | G17: ='Detailed breakup'!P531 -> 12995429147 | H17: =F17-G17 -> 7331711801
B18: b | C18: Amount for the Provisional Sum under Sub-Clause 13.4 of the General Conditions | E18: =_xlfn.UNICHAR(8377) -> ₹ | F18: ='Detailed breakup'!N532 -> 1616348 | G18: ='Detailed breakup'!P532 -> 1616348 | H18: ='Detailed breakup'!R532 -> 0
B19: c | C19: Amount reflecting Changes in Cost under Sub-Clause 13.7 of the General Conditions | E19: =_xlfn.UNICHAR(8377) -> ₹ | F19: ='Price Adj.'!V75 -> 373693103 | G19: ='Price Adj.'!V76 -> 71027937 | H19: =F19-G19 -> 302665166
B20: d | C20: Amount of Variation Order executed under Sub-Clause 13.3 of the General Conditions | E20: =_xlfn.UNICHAR(8377) -> ₹ | F20: 0 | G20: 0 | H20: =F20-G20 -> 0
B21: e | C21: Amount reflecting Change in Law under Sub-Clause 13.6 of the General Conditions | E21: =_xlfn.UNICHAR(8377) -> ₹ | F21: 0 | G21: 0 | H21: =F21-G21 -> 0
C22: Total Work Done (A) = (Aa+Ab+Ac+Ad+Ae) | E22: =_xlfn.UNICHAR(8377) -> ₹ | F22: =(SUM(F17:F21)) -> 20702450399 | G22: =(SUM(G17:G21)) -> 13068073432 | H22: =(SUM(H17:H21)) -> 7634376967
C23: Total Work Done (Excl. of Taxes) (A1) = (A/1.18) | E23: =_xlfn.UNICHAR(8377) -> ₹ | F23: =(F22/1.18) -> 1.7544449e+10 | G23: =(G22/1.18) -> 1.1074639e+10 | H23: =(H22/1.18) -> 6.469811e+09
B24: B | C24: Advances
B25: a | C25: Mobilization Advance under Sub-Clause 14.2 of General Condidtions - 1st Installment | E25: ₹ | F25: =G25+H25 -> 2688540000 | G25: =H11*10% -> 2688540000 | H25: 0
B26: b | C26: Mobilization Advance under Sub-Clause 14.2 of General Condidtions - 2nd Installment | E26: ₹ | F26: =H26+G26 -> 0 | G26: 0 | H26: 0
C27: Total Advances (B) = (Ba+Bb) | E27: ₹ | F27: =(SUM(F25:F26)) -> 2688540000 | G27: =(SUM(G25:G26)) -> 2688540000 | H27: =(SUM(H25:H26)) -> 0
C28: Gross Amount due including Advances (B1) = (A+B) | E28: ₹ | F28: =(F22+F27) -> 23390990399 | G28: =(G22+G27) -> 15756613432 | H28: =(H22+H27) -> 7634376967
C29: Gross Amount (Excl. of Taxes) (B2) = (B1/1.18) | E29: ₹ | F29: =(F28/1.18) -> 1.9822873e+10 | G29: =(G28/1.18) -> 1.3353062e+10 | H29: =(H28/1.18) -> 6.469811e+09
B30: C | C30: Recoveries
B31: a | C31: Mobilization Advance under Sub-Clause 14.2 of General Condidtions @ 15% on [A] | E31: ₹ | F31: =(G31+H31) -> 3.1053676e+09 | G31: =(G22*15%) -> 1.960211e+09 | H31: =(H22*15%) -> 1.1451565e+09
B32: b | C32: Retention Amount @ 6% upto 5% of Contract Value on [A] | E32: ₹ | F32: =(G32+H32) -> 1.242147e+09 | G32: =(G22*6%) -> 7.8408441e+08 | H32: =(H22*6%) -> 4.5806262e+08
C33: Total Recoveries (C) = (Ca+Cb) | E33: ₹ | F33: =SUM(F31:F32) -> 4.3475146e+09 | G33: =SUM(G31:G32) -> 2.7442954e+09 | H33: =SUM(H31:H32) -> 1.6032192e+09
C34: Amount due before Taxes (C1) = (B1-C) | E34: ₹ | F34: =F28-F33 -> 1.9043476e+10 | G34: =G28-G33 -> 1.3012318e+10 | H34: =H28-H33 -> 6.0311578e+09
B35: D | C35: Withheld
B36: a | C36: Withheld Amount | E36: ₹ | F36: =G36+H36 -> 0 | G36: 0 | H36: 0
B37: b | C37: Release of Withheld Amount | E37: ₹ | F37: =G37+H37 -> 0 | G37: 0 | H37: 0
C38: Total Advances (D) = (Da+Db) | E38: ₹ | F38: =SUM(F36:F37) -> 0 | G38: =SUM(G36:G37) -> 0 | H38: =SUM(H36:H37) -> 0
C39: Taxable Amount (D1) = ((A-Ca)/1.18) | E39: ₹ | F39: =((F22-F31)/1.18) -> 1.4912782e+10 | G39: =((G22-G31)/1.18) -> 9.4134427e+09 | H39: =((H22-H31)/1.18) -> 5.4993393e+09
B40: E | C40: Deductions
B41: a | C41: Income tax @ 2% on [(B+(A-Ca))/1.18] | E41: ₹ | F41: =((F27+F22-F31)/1.18*2%) -> 3.4382412e+08 | G41: 64838315 | H41: =F41-G41 -> 2.789858e+08
B42: b | C42: Forest Royalty @ 2% on [A/1.18/1.02] | E42: ₹ | F42: =((F22/1.18/1.02)*2%) -> 3.4400881e+08 | G42: 22225883 | H42: =F42-G42 -> 3.2178293e+08
B43: c | C43: Income tax @ 2.5% on Forest Royalty [Eb] | E43: ₹ | F43: =(F42*2.5%) -> 8600220.3 | G43: 449089 | H43: =F43-G43 -> 8151131.3
B44: d | C44: Mines and Mineral Development, Restoration and Rehabilitation Fund @ 10% on [Eb] | E44: ₹ | F44: =(F42*10%) -> 34400881 | G44: 1796354 | H44: =F44-G44 -> 32604527
B45: e | C45: District Foundation Fund Trust @ 10% on [Eb] | E45: ₹ | F45: =(F42*10%) -> 34400881 | G45: 1796354 | H45: =F45-G45 -> 32604527
B46: f | C46: CGST @ 1% on [(B+(A-Ca))/1.18] | E46: ₹ | F46: =((F27+F22-F31)/1.18*1%) -> 1.7191206e+08 | G46: 19179316 | H46: =F46-G46 -> 1.5273274e+08
B47: g | C47: SGST @ 1% on [(B+(A-Ca))/1.18] | E47: ₹ | F47: =((F27+F22-F31)/1.18*1%) -> 1.7191206e+08 | G47: 19179316 | H47: =F47-G47 -> 1.5273274e+08
B48: h | C48: Labour Cess @1% on [A1] | E48: ₹ | F48: =(F23*1%) -> 1.7544449e+08 | G48: 10810459 | H48: =F48-G48 -> 1.6463404e+08
C49: Total Deductions (E) = (Ea+Eb+Ec+Ed+Ee+Ef+Eg+Eh) | E49: ₹ | F49: =SUM(F41:F48) -> 1.2845035e+09 | G49: =SUM(G41:G48) -> 140275086 | H49: =SUM(H41:H48) -> 1.1442284e+09
D50: Amount Payable (F) = (C1-D-E) | E50: ₹ | F50: =(F34-F38-F49) -> 1.7758972e+10 | G50: =(G34-G38-G49) -> 1.2872043e+10 | H50: =(H34-H38-H49) -> 4.8869294e+09
B51: Amount Payable (In Words) - Rupees Sixteen Crores Forty Lakhs Eight Thousand Three Hundred and Fourteen Only

Sheet Abs. - PMC (For Print)
B2: INTERIM PAYMENT CERTIFICATION
B3: ABSTRACT SHEET
B4: Interim Payment Certificate No. : | D4: IPC - 34 | G4: Bill date : | H4: =TODAY()-1 -> 46285
B5: Type of Work : | D5: Main Works & Price Adjustment
B6: Period of bill : | D6: 1st Jul'26 to 31st Jul'26
B7: EPC Contractor : | D7: Larsen and Toubro Limited
B8: Address: | D8: L&T Construction, Majirgaon Palashbari - Sualkuchi Bridge Project, Dag No. 268 & 269, Patta No. 43 & 168, Revenue Village - Santala, Revenue Circle - Palashbari, Kamrup District, Assam - 781125.
B9: Employer : | D9: The Chief Engineer (EAP), Public Works Roads Department (PWRD), Assam
B10: Employer's Representative : | D10: Rodic Consultants Private Limited in JV with Intercontinental Consultants and Technocrats Private Limited
B11: LOA Ref. No. : | D11: CE/EAP/ABP-II/EPC/OCB/2023/35 | G11: Contract Value (INR) : | H11: =26885400000 -> 26885400000
B12: Work Order No : | D12: Contract Agreement signed on 01-Mar-24 | G12: Financial Progress: | H12: ='Breakup-Summary'!$F$23 -> 0.75762732
B13: Name of Work : | D13: Construction of 4-lane Extradosed PSC Bridge over river Brahmaputra connecting Palashbari and Sualkuchi including Viaduct, Approaches and River Training works etc on EPC mode
B14: S.No. | C14: Description | E14: Currency | F14: Amount
F15: Cumulative Bill | G15: Up to Previous Bill | H15: This Bill
B16: A | C16: Work Done
B17: a | C17: Amount for the works executed under Sub-Clause 14.3 of the General Conditions | E17: ₹ | F17: ='Detailed breakup'!$N$531 -> 20327140948 | G17: ='Detailed breakup'!$P$531 -> 12995429147 | H17: =F17-G17 -> 7331711801
B18: b | C18: Amount for the Provisional Sum under Sub-Clause 13.4 of the General Conditions | E18: ₹ | F18: ='Detailed breakup'!N532 -> 1616348 | G18: ='Detailed breakup'!P532 -> 1616348 | H18: ='Detailed breakup'!R532 -> 0
B19: c | C19: Amount reflecting Changes in Cost under Sub-Clause 13.7 of the General Conditions | E19: ₹ | F19: ='Price Adj.'!$V$75 -> 373693103 | G19: ='Price Adj.'!$V$76 -> 71027937 | H19: =F19-G19 -> 302665166
B20: d | C20: Amount of Variation Order executed under Sub-Clause 13.3 of the General Conditions | E20: ₹ | F20: 0 | G20: 0 | H20: =F20-G20 -> 0
B21: e | C21: Amount reflecting Change in Law under Sub-Clause 13.6 of the General Conditions | E21: ₹ | F21: 0 | G21: 0 | H21: =F21-G21 -> 0
C22: Total Work Done (A) = (Aa+Ab+Ac+Ad+Ae) | E22: ₹ | F22: =(SUM(F17:F21)) -> 20702450399 | G22: =(SUM(G17:G21)) -> 13068073432 | H22: =(SUM(H17:H21)) -> 7634376967
B23: B | C23: Advances / Recovery
B24: a | C24: Mobilization Advance under Sub-Clause 14.2 of General Conditions - 1st Installment | E24: ₹ | F24: =G24+H24 -> 1344270000 | G24: =H11*5% -> 1344270000 | H24: 0
B25: b | C25: Mobilization Advance under Sub-Clause 14.2 of General Conditions - 2nd Installment | E25: ₹ | F25: =G25+H25 -> 1344270000 | G25: =H11*5% -> 1344270000 | H25: 0
B26: c | C26: Recovery of Mob. Advance under Sub-Clause 14.2 of GC @ 15% on [Aa+Ab] | E26: ₹ | F26: =ROUND((F17+F18)*15%,0) -> 3049313594 | G26: =ROUND((G17+G18)*15%,0) -> 1949556824 | H26: =F26-G26 -> 1099756770
C27: Total Advances (B) = (Ba+Bb-Bc) | E27: ₹ | F27: =F24+F25-F26 -> -360773594 | G27: =G24+G25-G26 -> 738983176 | H27: =H24+H25-H26 -> -1099756770
C28: Gross Amount due including Advances (B1) = (A+B) | E28: ₹ | F28: =(F22+F27) -> 20341676805 | G28: =(G22+G27) -> 13807056608 | H28: =(H22+H27) -> 6534620197
C30: Taxable Amount (B2) = ((A+B)/1.18) | E30: ₹ | F30: =ROUND((F22+F27)/1.18,0) -> 17238709157 | G30: =ROUND((G22+G27)/1.18,0) -> 11700895431 | H30: =ROUND((H22+H27)/1.18,0) -> 5537813726
B31: C | C31: Recovery / Release
B32: a | C32: Recovery of Retention Amount @ 6% upto 5% of Contract Value on [A] | E32: ₹ | F32: =ROUND((F22)*6%,0) -> 1242147024 | G32: =ROUND((G22*6%),0) -> 784084406 | H32: =F32-G32 -> 458062618
B33: b | C33: Release of Retention Amount against Bank Guarantee | E33: ₹ | F33: =-'Retention Release'!$G$38 -> -605998256 | G33: =-'Retention Release'!$G$39 -> -605998256 | H33: =F33-G33 -> 0
C34: Total Recovery (C) = (Ca+Cb) | E34: ₹ | F34: =SUM(F32:F33) -> 636148768 | G34: =SUM(G32:G33) -> 178086150 | H34: =SUM(H32:H33) -> 458062618
C35: Amount due before Taxes (C1) = (B1-C) | E35: ₹ | F35: =F28-F34 -> 19705528037 | G35: =G28-G34 -> 13628970458 | H35: =H28-H34 -> 6076557579
B36: D | C36: Withheld / Release
B37: a | C37: Withheld Amount | E37: ₹ | F37: =ROUND('Withheld-Release'!$M$46,0) -> 497964247 | G37: =ROUND('Withheld-Release'!$M$47,0) -> 497964247 | H37: =F37-G37 -> 0
B38: b | C38: Release of Withhled Amount | E38: ₹ | F38: =-ROUND('Withheld-Release'!$R$46,0) -> -497964247 | G38: =-ROUND('Withheld-Release'!R47,0) -> -497964247 | H38: =F38-G38 -> 0
C39: Total Withheld (D) = (Da+Db) | E39: ₹ | F39: =SUM(F37:F38) -> 0 | G39: =SUM(G37:G38) -> 0 | H39: =SUM(H37:H38) -> 0
C40: Amount due before Taxes after withheld (D1) = (C1-D) | E40: ₹ | F40: =F35-F39 -> 19705528037 | G40: =G35-G39 -> 13628970458 | H40: =H35-H39 -> 6076557579
B41: E | C41: Deductions
B42: a | C42: TDS - Income tax @ 2% on [B2] | E42: ₹ | J42: =ROUND((F30*2%),0) -> 344774183 | K42: 227561965 | L42: =ROUND((H30*2%),0) -> 110756275 | N42: =O42+P42 -> 338318240 | O42: =K42 -> 227561965 | P42: =L42 -> 110756275
B43: b | C43: Forest Royalty @ 2% on [(Aa+Ab)/1.18/1.02] | E43: ₹ | J43: =(F17+F18)*2%/(1.18*1.02)-R43 -> 2.3201249e+08 | K43: 104591554 | L43: =J43-K43 -> 1.2742094e+08 | N43: =O43+P43 -> 2.2462135e+08 | O43: =K43 -> 104591554 | P43: =L43-Q43 -> 1.2002979e+08 | Q43: ='Royalty Details'!G72 -> 7391143.5 | R43: ='Summary-Royalty'!T12 -> 1.0578673e+08 | S43: =J43+R43 -> 3.3779922e+08
B44: c | C44: TCS - Income tax @ 2.5% on Forest Royalty [Eb] | E44: ₹ | J44: =((F17+F18)*2%/(1.18*1.02))*2.5% -> 8444980.6 | K44: 5247793 | L44: =J44-K44 -> 3197187.6 | N44: =O44+P44 -> 8444980.6 | O44: =K44 -> 5247793 | P44: =L44 -> 3197187.6 | R44: ='Summary-Royalty'!T13 -> 281240.33 | S44: =J44+R44 -> 8726220.9
B45: d | C45: Mines and Mineral Development, Restoration and Rehabilitation Fund @ 10% on [Eb] | E45: ₹ | J45: =(((F17+F18)*2%/(1.18*1.02)))*10%-R45 -> 23206613 | K45: 10459157 | L45: =J45-K45 -> 12747456 | N45: =O45+P45 -> 22462136 | O45: =K45 -> 10459157 | P45: =ROUND(P43*0.1,0) -> 12002979 | R45: =('Summary-Royalty'!$T$14-$R$47)/2 -> 10573309 | S45: =J45+R45 -> 33779922
B46: e | C46: District Foundation Fund Trust @ 10% on [Eb] | E46: ₹ | J46: =(((F17+F18)*2%/(1.18*1.02)))*10%-R46 -> 23206613 | K46: 10459157 | L46: =J46-K46 -> 12747456 | N46: =O46+P46 -> 22462136 | O46: =K46 -> 10459157 | P46: =P45 -> 12002979 | R46: =('Summary-Royalty'!$T$14-$R$47)/2 -> 10573309 | S46: =J46+R46 -> 33779922
B47: f | C47: State Mineral Exploration Trust @ 2% on [Eb] | E47: ₹ | J47: =(F17+F18-12134718776-1244255)*2%*2%/(1.18*1.02)-R47 -> 2625233.1 | K47: 97530 | L47: =J47-K47 -> 2527703.1 | N47: =O47+P47 -> 2498126 | O47: =K47 -> 97530 | P47: =ROUND(($P$43*2%),0) -> 2400596 | R47: 97530 | S47: =J47+R47 -> 2722763.1
B48: g | C48: TDS - CGST @ 1% on [B2] | E48: ₹ | J48: =K48+L48 -> 169159119 | K48: 113780982 | L48: =ROUND((H30*1%),0) -> 55378137 | N48: =O48+P48 -> 169159119 | O48: =K48 -> 113780982 | P48: =L48 -> 55378137
B49: h | C49: TDS - SGST @ 1% on [B2] | E49: ₹ | J49: =K49+L49 -> 169159119 | K49: 113780982 | L49: =ROUND((H30*1%),0) -> 55378137 | N49: =O49+P49 -> 169159119 | O49: =K49 -> 113780982 | P49: =L49 -> 55378137 | R49: =$R$43*10% -> 10578673
B50: i | C50: Labour Cess @1% on [A] | E50: ₹ | J50: =K50+L50 -> 202668665 | K50: 126324895 | L50: =ROUND(($H$22*1%),0) -> 76343770 | N50: =O50+P50 -> 202668665 | O50: =K50 -> 126324895 | P50: =L50 -> 76343770 | R50: =$R$43*10% -> 10578673
C51: Total Deductions (E) = (Ea+Eb+Ec+Ed+Ee+Ef+Eg+Eh+Ei) | E51: ₹ | J51: =SUM(J42:J50) -> 1.175257e+09 | K51: =SUM(K42:K50) -> 712304015 | L51: =SUM(L42:L50) -> 4.5649706e+08 | N51: =SUM(N42:N50) -> 1.1597939e+09 | O51: =SUM(O42:O50) -> 712304015 | P51: =SUM(P42:P50) -> 4.4748985e+08
D52: Amount Payable (F) = (C1-D-E) | E52: ₹ | J52: =F35-F39-J51 -> 1.8530271e+10 | K52: =G35-G39-K51 -> 12916666443 | L52: =H35-H39-L51 -> 5.6200605e+09 | N52: =F40-N51 -> 1.8545734e+10 | O52: =G40-O51 -> 12916666443 | P52: =H40-P51 -> 5.6290677e+09
B53: Amount Payable (In Words) -
N55: =O55+P55 -> 338318240 | O55: 227561965 | P55: =P42 -> 110756275
N56: =O56+P56 -> 225721262 | O56: 104591554 | P56: =ROUND((H17+H18)*2%/(1.18*1.02),0)-700000 -> 121129708
N57: =O57+P57 -> 8293535.7 | O57: 5247793 | P57: =ROUND((H17+H18)*2%/(1.18*1.02),0)*2.5% -> 3045742.7
N58: =O58+P58 -> 22572128 | O58: 10459157 | P58: =ROUND(P56*0.1,0) -> 12112971
N59: =O59+P59 -> 22572128 | O59: 10459157 | P59: =P58 -> 12112971
N60: =O60+P60 -> 2520124 | O60: 97530 | P60: =ROUND(($P$56*2%),0) -> 2422594
N61: =O61+P61 -> 1.6915912e+08 | O61: 113780982 | P61: =H30*1% -> 55378137
N62: =O62+P62 -> 1.6915912e+08 | O62: 113780982 | P62: =P61 -> 55378137
N63: =O63+P63 -> 2.0266866e+08 | O63: 126324895 | P63: =H22*1% -> 76343770
N64: =SUM(N55:N63) -> 1.1609843e+09 | O64: =SUM(O55:O63) -> 712304015 | P64: =SUM(P55:P63) -> 4.4868031e+08
N65: =F40-N64 -> 1.8544544e+10 | O65: =G40-O64 -> 12916666443 | P65: =H40-P64 -> 5.6278773e+09

Sheet Breakup-Summary
C2: Construction of 4-lane Extra-dosed PSC Bridge over river Brahmaputra connecting Palashbari and Sualkuchi including Viaduct, Approaches and River Training works etc on EPC mode
B3: General Conditions of Contract - Clause 14.4 - Summary - Schedule of Payments
B4: Schedule No | C4: Description | D4: Schedule Cost (% of the Contract Price) | F4: Cumulative Bill | H4: Up to Previous Bill | J4: This Bill (INR)
D5: Weightage % | E5: Amount (INR) | F5: Weightage % | G5: Amount (Rs.) | H5: Weightage % | I5: Amount (Rs.) | J5: Weightage % | K5: Amount (Rs.)
B7: Schedule 1 | C7: Preliminaries & General Items | D7: 0.025 | E7: =D7*(26885400000-55400000) -> 670750000 | F7: =G7/$E7*$D7 -> 0.019109844 | G7: ='Detailed breakup'!N119 -> 512717121 | H7: =I7/$E7*$D7 -> 0.019109844 | I7: ='Detailed breakup'!P119 -> 512717121 | J7: =K7/$E7*$D7 -> 0 | K7: ='Detailed breakup'!R119 -> 0
B9: Schedule 2 | C9: Validation of Survey Data, Investigation, Design and As-Built Drawings | D9: 0.03 | E9: =D9*(26885400000-55400000) -> 804900000 | F9: =G9/$E9*$D9 -> 0.027275441 | G9: ='Detailed breakup'!N275 -> 731800089 | H9: =I9/$E9*$D9 -> 0.027244691 | I9: ='Detailed breakup'!P275 -> 730975066 | J9: =K9/$E9*$D9 -> 3.0750019e-05 | K9: ='Detailed breakup'!R275 -> 825023
B11: Schedule 3 | C11: Enabling Works for Main Works | D11: 0.045 | E11: =D11*(26885400000-55400000) -> 1207350000 | F11: =G11/$E11*$D11 -> 0.04149 | G11: ='Detailed breakup'!N313 -> 1113176703 | H11: =I11/$E11*$D11 -> 0.04149 | I11: ='Detailed breakup'!P313 -> 1113176703 | J11: =K11/$E11*$D11 -> 0 | K11: ='Detailed breakup'!R313 -> 0
B13: Schedule 4 | C13: Main Extradosed Bridge Works | D13: 0.67 | E13: =D13*(26885400000-55400000) -> 17976100000 | F13: =G13/$E13*$D13 -> 0.53041941 | G13: ='Detailed breakup'!N376 -> 14231152805 | H13: =I13/$E13*$D13 -> 0.26078233 | I13: ='Detailed breakup'!P376 -> 6996789931 | J13: =K13/$E13*$D13 -> 0.26963708 | K13: ='Detailed breakup'!R376 -> 7234362874
B15: Schedule 5 | C15: Wetland and Approach Viaduct Works | D15: 0.145 | E15: =D15*(26885400000-55400000) -> 3.89035e+09 | F15: =G15/$E15*$D15 -> 0.10913714 | G15: ='Detailed breakup'!N459 -> 2928149367 | H15: =I15/$E15*$D15 -> 0.10565219 | I15: ='Detailed breakup'!P459 -> 2834648310 | J15: =K15/$E15*$D15 -> 0.0034849444 | K15: ='Detailed breakup'!R459 -> 93501057
B17: Schedule 6 | C17: Underpass Works | D17: 0.025 | E17: =D17*(26885400000-55400000) -> 670750000 | F17: =G17/$E17*$D17 -> 0.022104 | G17: ='Detailed breakup'!N491 -> 593050320 | H17: =I17/$E17*$D17 -> 0.022104 | I17: ='Detailed breakup'!P491 -> 593050320 | J17: =K17/$E17*$D17 -> 0 | K17: ='Detailed breakup'!R491 -> 0
B19: Schedule 7 | C19: Approach road Works | D19: 0.06 | E19: =D19*(26885400000-55400000) -> 1609800000 | F19: =G19/$E19*$D19 -> 0.008091485 | G19: ='Detailed breakup'!N517 -> 217094543 | H19: =I19/$E19*$D19 -> 0.0079788183 | I19: ='Detailed breakup'!P517 -> 214071696 | J19: =K19/$E19*$D19 -> 0.00011266668 | K19: ='Detailed breakup'!R517 -> 3022847
B21: Schedule 8 | C21: Provisional Sum | E21: =55400000 -> 55400000 | G21: ='Detailed breakup'!N529 -> 1616348 | I21: ='Detailed breakup'!P529 -> 1616348 | K21: ='Detailed breakup'!R529 -> 0
C23: Total | D23: =SUM(D6:D22) -> 1 | E23: =SUM(E7:E22) -> 26885400000 | F23: =SUM(F7:F21) -> 0.75762732 | G23: =SUM(G7:G22) -> 20328757296 | H23: =SUM(H7:H22) -> 0.48436188 | I23: =SUM(I7:I22) -> 12997045495 | J23: =SUM(J7:J21) -> 0.27326544 | K23: =SUM(K7:K22) -> 7331711801 | L23: 339313902 | M23: =K23-L23 -> 6992397899
E25: =E21/10^7 -> 5.54
K26: =K23*0.73 -> 5.3521496e+09
K27: =SUM('Royalty Details'!G55:J58) -> 7392224
K28: 11700000
K30: =SUM(K26:K29) -> 5.3712418e+09
D73: PL1 - Piercap - WV1
D74: PL2 - Piercap - WV1
D75: PR3 - Piercap - WV1
D76: PR1 - Piercap - WV1
D77: PL3 - Piercap - WV1
D78: PR2 - Piercap - WV1
D79: PL0 - Piercap - WV1
D80: PR0 - Piercap - WV1

Sheet Detailed breakup
C2: Construction of 4-lane Extra-dosed PSC Bridge over river Brahmaputra connecting Palashbari and Sualkuchi including Viaduct, Approaches and River Training works etc on EPC mode
B3: General Conditions of Contract - Clause 14.4 - Schedule of Payments
O4: ='Abs. - PMC'!B6 -> Period of bill : | Q4: ='Abs. - PMC'!D6 -> 1st Jul'26 to 31st Jul'26
B5: Schedule No | C5: Description | D5: Schedule Cost (% of the Contract Price) | F5: Item No | G5: Item Description | H5: UOM | I5: Percentage | J5: Tentative Scope | K5: Amount (INR) | L5: Amount payable per Unit (INR) | M5: Cumulative Bill | O5: Upto Previous Bill | Q5: This Bill | T5: Measurement Book
D6: Weightage % | E6: Amount (INR) | M6: Quantity | N6: Amount (INR) | O6: Quantity | P6: Amount (INR) | Q6: Quantity | R6: Amount (INR) | T6: Page | U6: No
B8: Schedule 1 | C8: Preliminaries & General Items | D8: 0.025 | E8: =D8*(26885400000-55400000) -> 670750000 | F8: 101 | G8: Provision (construction) of office facilities for the Employer | H8: LS | I8: 0.305 | K8: =I8*$E$8 -> 204578750
F9: a | G9: Completion of Foundation | H9: Nos. | I9: 0.2 | J9: 2 | K9: =I9*$K$8 -> 40915750 | L9: =IFERROR(K9/J9,0) -> 20457875 | M9: ='Schedule 1'!F14 -> 2 | N9: =ROUND(L9*M9,0) -> 40915750 | O9: ='Schedule 1'!F15 -> 2 | P9: 40915750 | Q9: =M9-O9 -> 0 | R9: =N9-P9 -> 0 | S9: =J9-M9 -> 0
F10: b | G10: Completion of Plinth | H10: Nos. | I10: 0.18 | J10: 2 | K10: =I10*$K$8 -> 36824175 | L10: =IFERROR(K10/J10,0) -> 18412088 | M10: ='Schedule 1'!F21 -> 2 | N10: =(L10*M10) -> 36824175 | O10: ='Schedule 1'!F22 -> 2 | P10: 36824175 | Q10: =M10-O10 -> 0 | R10: =N10-P10 -> 0 | S10: =J10-M10 -> 0
F11: c | G11: Completion of Walls | H11: Nos. | I11: 0.15 | J11: 2 | K11: =I11*$K$8 -> 30686812 | L11: =IFERROR(K11/J11,0) -> 15343406 | M11: ='Schedule 1'!F28 -> 2 | N11: =ROUND(L11*M11,0) -> 30686813 | O11: ='Schedule 1'!F29 -> 2 | P11: 30686813 | Q11: =M11-O11 -> 0 | R11: =N11-P11 -> 0 | S11: =J11-M11 -> 0
F12: d | G12: Completion of Roofs | H12: Nos. | I12: 0.15 | J12: 2 | K12: =I12*$K$8 -> 30686812 | L12: =IFERROR(K12/J12,0) -> 15343406 | M12: ='Schedule 1'!F35 -> 2 | N12: =ROUND(L12*M12,0) -> 30686813 | O12: ='Schedule 1'!F36 -> 2 | P12: 30686813 | Q12: =M12-O12 -> 0 | R12: =N12-P12 -> 0 | S12: =J12-M12 -> 0
F13: e | G13: Completion of Flooring | H13: Nos. | I13: 0.18 | J13: 2 | K13: =I13*$K$8 -> 36824175 | L13: =IFERROR(K13/J13,0) -> 18412088 | M13: ='Schedule 1'!F42 -> 2 | N13: =(L13*M13) -> 36824175 | O13: ='Schedule 1'!F43 -> 2 | P13: 36824175 | Q13: =M13-O13 -> 0 | R13: =N13-P13 -> 0 | S13: =J13-M13 -> 0
F14: f | G14: Completion of Finishing Works | S14: =J14-M14 -> 0
F15: i | G15: Electrical and Sanitary Works | H15: Nos. | I15: 0.1 | J15: 2 | K15: =I15*$K$8 -> 20457875 | L15: =IFERROR(K15/J15,0) -> 10228938 | M15: ='Schedule 1'!F50 -> 2 | N15: =ROUND(L15*M15,0) -> 20457875 | O15: ='Schedule 1'!F51 -> 2 | P15: 20457875 | Q15: =M15-O15 -> 0 | R15: =N15-P15 -> 0 | S15: =J15-M15 -> 0
F16: ii | G16: Office Furniture | S16: =J16-M16 -> 0
F17: 1 | G17: Executive Office Desk | H17: Nos. | I17: 0.0025 | J17: 8 | K17: =I17*$K$8 -> 511446.88 | L17: =IFERROR(K17/J17,0) -> 63930.859 | M17: ='Schedule 1'!F57 -> 8 | N17: =ROUND(L17*M17,0) -> 511447 | O17: ='Schedule 1'!F58 -> 8 | P17: 511447 | Q17: =M17-O17 -> 0 | R17: =N17-P17 -> 0 | S17: =J17-M17 -> 0
F18: 2 | G18: Executive Chairs | H18: Nos. | I18: 0.0025 | J18: 8 | K18: =I18*$K$8 -> 511446.88 | L18: =IFERROR(K18/J18,0) -> 63930.859 | M18: ='Schedule 1'!F64 -> 8 | N18: =ROUND(L18*M18,0) -> 511447 | O18: ='Schedule 1'!F65 -> 8 | P18: 511447 | Q18: =M18-O18 -> 0 | R18: =N18-P18 -> 0 | S18: =J18-M18 -> 0
F19: 3 | G19: Visitor Chairs | H19: Nos. | I19: 0.0015 | J19: 20 | K19: =I19*$K$8 -> 306868.12 | L19: =IFERROR(K19/J19,0) -> 15343.406 | M19: ='Schedule 1'!F68 -> 20 | N19: =ROUND(L19*M19,0) -> 306868 | O19: ='Schedule 1'!F71 -> 20 | P19: 306868 | Q19: =M19-O19 -> 0 | R19: =N19-P19 -> 0 | S19: =J19-M19 -> 0
F20: 4 | G20: Conference Table | H20: Nos. | I20: 0.005 | J20: 2 | K20: =I20*$K$8 -> 1022893.8 | L20: =IFERROR(K20/J20,0) -> 511446.88 | M20: ='Schedule 1'!F74 -> 2 | N20: =ROUND(L20*M20,0) -> 1022894 | O20: ='Schedule 1'!F77 -> 2 | P20: 1022894 | Q20: =M20-O20 -> 0 | R20: =N20-P20 -> 0 | S20: =J20-M20 -> 0
F21: 5 | G21: Conference Chairs | H21: Nos. | I21: 0.005 | J21: 60 | K21: =I21*$K$8 -> 1022893.8 | L21: =IFERROR(K21/J21,0) -> 17048.229 | M21: ='Schedule 1'!F80 -> 60 | N21: =ROUND(L21*M21,0) -> 1022894 | O21: ='Schedule 1'!F83 -> 60 | P21: 1022894 | Q21: =M21-O21 -> 0 | R21: =N21-P21 -> 0 | S21: =J21-M21 -> 0
F22: 6 | G22: Projector and Monitor in Conference room | H22: Nos. | I22: 0.003 | J22: 1 | K22: =I22*$K$8 -> 613736.25 | L22: =IFERROR(K22/J22,0) -> 613736.25 | M22: ='Schedule 1'!F86 -> 1 | N22: =ROUND(L22*M22,0) -> 613736 | O22: ='Schedule 1'!F89 -> 1 | P22: 613736 | Q22: =M22-O22 -> 0 | R22: =N22-P22 -> 0 | S22: =J22-M22 -> 0
F23: 7 | G23: Display Arrangement | H23: Nos. | I23: 0.001 | J23: 2 | K23: =I23*$K$8 -> 204578.75 | L23: =IFERROR(K23/J23,0) -> 102289.38 | M23: ='Schedule 1'!F92 -> 2 | N23: =ROUND(L23*M23,0) -> 204579 | O23: ='Schedule 1'!F95 -> 2 | P23: 204579 | Q23: =M23-O23 -> 0 | R23: =N23-P23 -> 0 | S23: =J23-M23 -> 0
F24: 8 | G24: Steel Almirah and Racks | H24: Nos. | I24: 0.002 | J24: 10 | K24: =I24*$K$8 -> 409157.5 | L24: =IFERROR(K24/J24,0) -> 40915.75 | M24: ='Schedule 1'!F101 -> 10 | N24: =ROUND(L24*M24,0) -> 409158 | O24: ='Schedule 1'!F102 -> 10 | P24: 409158 | Q24: =M24-O24 -> 0 | R24: =N24-P24 -> 0 | S24: =J24-M24 -> 0
F25: 9 | G25: Domestic Water Purifier | H25: Nos. | I25: 0.0025 | J25: 2 | K25: =I25*$K$8 -> 511446.88 | L25: =IFERROR(K25/J25,0) -> 255723.44 | M25: ='Schedule 1'!F108 -> 2 | N25: =ROUND(L25*M25,0) -> 511447 | O25: ='Schedule 1'!F109 -> 2 | P25: 511447 | Q25: =M25-O25 -> 0 | R25: =N25-P25 -> 0 | S25: =J25-M25 -> 0
F26: iii | G26: Office Equipment | S26: =J26-M26 -> 0
F27: 1 | G27: Laptops | H27: Nos. | I27: 0.01 | J27: 6 | K27: =I27*$K$8 -> 2045787.5 | L27: =IFERROR(K27/J27,0) -> 340964.58 | M27: ='Schedule 1'!F114 -> 6 | N27: =ROUND(L27*M27,0) -> 2045788 | O27: ='Schedule 1'!F115 -> 6 | P27: 2045788 | Q27: =M27-O27 -> 0 | R27: =N27-P27 -> 0 | S27: =J27-M27 -> 0
F28: 2 | G28: Colour Printer | H28: Nos. | I28: 0.005 | J28: 2 | K28: =I28*$K$8 -> 1022893.8 | L28: =IFERROR(K28/J28,0) -> 511446.88 | M28: ='Schedule 1'!F120 -> 2 | N28: =ROUND(L28*M28,0) -> 1022894 | O28: ='Schedule 1'!F121 -> 2 | P28: 1022894 | Q28: =M28-O28 -> 0 | R28: =N28-P28 -> 0 | S28: =J28-M28 -> 0
F29: =F8+1 -> 102 | G29: Provision (construction) of contractor’s site office, site laboratories, labor camps etc | H29: LS | I29: 0.279 | K29: =I29*$E$8 -> 1.8713925e+08 | S29: =J29-M29 -> 0
F30: a | G30: Completion of Foundation | S30: =J30-M30 -> 0
F31: i | G31: Office | H31: Nos. | I31: 0.1 | J31: 1 | K31: =I31*$K$29 -> 18713925 | L31: =IFERROR(K31/J31,0) -> 18713925 | M31: ='Schedule 1'!F128 -> 1 | N31: =ROUND(L31*M31,0) -> 18713925 | O31: ='Schedule 1'!F129 -> 1 | P31: 18713925 | Q31: =M31-O31 -> 0 | R31: =N31-P31 -> 0 | S31: =J31-M31 -> 0
F32: ii | G32: Laboratory | H32: Nos. | I32: 0.04 | J32: 2 | K32: =I32*$K$29 -> 7485570 | L32: =IFERROR(K32/J32,0) -> 3742785 | M32: ='Schedule 1'!F135 -> 2 | N32: =ROUND(L32*M32,0) -> 7485570 | O32: ='Schedule 1'!F136 -> 2 | P32: 7485570 | Q32: =M32-O32 -> 0 | R32: =N32-P32 -> 0 | S32: =J32-M32 -> 0
F33: iii | G33: Labour Camps | S33: =J33-M33 -> 0
F34: 1 | G34: Building | H34: Nos. | I34: 0.02 | J34: 2 | K34: =I34*$K$29 -> 3742785 | L34: =IFERROR(K34/J34,0) -> 1871392.5 | M34: ='Schedule 1'!F144 -> 2 | N34: =ROUND(L34*M34,0) -> 3742785 | O34: ='Schedule 1'!F145 -> 2 | P34: 3742785 | Q34: =M34-O34 -> 0 | R34: =N34-P34 -> 0 | S34: =J34-M34 -> 0
F35: 2 | G35: Kitchen | H35: Nos. | I35: 0.01 | J35: 2 | K35: =I35*$K$29 -> 1871392.5 | L35: =IFERROR(K35/J35,0) -> 935696.25 | M35: ='Schedule 1'!F151 -> 2 | N35: =ROUND(L35*M35,0) -> 1871393 | O35: ='Schedule 1'!F152 -> 2 | P35: 1871393 | Q35: =M35-O35 -> 0 | R35: =N35-P35 -> 0 | S35: =J35-M35 -> 0
F36: b | G36: Completion of Plinth | S36: =J36-M36 -> 0
F37: i | G37: Office | H37: Nos. | I37: 0.1 | J37: 1 | K37: =I37*$K$29 -> 18713925 | L37: =IFERROR(K37/J37,0) -> 18713925 | M37: ='Schedule 1'!F157 -> 1 | N37: =ROUND(L37*M37,0) -> 18713925 | O37: ='Schedule 1'!F158 -> 1 | P37: 18713925 | Q37: =M37-O37 -> 0 | R37: =N37-P37 -> 0 | S37: =J37-M37 -> 0
F38: ii | G38: Laboratory | H38: Nos. | I38: 0.04 | J38: 2 | K38: =I38*$K$29 -> 7485570 | L38: =IFERROR(K38/J38,0) -> 3742785 | M38: ='Schedule 1'!F164 -> 2 | N38: =ROUND(L38*M38,0) -> 7485570 | O38: ='Schedule 1'!F165 -> 2 | P38: 7485570 | Q38: =M38-O38 -> 0 | R38: =N38-P38 -> 0 | S38: =J38-M38 -> 0
F39: iii | G39: Labour Camps | S39: =J39-M39 -> 0
F40: 1 | G40: Building | H40: Nos. | I40: 0.02 | J40: 2 | K40: =I40*$K$29 -> 3742785 | L40: =IFERROR(K40/J40,0) -> 1871392.5 | M40: ='Schedule 1'!F172 -> 2 | N40: =ROUND(L40*M40,0) -> 3742785 | O40: ='Schedule 1'!F173 -> 2 | P40: 3742785 | Q40: =M40-O40 -> 0 | R40: =N40-P40 -> 0 | S40: =J40-M40 -> 0
F41: 2 | G41: Kitchen | H41: Nos. | I41: 0.01 | J41: 2 | K41: =I41*$K$29 -> 1871392.5 | L41: =IFERROR(K41/J41,0) -> 935696.25 | M41: ='Schedule 1'!F180 -> 2 | N41: =ROUND(L41*M41,0) -> 1871393 | O41: ='Schedule 1'!F181 -> 2 | P41: 1871393 | Q41: =M41-O41 -> 0 | R41: =N41-P41 -> 0 | S41: =J41-M41 -> 0
F42: c | G42: Completion of Walls | S42: =J42-M42 -> 0
F43: i | G43: Office | H43: Nos. | I43: 0.1 | J43: 1 | K43: =I43*$K$29 -> 18713925 | L43: =IFERROR(K43/J43,0) -> 18713925 | M43: ='Schedule 1'!F186 -> 1 | N43: =ROUND(L43*M43,0) -> 18713925 | O43: ='Schedule 1'!F187 -> 1 | P43: 18713925 | Q43: =M43-O43 -> 0 | R43: =N43-P43 -> 0 | S43: =J43-M43 -> 0
F44: ii | G44: Laboratory | H44: Nos. | I44: 0.04 | J44: 2 | K44: =I44*$K$29 -> 7485570 | L44: =IFERROR(K44/J44,0) -> 3742785 | M44: ='Schedule 1'!F193 -> 2 | N44: =ROUND(L44*M44,0) -> 7485570 | O44: ='Schedule 1'!F194 -> 2 | P44: 7485570 | Q44: =M44-O44 -> 0 | R44: =N44-P44 -> 0 | S44: =J44-M44 -> 0
F45: iii | G45: Labour Camps | S45: =J45-M45 -> 0
F46: 1 | G46: Building | H46: Nos. | I46: 0.02 | J46: 2 | K46: =I46*$K$29 -> 3742785 | L46: =IFERROR(K46/J46,0) -> 1871392.5 | M46: ='Schedule 1'!F201 -> 2 | N46: =ROUND(L46*M46,0) -> 3742785 | O46: ='Schedule 1'!F202 -> 2 | P46: 3742785 | Q46: =M46-O46 -> 0 | R46: =N46-P46 -> 0 | S46: =J46-M46 -> 0
F47: 2 | G47: Kitchen | H47: Nos. | I47: 0.01 | J47: 2 | K47: =I47*$K$29 -> 1871392.5 | L47: =IFERROR(K47/J47,0) -> 935696.25 | M47: ='Schedule 1'!F208 -> 2 | N47: =ROUND(L47*M47,0) -> 1871393 | O47: ='Schedule 1'!F209 -> 2 | P47: 1871393 | Q47: =M47-O47 -> 0 | R47: =N47-P47 -> 0 | S47: =J47-M47 -> 0
F48: d | G48: Completion of Roofs | S48: =J48-M48 -> 0
F49: i | G49: Office | H49: Nos. | I49: 0.09 | J49: 1 | K49: =I49*$K$29 -> 16842533 | L49: =IFERROR(K49/J49,0) -> 16842533 | M49: ='Schedule 1'!F214 -> 1 | N49: =ROUND(L49*M49,0) -> 16842533 | O49: ='Schedule 1'!F215 -> 1 | P49: 16842533 | Q49: =M49-O49 -> 0 | R49: =N49-P49 -> 0 | S49: =J49-M49 -> 0
F50: ii | G50: Laboratory | H50: Nos. | I50: 0.04 | J50: 2 | K50: =I50*$K$29 -> 7485570 | L50: =IFERROR(K50/J50,0) -> 3742785 | M50: ='Schedule 1'!F221 -> 2 | N50: =ROUND(L50*M50,0) -> 7485570 | O50: ='Schedule 1'!F222 -> 2 | P50: 7485570 | Q50: =M50-O50 -> 0 | R50: =N50-P50 -> 0 | S50: =J50-M50 -> 0
F51: iii | G51: Labour Camps | S51: =J51-M51 -> 0
F52: 1 | G52: Building | H52: Nos. | I52: 0.02 | J52: 2 | K52: =I52*$K$29 -> 3742785 | L52: =IFERROR(K52/J52,0) -> 1871392.5 | M52: ='Schedule 1'!F228 -> 2 | N52: =ROUND(L52*M52,0) -> 3742785 | O52: ='Schedule 1'!F229 -> 2 | P52: 3742785 | Q52: =M52-O52 -> 0 | R52: =N52-P52 -> 0 | S52: =J52-M52 -> 0
F53: 2 | G53: Kitchen | H53: Nos. | I53: 0.01 | J53: 2 | K53: =I53*$K$29 -> 1871392.5 | L53: =IFERROR(K53/J53,0) -> 935696.25 | M53: ='Schedule 1'!F235 -> 2 | N53: =ROUND(L53*M53,0) -> 1871393 | O53: ='Schedule 1'!F236 -> 2 | P53: 1871393 | Q53: =M53-O53 -> 0 | R53: =N53-P53 -> 0 | S53: =J53-M53 -> 0
F54: e | G54: Completion of Flooring | S54: =J54-M54 -> 0
F55: i | G55: Office | H55: Nos. | I55: 0.09 | J55: 1 | K55: =I55*$K$29 -> 16842533 | L55: =IFERROR(K55/J55,0) -> 16842533 | M55: ='Schedule 1'!F241 -> 1 | N55: =ROUND(L55*M55,0) -> 16842533 | O55: ='Schedule 1'!F242 -> 1 | P55: 16842533 | Q55: =M55-O55 -> 0 | R55: =N55-P55 -> 0 | S55: =J55-M55 -> 0
F56: ii | G56: Laboratory | H56: Nos. | I56: 0.03 | J56: 2 | K56: =I56*$K$29 -> 5614177.5 | L56: =IFERROR(K56/J56,0) -> 2807088.8 | M56: ='Schedule 1'!F248 -> 2 | N56: =ROUND(L56*M56,0) -> 5614178 | O56: ='Schedule 1'!F249 -> 2 | P56: 5614178 | Q56: =M56-O56 -> 0 | R56: =N56-P56 -> 0 | S56: =J56-M56 -> 0
F57: iii | G57: Labour Camps | S57: =J57-M57 -> 0
F58: 1 | G58: Building | H58: Nos. | I58: 0.02 | J58: 2 | K58: =I58*$K$29 -> 3742785 | L58: =IFERROR(K58/J58,0) -> 1871392.5 | M58: ='Schedule 1'!F255 -> 2 | N58: =ROUND(L58*M58,0) -> 3742785 | O58: ='Schedule 1'!F256 -> 2 | P58: 3742785 | Q58: =M58-O58 -> 0 | R58: =N58-P58 -> 0 | S58: =J58-M58 -> 0
F59: 2 | G59: Kitchen | H59: Nos. | I59: 0.01 | J59: 2 | K59: =I59*$K$29 -> 1871392.5 | L59: =IFERROR(K59/J59,0) -> 935696.25 | M59: ='Schedule 1'!F262 -> 2 | N59: =ROUND(L59*M59,0) -> 1871393 | O59: ='Schedule 1'!F263 -> 2 | P59: 1871393 | Q59: =M59-O59 -> 0 | R59: =N59-P59 -> 0 | S59: =J59-M59 -> 0
F60: f | G60: Completion of Finishing Works | S60: =J60-M60 -> 0
F61: i | G61: Office | H61: Nos. | I61: 0.08 | J61: 1 | K61: =I61*$K$29 -> 14971140 | L61: =IFERROR(K61/J61,0) -> 14971140 | M61: ='Schedule 1'!F268 -> 1 | N61: =ROUND(L61*M61,0) -> 14971140 | O61: ='Schedule 1'!F269 -> 1 | P61: 14971140 | Q61: =M61-O61 -> 0 | R61: =N61-P61 -> 0 | S61: =J61-M61 -> 0
F62: ii | G62: Laboratory | S62: =J62-M62 -> 0
F63: 1 | G63: Civil Works | H63: Nos. | I63: 0.02 | J63: 2 | K63: =I63*$K$29 -> 3742785 | L63: =IFERROR(K63/J63,0) -> 1871392.5 | M63: ='Schedule 1'!F275 -> 2 | N63: =ROUND(L63*M63,0) -> 3742785 | O63: ='Schedule 1'!F276 -> 2 | P63: 3742785 | Q63: =M63-O63 -> 0 | R63: =N63-P63 -> 0 | S63: =J63-M63 -> 0
F64: 2 | G64: Lab Equipment | H64: Nos. | I64: 0.04 | J64: 2 | K64: =I64*$K$29 -> 7485570 | L64: =IFERROR(K64/J64,0) -> 3742785 | M64: ='Schedule 1'!F282 -> 2 | N64: =ROUND(L64*M64,0) -> 7485570 | O64: ='Schedule 1'!F283 -> 2 | P64: 7485570 | Q64: =M64-O64 -> 0 | R64: =N64-P64 -> 0 | S64: =J64-M64 -> 0
F65: iii | G65: Labour Camps | S65: =J65-M65 -> 0
F66: 1 | G66: Building | H66: Nos. | I66: 0.02 | J66: 2 | K66: =I66*$K$29 -> 3742785 | L66: =IFERROR(K66/J66,0) -> 1871392.5 | M66: ='Schedule 1'!F289 -> 2 | N66: =ROUND(L66*M66,0) -> 3742785 | O66: ='Schedule 1'!F290 -> 2 | P66: 3742785 | Q66: =M66-O66 -> 0 | R66: =N66-P66 -> 0 | S66: =J66-M66 -> 0
F67: 2 | G67: Kitchen | H67: Nos. | I67: 0.02 | J67: 2 | K67: =I67*$K$29 -> 3742785 | L67: =IFERROR(K67/J67,0) -> 1871392.5 | M67: ='Schedule 1'!F296 -> 2 | N67: =ROUND(L67*M67,0) -> 3742785 | O67: ='Schedule 1'!F297 -> 2 | P67: 3742785 | Q67: =M67-O67 -> 0 | R67: =N67-P67 -> 0 | S67: =J67-M67 -> 0
F68: =F29+1 -> 103 | G68: Operation and Maintenance of all temporary facilities including those mentioned in Item 101 & 102 | H68: LS | I68: 0.123 | K68: =I68*$E$8 -> 82502250 | S68: =J68-M68 -> 0
F69: a | G69: Employer's Office | H69: Quarterly | I69: 0.35 | J69: 16 | K69: =I69*$K$68 -> 28875788 | L69: =IFERROR(K69/J69,0) -> 1804736.7 | M69: ='Schedule 1'!F318 -> 8 | N69: =ROUND(L69*M69,0) -> 14437894 | O69: ='Schedule 1'!F319 -> 8 | P69: 14437894 | Q69: =M69-O69 -> 0 | R69: =N69-P69 -> 0 | S69: =J69-M69 -> 8 | T69: =L69 -> 1804736.7
F70: b | G70: Vehicles | S70: =J70-M70 -> 0
F71: i | G71: Bolero & Scorpio | H71: Nos.-Quarterly | I71: 0.2 | J71: 96 | K71: =I71*$K$68 -> 16500450 | L71: =IFERROR(K71/J71,0) -> 171879.69 | M71: ='Schedule 1'!F331 -> 48 | N71: =ROUND(L71*M71,0) -> 8250225 | O71: ='Schedule 1'!F332 -> 48 | P71: 8250225 | Q71: =M71-O71 -> 0 | R71: =N71-P71 -> 0 | S71: =J71-M71 -> 48 | T71: =L71*6 -> 1031278.1
F72: ii | G72: Speed Boat | H72: Nos.-Quarterly | I72: 0.03 | J72: 32 | K72: =I72*$K$68 -> 2475067.5 | L72: =IFERROR(K72/J72,0) -> 77345.859 | M72: ='Schedule 1'!F344 -> 16 | N72: =ROUND(L72*M72,0) -> 1237534 | O72: ='Schedule 1'!F345 -> 16 | P72: 1237534 | Q72: =M72-O72 -> 0 | R72: =N72-P72 -> 0 | S72: =J72-M72 -> 16 | T72: =L72*2 -> 154691.72
F73: iii | G73: Rescue Boat | H73: Nos.-Quarterly | I73: 0.02 | J73: 16 | K73: =I73*$K$68 -> 1650045 | L73: =IFERROR(K73/J73,0) -> 103127.81 | M73: ='Schedule 1'!F357 -> 8 | N73: =ROUND(L73*M73,0) -> 825023 | O73: ='Schedule 1'!F358 -> 8 | P73: 825023 | Q73: =M73-O73 -> 0 | R73: =N73-P73 -> 0 | S73: =J73-M73 -> 8 | T73: =L73*1 -> 103127.81
F74: c | G74: Contractor's Office | H74: Quarterly | I74: 0.15 | J74: 16 | K74: =I74*$K$68 -> 12375338 | L74: =IFERROR(K74/J74,0) -> 773458.59 | M74: ='Schedule 1'!F370 -> 8 | N74: =ROUND(L74*M74,0) -> 6187669 | O74: ='Schedule 1'!F371 -> 8 | P74: 6187669 | Q74: =M74-O74 -> 0 | R74: =N74-P74 -> 0 | S74: =J74-M74 -> 8 | T74: =L74 -> 773458.59
F75: d | G75: Site Laboratory | H75: Quarterly | I75: 0.15 | J75: 16 | K75: =I75*$K$68 -> 12375338 | L75: =IFERROR(K75/J75,0) -> 773458.59 | M75: ='Schedule 1'!F391 -> 8 | N75: =ROUND(L75*M75,0) -> 6187669 | O75: ='Schedule 1'!F392 -> 8 | P75: 6187669 | Q75: =M75-O75 -> 0 | R75: =N75-P75 -> 0 | S75: =J75-M75 -> 8 | T75: =L75 -> 773458.59
F76: e | G76: Labour Camps | H76: Quarterly | I76: 0.1 | J76: 16 | K76: =I76*$K$68 -> 8250225 | L76: =IFERROR(K76/J76,0) -> 515639.06 | M76: ='Schedule 1'!F412 -> 8 | N76: =ROUND(L76*M76,0) -> 4125113 | O76: ='Schedule 1'!F413 -> 8 | P76: 4125113 | Q76: =M76-O76 -> 0 | R76: =N76-P76 -> 0 | S76: =J76-M76 -> 8 | T76: =L76 -> 515639.06
F77: =F68+1 -> 104 | G77: Compliance of Environmental Management Plan (EMP) | H77: LS | I77: 0.225 | K77: =I77*$E$8 -> 150918750 | S77: =J77-M77 -> 0
F78: a | G78: Environmental Management Plan Implementation - Preservation of Top Soil, Propeller Guards, Plant Establishments : CTE, CTO, NOC's, Dust Supression Measures, Compensatory afforestation, TBT for Wildlife conservation for consideration of 48 months construction period or till completion of the project, whichever is later | H78: Half Yearly | I78: 0.0735 | J78: 8 | K78: =I78*$K$77 -> 11092528 | L78: =IFERROR(K78/J78,0) -> 1386566 | M78: ='Schedule 1'!$F$422 -> 4 | N78: =ROUND(L78*M78,0) -> 5546264 | O78: ='Schedule 1'!$F$423 -> 4 | P78: 5546264 | Q78: =M78-O78 -> 0 | R78: =N78-P78 -> 0 | S78: =J78-M78 -> 4 | T78: =L78 -> 1386566
F79: b | G79: Implementation of Environmental Monitoring Program for consideration of 48 months construction period or till completion of the project, whichever is later | S79: =J79-M79 -> 0
F80: i | G80: Ambient Air Quality | H80: Bi-Monthly | I80: 0.03 | J80: 24 | K80: =I80*$K$77 -> 4527562.5 | L80: =IFERROR(K80/J80,0) -> 188648.44 | M80: ='Schedule 1'!F451 -> 12 | N80: =ROUND(L80*M80,0) -> 2263781 | O80: ='Schedule 1'!$F$452 -> 12 | P80: 2263781 | Q80: =M80-O80 -> 0 | R80: =N80-P80 -> 0 | S80: =J80-M80 -> 12 | T80: =L80 -> 188648.44
F81: ii | G81: Noise Level | H81: Bi-Monthly | I81: 0.03 | J81: 24 | K81: =I81*$K$77 -> 4527562.5 | L81: =IFERROR(K81/J81,0) -> 188648.44 | M81: ='Schedule 1'!F480 -> 12 | N81: =ROUND(L81*M81,0) -> 2263781 | O81: ='Schedule 1'!$F$481 -> 12 | P81: 2263781 | Q81: =M81-O81 -> 0 | R81: =N81-P81 -> 0 | S81: =J81-M81 -> 12 | T81: =L81 -> 188648.44
F82: iii | G82: Water Quality | H82: Bi-Monthly | I82: 0.03 | J82: 24 | K82: =I82*$K$77 -> 4527562.5 | L82: =IFERROR(K82/J82,0) -> 188648.44 | M82: ='Schedule 1'!F509 -> 12 | N82: =ROUND(L82*M82,0) -> 2263781 | O82: ='Schedule 1'!F510 -> 12 | P82: 2263781 | Q82: =M82-O82 -> 0 | R82: =N82-P82 -> 0 | S82: =J82-M82 -> 12 | T82: =L82 -> 188648.44
F83: iv | G83: Soil Quality | H83: Half Yearly | I83: 0.03 | J83: 8 | K83: =I83*$K$77 -> 4527562.5 | L83: =IFERROR(K83/J83,0) -> 565945.31 | M83: ='Schedule 1'!$F$522 -> 4 | N83: =ROUND(L83*M83,0) -> 2263781 | O83: ='Schedule 1'!$F$523 -> 4 | P83: 2263781 | Q83: =M83-O83 -> 0 | R83: =N83-P83 -> 0 | S83: =J83-M83 -> 4 | T83: =L83 -> 565945.31
F84: v | G84: Ecology and Biodiversity - Regular Survey of Ecology and Biodiversity (Terrestrial & Aquatic), Survey Equipment | H84: Half Yearly | I84: 0.06 | J84: 8 | K84: =I84*$K$77 -> 9055125 | L84: =IFERROR(K84/J84,0) -> 1131890.6 | M84: ='Schedule 1'!$F$531 -> 4 | N84: =ROUND(L84*M84,0) -> 4527563 | O84: ='Schedule 1'!$F$532 -> 4 | P84: 4527563 | Q84: =M84-O84 -> 0 | R84: =N84-P84 -> 0 | S84: =J84-M84 -> 4 | T84: =L84 -> 1131890.6
F85: c | G85: Compliance of Environmental Clearance Conditions - EC identification no. EC22B039AS197455 - Handling of Hazardous Waste, Provision of First Aid Room, Sanitary Measures, Green Belt Plantation for consideration of 48 months construction period or till completion of the project, whichever is later | H85: Half Yearly | I85: 0.1 | J85: 8 | K85: =I85*$K$77 -> 15091875 | L85: =IFERROR(K85/J85,0) -> 1886484.4 | M85: ='Schedule 1'!$F$540 -> 4 | N85: =ROUND(L85*M85,0) -> 7545938 | O85: ='Schedule 1'!$F$541 -> 4 | P85: 7545938 | Q85: =M85-O85 -> 0 | R85: =N85-P85 -> 0 | S85: =J85-M85 -> 4 | T85: =L85 -> 1886484.4
F86: d | G86: Implementation of Environmental Management Plan - For Aquatic Ecology and Dolphin Conservation - Monitoring of Dolphins, Migratory Birds, Turtle & Fish through Dolphin Biologists, No-go Zone for Boats & Vessels for consideration of 48 months construction period or till completion of the project, whichever is later | H86: Half Yearly | I86: 0.1 | J86: 8 | K86: =I86*$K$77 -> 15091875 | L86: =IFERROR(K86/J86,0) -> 1886484.4 | M86: ='Schedule 1'!$F$549 -> 4 | N86: =ROUND(L86*M86,0) -> 7545938 | O86: ='Schedule 1'!$F$550 -> 4 | P86: 7545938 | Q86: =M86-O86 -> 0 | R86: =N86-P86 -> 0 | S86: =J86-M86 -> 4 | T86: =L86 -> 1886484.4
F87: e | G87: Dolphin Pinger for Dolphin Safety | S87: =J87-M87 -> 0
F88: i | G88: Installation & Monitoring | H88: Nos. | I88: 0.05 | J88: 30 | K88: =I88*$K$77 -> 7545937.5 | L88: =IFERROR(K88/J88,0) -> 251531.25 | M88: ='Schedule 1'!$F$556 -> 30 | N88: =ROUND(L88*M88,0) -> 7545938 | O88: ='Schedule 1'!$F$557 -> 30 | P88: 7545938 | Q88: =M88-O88 -> 0 | R88: =N88-P88 -> 0 | S88: =J88-M88 -> 0
F89: ii | G89: Maintenance of Equipment | H89: Quarterly | I89: 0.05 | J89: 16 | K89: =I89*$K$77 -> 7545937.5 | L89: =IFERROR(K89/J89,0) -> 471621.09 | M89: ='Schedule 1'!$F$568 -> 8 | N89: =ROUND(L89*M89,0) -> 3772969 | O89: ='Schedule 1'!$F$569 -> 8 | P89: 3772969 | Q89: =M89-O89 -> 0 | R89: =N89-P89 -> 0 | S89: =J89-M89 -> 8 | T89: =30*6*L89 -> 84891797
F90: f | G90: Wetland Restoration - Clearance of Eutrophication, Water area, etc as per EC Condition till completion of the project | H90: LS | I90: 0.0665 | J90: 1 | K90: =I90*$K$77 -> 10036097 | L90: =IFERROR(K90/J90,0) -> 10036097 | M90: 0 | N90: =ROUND(L90*M90,0) -> 0 | O90: 0 | P90: 0 | Q90: =M90-O90 -> 0 | R90: =N90-P90 -> 0 | S90: =J90-M90 -> 1
F91: g | G91: EMP provisions - During Construction Phase for consideration of 48 months construction period or till completion of the project, whichever is later | S91: =J91-M91 -> 0
F92: i | G92: Solid Waste Management accessories | H92: Quarterly | I92: 0.03 | J92: 16 | K92: =I92*$K$77 -> 4527562.5 | L92: =IFERROR(K92/J92,0) -> 282972.66 | M92: ='Schedule 1'!F581 -> 8 | N92: =ROUND(L92*M92,0) -> 2263781 | O92: ='Schedule 1'!F582 -> 8 | P92: 2263781 | Q92: =M92-O92 -> 0 | R92: =N92-P92 -> 0 | S92: =J92-M92 -> 8 | T92: =L92 -> 282972.66
F93: ii | G93: Health and Occupational Safety Management Plan | H93: Quarterly | I93: 0.05 | J93: 16 | K93: =I93*$K$77 -> 7545937.5 | L93: =IFERROR(K93/J93,0) -> 471621.09 | M93: ='Schedule 1'!F594 -> 8 | N93: =ROUND(L93*M93,0) -> 3772969 | O93: ='Schedule 1'!F595 -> 8 | P93: 3772969 | Q93: =M93-O93 -> 0 | R93: =N93-P93 -> 0 | S93: =J93-M93 -> 8 | T93: =L93 -> 471621.09
F94: iii | G94: Environmental Training Plan | H94: Quarterly | I94: 0.03 | J94: 16 | K94: =I94*$K$77 -> 4527562.5 | L94: =IFERROR(K94/J94,0) -> 282972.66 | M94: ='Schedule 1'!F607 -> 8 | N94: =ROUND(L94*M94,0) -> 2263781 | O94: ='Schedule 1'!F608 -> 8 | P94: 2263781 | Q94: =M94-O94 -> 0 | R94: =N94-P94 -> 0 | S94: =J94-M94 -> 8 | T94: =L94 -> 282972.66
F95: iv | G95: Traffic Management Plan | H95: Quarterly | I95: 0.03 | J95: 16 | K95: =I95*$K$77 -> 4527562.5 | L95: =IFERROR(K95/J95,0) -> 282972.66 | M95: ='Schedule 1'!F620 -> 8 | N95: =ROUND(L95*M95,0) -> 2263781 | O95: ='Schedule 1'!F621 -> 8 | P95: 2263781 | Q95: =M95-O95 -> 0 | R95: =N95-P95 -> 0 | S95: =J95-M95 -> 8 | T95: =L95 -> 282972.66
F96: v | G96: Emergency Preparedness Plan | H96: Quarterly | I96: 0.03 | J96: 16 | K96: =I96*$K$77 -> 4527562.5 | L96: =IFERROR(K96/J96,0) -> 282972.66 | M96: ='Schedule 1'!F633 -> 8 | N96: =ROUND(L96*M96,0) -> 2263781 | O96: ='Schedule 1'!F634 -> 8 | P96: 2263781 | Q96: =M96-O96 -> 0 | R96: =N96-P96 -> 0 | S96: =J96-M96 -> 8 | T96: =L96 -> 282972.66
F97: vi | G97: Miscellaneous (repair and maintenance) | H97: Quarterly | I97: 0.01 | J97: 16 | K97: =I97*$K$77 -> 1509187.5 | L97: =IFERROR(K97/J97,0) -> 94324.219 | M97: ='Schedule 1'!F646 -> 8 | N97: =ROUND(L97*M97,0) -> 754594 | O97: ='Schedule 1'!F647 -> 8 | P97: 754594 | Q97: =M97-O97 -> 0 | R97: =N97-P97 -> 0 | S97: =J97-M97 -> 8 | T97: =L97 -> 94324.219
F98: h | G98: Provision for establishment of Sewage and Water Treatment Plant within construction period of 48 months or till completion of the project, whichever is later | S98: =J98-M98 -> 0
F99: i | G99: Sewage Treatment Plant | S99: =J99-M99 -> 0
F100: 1 | G100: Construction | H100: Nos. | I100: 0.03 | J100: 3 | K100: =I100*$K$77 -> 4527562.5 | L100: =IFERROR(K100/J100,0) -> 1509187.5 | M100: ='Schedule 1'!$F$654 -> 3 | N100: =ROUND(L100*M100,0) -> 4527563 | O100: ='Schedule 1'!$F$655 -> 3 | P100: 4527563 | Q100: =M100-O100 -> 0 | R100: =N100-P100 -> 0 | S100: =J100-M100 -> 0
F101: 2 | G101: Maintenance | H101: Quarterly | I101: 0.01 | J101: 15 | K101: =I101*$K$77 -> 1509187.5 | L101: =IFERROR(K101/J101,0) -> 100612.5 | M101: ='Schedule 1'!$F$673 -> 7 | N101: =ROUND(L101*M101,0) -> 704288 | O101: ='Schedule 1'!$F$674 -> 7 | P101: 704288 | Q101: =M101-O101 -> 0 | R101: =N101-P101 -> 0 | S101: =J101-M101 -> 8 | T101: =4*L101 -> 402450
F102: ii | G102: Waste Water Treatment Plant | S102: =J102-M102 -> 0
...

Sheet MB Details
B1: Item No. | C1: page No | D1: Item Description | E1: UoM | F1: Location | G1: Executed Quantity | H1: RFI No. / Letter No. | I1: Date | J1: IPC No. | K1: Signed date | L1: Remarks
B2: 406.a / 407.c | C2: 75 | D2: Precast - Box girder segments | E2: Nos. | F2: Palashbari | G2: 1 | H2: MPSB/MB/244 | I2: 45940 | J2: IPC - 34 | K2: 45942 | L2: P17-BP-S32a-O | M2: =K2-I2 -> 2
A3: Installation of PSC Box girders/I-Girders at site including installation of Post Tensioning for completion of deck | B3: 506.a.1 | C3: 75 | D3: For Wetland Viaduct - Casting of Deck Panel | E3: Span | F3: Sualkuchi | G3: 1 | H3: MPSB/Str/4959 | I3: 46193 | J3: IPC - 34 | K3: 46193 | L3: PL10 to PL11 | M3: =K3-I3 -> 0
A4: Construction of sub- structure; abutment/piers / lower pylon & Construction of pier- cap/ pier table | B4: 502 & 503.a.2 | C4: 76 | D4: For Wetland Viaduct - On completion of pier-cap / pier table | E4: Nos. | F4: Sualkuchi | G4: 1 | H4: MPSB/Str/4967 | I4: 46193 | J4: IPC - 34 | K4: 46199 | L4: Km 10+636 - PR1 - Piercap | M4: =K4-I4 -> 6
A5: Procurement, testing and supply of post tensioning material to site | B5: 505.a.3 | C5: 76 | D5: For Wetland Viaduct - Final stressing of Girders at site | E5: Nos. | F5: Sualkuchi | G5: 1 | H5: MPSB/Str/5077 | I5: 46206 | J5: IPC - 34 | K5: 46206 | L5: WV2-P3-P4-G2 | M5: =K5-I5 -> 0
B6: 506.a.2 | C6: 77 | D6: For Wetland Viaduct - Deck Panel Erection | E6: Span | F6: Sualkuchi | G6: 3 | H6: MPSB/Str/5079 | I6: 46206 | J6: IPC - 34 | K6: 46206 | L6: PL9 to PL12 | M6: =K6-I6 -> 0
A7: Installation of bearings and expansion joints | B7: 507.a.2 | C7: 77 | D7: For Wetland Viaduct - Bearings - Installation | E7: Nos. | F7: Sualkuchi | G7: 2 | H7: MPSB/Sur/3725 | I7: 46206 | J7: IPC - 34 | K7: 46206 | L7: PR20 | M7: =K7-I7 -> 0
B8: 506.a.1 | C8: 77 | D8: For Wetland Viaduct - Casting of Deck Panel | E8: Span | F8: Sualkuchi | G8: 1 | H8: MPSB/Str/5081 | I8: 46206 | J8: IPC - 34 | K8: 46207 | L8: PL1 to PL2 | M8: =K8-I8 -> 1
B9: 507.a.2 | C9: 78 | D9: For Wetland Viaduct - Bearings - Installation | E9: Nos. | F9: Sualkuchi | G9: 2 | H9: MPSB/Sur/3726 | I9: 46206 | J9: IPC - 34 | K9: 46210 | L9: PR21 | M9: =K9-I9 -> 4
B10: 505.a.3 | C10: 78 | D10: For Wetland Viaduct - Final stressing of Girders at site | E10: Nos. | F10: Sualkuchi | G10: 1 | H10: MPSB/Str/5092 | I10: 46210 | J10: IPC - 34 | K10: 46211 | L10: WV2-P3-P4-G3 | M10: =K10-I10 -> 1
A11: Construction of sub- structure; abutment/ piers / lower pylon | B11: 403.a | C11: 78 | D11: Construction of abutment / piers / lower pylon | E11: Rmt | F11: Palashbari | G11: 2 | H11: MPSB/Str/5108 | I11: 46212 | J11: IPC - 34 | K11: 46214 | L11: P7 - Lower Pylon - 2nd Lift | M11: =K11-I11 -> 2
B12: 403.a | C12: 79 | D12: Construction of abutment / piers / lower pylon | E12: Rmt | F12: Sualkuchi | G12: 2.115 | H12: MPSB/Str/5101 | I12: 46212 | J12: IPC - 34 | K12: 46214 | L12: P25 - Lower Pylon - 2nd Lift | M12: =K12-I12 -> 2
B13: 406.a / 407.c | C13: 79 | D13: Precast - Box girder segments | E13: Nos. | F13: Palashbari | G13: 1 | H13: MPSB/MB/2089 | I13: 46212 | J13: IPC - 34 | K13: 46214 | L13: P16-KS-S09-M | M13: =K13-I13 -> 2
B14: 406.a / 407.c | C14: 79 | D14: Precast - Box girder segments | E14: Nos. | F14: Palashbari | G14: 1 | H14: MPSB/MB/2090 | I14: 46212 | J14: IPC - 34 | K14: 46215 | L14: P9-BP-S04a-O | M14: =K14-I14 -> 3
B15: 406.a / 407.c | C15: 79 | D15: Precast - Box girder segments | E15: Nos. | F15: Palashbari | G15: 1 | H15: MPSB/MB/2087 | I15: 46211 | J15: IPC - 34 | K15: 46215 | L15: P15-BP-S10-O | M15: =K15-I15 -> 4
A16: Construction of PSC Box girders/I-Girders in casting yard | B16: 504.a.1 | C16: 80 | D16: For Wetland Viaduct - Casting of Girders in the precast yard | E16: Nos. | F16: Sualkuchi | G16: 1 | H16: MPSB/Str/5105 | I16: 46212 | J16: IPC - 34 | K16: 46215 | L16: WV1-P1-P2-G3 | M16: =K16-I16 -> 3
B17: 406.a / 407.c | C17: 80 | D17: Precast - Box girder segments | E17: Nos. | F17: Palashbari | G17: 1 | H17: MPSB/MB/2101 | I17: 46213 | J17: IPC - 34 | K17: 46216 | L17: P9-KS-S32-O | M17: =K17-I17 -> 3
A18: Construction of foundation | B18: 501.b.3 | C18: 81 | D18: For Approach Viaduct - On completion of Pile Cap | E18: Nos. | F18: Sualkuchi | G18: 1 | H18: MPSB/Str/5098 | I18: 46211 | J18: IPC - 34 | K18: 46216 | L18: Km 9+352 - PL34 - Pilecap | M18: =K18-I18 -> 5
B19: 406.a / 407.c / 408.c | C19: 81 | D19: Precast - Box girder segments | E19: Nos. | F19: Sualkuchi | G19: 1 | H19: MPSB/MB/2107 | I19: 46213 | J19: IPC - 34 | K19: 46216 | L19: P21-KS-S33-O© | M19: =K19-I19 -> 3
B20: 406.a / 407.c / 408.c | C20: 81 | D20: Precast - Box girder segments | E20: Nos. | F20: Sualkuchi | G20: 1 | H20: MPSB/MB/2113 | I20: 46214 | J20: IPC - 34 | K20: 46217 | L20: P21-BP-S25a-O© | M20: =K20-I20 -> 3
B21: 501.b.2 | C21: 81 | D21: For Approach Viaduct - On completion of Well | E21: Rmt | F21: Palashbari | G21: 1.05 | H21: MPSB/Str/5134 | I21: 46216 | J21: IPC - 34 | K21: 46217 | L21: P4 - 18th Lift | M21: =K21-I21 -> 1
B22: 507.a.2 | C22: 82 | D22: For Wetland Viaduct - Bearings - Installation | E22: Nos. | F22: Sualkuchi | G22: 4 | H22: MPSB/Sur/3761 | I22: 46217 | J22: IPC - 34 | K22: 46217 | L22: PR18 | M22: =K22-I22 -> 0
B23: 406.a / 407.c / 408.c | C23: 82 | D23: Precast - Box girder segments | E23: Nos. | F23: Palashbari | G23: 1 | H23: MPSB/MB/2139 | I23: 46218 | J23: IPC - 34 | K23: 46218 | L23: P16-KS-S10-M© | M23: =K23-I23 -> 0
B24: 502 & 503.a.2 | C24: 82 | D24: For Wetland Viaduct - On completion of pier-cap / pier table | E24: Nos. | F24: Sualkuchi | G24: 1 | H24: MPSB/Str/5112 | I24: 46213 | J24: IPC - 34 | K24: 46218 | L24: Km 10+230 - PL0 - Piercap | M24: =K24-I24 -> 5
B25: 505.b.3 | C25: 83 | D25: For Approach Viaduct - Final Stressing of Girders at site | E25: Nos. | F25: Palashbari | G25: 1 | H25: MPSB/Str/5148 | I25: 46218 | J25: IPC - 34 | K25: 46218 | L25: SAV-P2-P3-G1 | M25: =K25-I25 -> 0
B26: 505.b.3 | C26: 83 | D26: For Approach Viaduct - Final Stressing of Girders at site | E26: Nos. | F26: Palashbari | G26: 1 | H26: MPSB/Str/5149 | I26: 46218 | J26: IPC - 34 | K26: 46218 | L26: SAV-P2-P3-G2 | M26: =K26-I26 -> 0
B27: 506.a.1 | C27: 83 | D27: For Wetland Viaduct - Casting of Deck Panel | E27: Span | F27: Sualkuchi | G27: 1 | H27: MPSB/Str/5135 | I27: 46217 | J27: IPC - 34 | K27: 46218 | L27: PL0 to PL1 | M27: =K27-I27 -> 1
B28: 406.a / 407.c | C28: 84 | D28: Precast - Box girder segments | E28: Nos. | F28: Palashbari | G28: 1 | H28: MPSB/MB/2109 | I28: 46214 | J28: IPC - 34 | K28: 46218 | L28: P16-BP-S17-M | M28: =K28-I28 -> 4
B29: 406.a / 407.c | C29: 84 | D29: Precast - Box girder segments | E29: Nos. | F29: Sualkuchi | G29: 1 | H29: MPSB/MB/2118 | I29: 46216 | J29: IPC - 34 | K29: 46219 | L29: P22-BP-S04-E | M29: =K29-I29 -> 3
B30: 406.a / 407.c / 408.c | C30: 84 | D30: Precast - Box girder segments | E30: Nos. | F30: Palashbari | G30: 1 | H30: MPSB/MB/2116 | I30: 46216 | J30: IPC - 34 | K30: 46219 | L30: P15-BP-S11-O© | M30: =K30-I30 -> 3
... B33: 506.a.1 | C33: 85 | D33: For Wetland Viaduct - Casting of Deck Panel | E33: Span | F33: Sualkuchi | G33: 1 | H33: MPSB/Str/5144 | I33: 46218 | J33: IPC - 34 | K33: 46219 | L33: PR19 to PR20 | M33: =K33-I33 -> 1
A34: Construction of earth retaining structures, culvert & minor structures | B34: 706.a | C34: 86 | D34: Completion of the main structural works excluding finishing works - Culverts | E34: Nos. | F34: Palashbari | G34: 0.5 | H34: MPSB/Str/5143 | I34: 46217 | J34: IPC - 34 | K34: 46219 | L34: Km 4+154 | M34: =K34-I34 -> 2
B35: 403.a | C35: 86 | D35: Construction of abutment / piers / lower pylon | E35: Rmt | F35: Sualkuchi | G35: 0.63 | H35: MPSB/Str/5128 | I35: 46216 | J35: IPC - 34 | K35: 46220 | L35: P29 - Lower Pylon - Starter | M35: =K35-I35 -> 4
B36: 504.a.2 | C36: 86 | D36: For Wetland Viaduct - Erection of Girders at site | E36: Nos. | F36: Sualkuchi | G36: 4 | H36: MPSB/Str/5091 | I36: 46210 | J36: IPC - 34 | K36: 46220 | L36: WV2-P15-P16 (G5 to G8) | M36: =K36-I36 -> 10
B37: 406.a / 407.c | C37: 87 | D37: Precast - Box girder segments | E37: Nos. | F37: Palashbari | G37: 1 | H37: MPSB/MB/2133 | I37: 46217 | J37: IPC - 34 | K37: 46220 | L37: P9-BP-S05a-O | M37: =K37-I37 -> 3
B38: 406.a / 407.c | C38: 87 | D38: Precast - Box girder segments | E38: Nos. | F38: Sualkuchi | G38: 1 | H38: MPSB/MB/2138 | I38: 46218 | J38: IPC - 34 | K38: 46220 | L38: P21-KS-S34-O | M38: =K38-I38 -> 2
B39: 406.a / 407.c | C39: 87 | D39: Precast - Box girder segments | E39: Nos. | F39: Sualkuchi | G39: 1 | H39: MPSB/MB/2154 | I39: 46220 | J39: IPC - 34 | K39: 46221 | L39: P22-BP-S05-E | M39: =K39-I39 -> 1
B40: 406.a / 407.c / 408.c | C40: 87 | D40: Precast - Box girder segments | E40: Nos. | F40: Sualkuchi | G40: 1 | H40: MPSB/MB/2137 | I40: 46218 | J40: IPC - 34 | K40: 46221 | L40: P21-BP-S21a-O© | M40: =K40-I40 -> 3
B41: 504.a.1 | C41: 88 | D41: For Wetland Viaduct - Casting of Girders in the precast yard | E41: Nos. | F41: Sualkuchi | G41: 1 | H41: MPSB/Str/5138 | I41: 46217 | J41: IPC - 34 | K41: 46221 | L41: WV1-P1-P2-G2 | M41: =K41-I41 -> 4
B42: 403.a | C42: 88 | D42: Construction of abutment / piers / lower pylon | E42: Rmt | F42: Palashbari | G42: 4.329 | H42: MPSB/Str/5151 | I42: 46218 | J42: IPC - 34 | K42: 46222 | L42: P8 - Lower Pylon - 7th Lift | M42: =K42-I42 -> 4
B43: 406.a / 407.c / 408.c | C43: 88 | D43: Precast - Box girder segments | E43: Nos. | F43: Palashbari | G43: 1 | H43: MPSB/MB/2140 | I43: 46218 | J43: IPC - 34 | K43: 46222 | L43: P9-KS-S33-O© | M43: =K43-I43 -> 4
B44: 406.a / 407.c | C44: 89 | D44: Precast - Box girder segments | E44: Nos. | F44: Palashbari | G44: 1 | H44: MPSB/MB/2149 | I44: 46220 | J44: IPC - 34 | K44: 46222 | L44: P16-BP-S18-M | M44: =K44-I44 -> 2
B45: 504.b.1 | C45: 89 | D45: For Approach Viaduct - Casting of Girders in the precast yard | E45: Nos. | F45: Palashbari | G45: 1 | H45: MPSB/Str/5160 | I45: 46221 | J45: IPC - 34 | K45: 46222 | L45: SAV-P5-P6-G7 | M45: =K45-I45 -> 1
B46: 406.a / 407.c | C46: 89 | D46: Precast - Box girder segments | E46: Nos. | F46: Sualkuchi | G46: 1 | H46: MPSB/MB/2159 | I46: 46221 | J46: IPC - 34 | K46: 46223 | L46: P21-BP-S26a-O | M46: =K46-I46 -> 2
... B73: 505.b.3 | C73: 97 | D73: For Approach Viaduct - Final Stressing of Girders at site | E73: Nos. | F73: Palashbari | G73: 1 | H73: MPSB/Str/5211 | I73: 46231 | J73: IPC - 34 | K73: 46231 | L73: SAV-P1R-P2R-G1 | M73: =K73-I73 -> 0
A74: Construction of foundation | B74: 402.c | C74: 98 | D74: Well Cap | E74: Nos. | F74: Sualkuchi | G74: 1 | H74: MPSB/Str/5219 | I74: 46232 | J74: IPC - 34 | K74: 46232 | L74: P24 - Well Cap | M74: =K74-I74 -> 0
B75: 406.a / 407.c | C75: 98 | D75: Precast - Box girder segments | E75: Nos. | F75: Palashbari | G75: 1 | H75: MPSB/MB/2211 | I75: 46230 | J75: IPC - 34 | K75: 46232 | L75: P15-BP-S14-O | M75: =K75-I75 -> 2
B76: 406.a / 407.c / 408.c | C76: 98 | D76: Precast - Box girder segments | E76: Nos. | F76: Sualkuchi | G76: 1 | H76: MPSB/MB/2214 | I76: 46231 | J76: IPC - 34 | K76: 46232 | L76: P21-BP-S29a-O© | M76: =K76-I76 -> 1
B77: 504.a.1 | C77: 99 | D77: For Wetland Viaduct - Casting of Girders in the precast yard | E77: Nos. | F77: Sualkuchi | G77: 1 | H77: MPSB/Str/5222 | I77: 46232 | J77: IPC - 34 | K77: 46232 | L77: WV1-P0-P1-G7 | M77: =K77-I77 -> 0
B78: 506.a.1 | C78: 99 | D78: For Wetland Viaduct - Casting of Deck Panel | E78: Span | F78: Sualkuchi | G78: 1 | H78: MPSB/Str/5213 | I78: 46231 | J78: IPC - 34 | K78: 46232 | L78: PR18 to PR19 | M78: =K78-I78 -> 1
B79: 506.a.1 | C79: 99 | D79: For Wetland Viaduct - Casting of Deck Panel | E79: Span | F79: Sualkuchi | G79: 1 | H79: MPSB/Str/5212 | I79: 46231 | J79: IPC - 34 | K79: 46232 | L79: PR17 to PR18 | M79: =K79-I79 -> 1
B80: 506.a.3 | C80: 99 | D80: For Wetland Viaduct - Deck Slab casting | E80: Span | F80: Sualkuchi | G80: 3 | H80: MPSB/Str/5197 | I80: 46228 | J80: IPC - 34 | K80: 46232 | L80: PL9 to PL12 | M80: =K80-I80 -> 4
B81: 403.a | C81: 100 | D81: Construction of abutment / piers / lower pylon | E81: Rmt | F81: Sualkuchi | G81: 5.38 | H81: MPSB/Str/5235 | I81: 46233 | J81: IPC - 34 | K81: 46233 | L81: P26 - Lower Pylon - 4th Lift | M81: =K81-I81 -> 0
B82: 403.a | C82: 100 | D82: Construction of abutment / piers / lower pylon | E82: Rmt | F82: Sualkuchi | G82: 4 | H82: MPSB/Str/5231 | I82: 46233 | J82: IPC - 34 | K82: 46233 | L82: P29 - Lower Pylon - 2nd Lift | M82: =K82-I82 -> 0
B83: 406.a / 407.c | C83: 100 | D83: Precast - Box girder segments | E83: Nos. | F83: Palashbari | G83: 1 | H83: MPSB/MB/2218 | I83: 46231 | J83: IPC - 34 | K83: 46233 | L83: P9-BP-S08a-O | M83: =K83-I83 -> 2
B84: 406.a / 407.c | C84: 100 | D84: Precast - Box girder segments | E84: Nos. | F84: Palashbari | G84: 1 | H84: MPSB/MB/2210 | I84: 46230 | J84: IPC - 34 | K84: 46233 | L84: P16-KS-S13-M | M84: =K84-I84 -> 3
B85: 504.a.1 | C85: 101 | D85: For Wetland Viaduct - Casting of Girders in the precast yard | E85: Nos. | F85: Sualkuchi | G85: 1 | H85: MPSB/Str/5216 | I85: 46231 | J85: IPC - 34 | K85: 46233 | L85: WV1-P1-P2-G4 | M85: =K85-I85 -> 2
B86: 504.a.1 | C86: 101 | D86: For Wetland Viaduct - Casting of Girders in the precast yard | E86: Nos. | F86: Sualkuchi | G86: 1 | H86: MPSB/Str/5136 | I86: 46217 | J86: IPC - 34 | K86: 46219 | L86: WV1-P2-P3-G4 | M86: =K86-I86 -> 2
... B89: 505.a.3 | C89: 102 | D89: For Wetland Viaduct - Final stressing of Girders at site | E89: Nos. | F89: Sualkuchi | G89: 1 | H89: MPSB/Str/5226 | I89: 46232 | J89: IPC - 34 | K89: 46233 | L89: WV2-P1-P2-G1 | M89: =K89-I89 -> 1
A90: Final Technical Design of the approach formation, retaining structures, drainage system, bridges, major and /or minor structures and miscellaneous work | B90: 204.e.ii.3 | C90: 102 | D90: Approach Viaduct - Substructure - Issue of GFC Drawings | E90: Nos. | G90: 0.25 | H90: HBT/1624/SO/DGV/2026/1771 | I90: 46234 | J90: IPC - 34 | K90: 46234 | L90: 2 / 16 Nos. - Approved - SAV - P1R & P2R, NAV - P32R & P33R - Balance 50% released | M90: =K90-I90 -> 0
B91: 406.a / 407.c / 408.c | C91: 103 | D91: Precast - Box girder segments | E91: Nos. | F91: Palashbari | G91: 1 | H91: MPSB/MB/2232 | I91: 46233 | J91: IPC - 34 | K91: 46234 | L91: P15-BP-S15-O© | M91: =K91-I91 -> 1
B92: 406.a / 407.c / 408.c | C92: 103 | D92: Precast - Box girder segments | E92: Nos. | F92: Palashbari | G92: 1 | H92: MPSB/MB/2231 | I92: 46233 | J92: IPC - 34 | K92: 46234 | L92: P15-KS-S09a-O© | M92: =K92-I92 -> 1
B93: 406.a / 407.c / 408.c | C93: 103 | D93: Precast - Box girder segments | E93: Nos. | F93: Palashbari | G93: 1 | H93: MPSB/MB/2244 | I93: 46234 | J93: IPC - 34 | K93: 46234 | L93: P16-KS-S14-M© | M93: =K93-I93 -> 0
B94: 406.a / 407.c / 408.c | C94: 103 | D94: Precast - Box girder segments | E94: Nos. | F94: Sualkuchi | G94: 1 | H94: MPSB/MB/2238 | I94: 46234 | J94: IPC - 34 | K94: 46234 | L94: P19-KS-S09a-O© | M94: =K94-I94 -> 0
B95: 406.a / 407.c / 408.c | C95: 103 | D95: Precast - Box girder segments | E95: Nos. | F95: Sualkuchi | G95: 1 | H95: MPSB/MB/2239 | I95: 46234 | J95: IPC - 34 | K95: 46234 | L95: P21-BP-S31a-O© | M95: =K95-I95 -> 0
B96: 406.a / 407.c | C96: 104 | D96: Precast - Box girder segments | E96: Nos. | F96: Palashbari | G96: 1 | H96: MPSB/MB/2246 | I96: 46234 | J96: IPC - 34 | K96: 46234 | L96: P15-KS-S10a-O | M96: =K96-I96 -> 0
B97: 406.a / 407.c | C97: 104 | D97: Precast - Box girder segments | E97: Nos. | F97: Palashbari | G97: 1 | H97: MPSB/MB/2243 | I97: 46234 | J97: IPC - 34 | K97: 46234 | L97: P15-BP-S22-O | M97: =K97-I97 -> 0
B98: 406.a / 407.c | C98: 104 | D98: Precast - Box girder segments | E98: Nos. | F98: Sualkuchi | G98: 1 | H98: MPSB/MB/2235 | I98: 46233 | J98: IPC - 34 | K98: 46234 | L98: P21-BP-S30a-O | M98: =K98-I98 -> 1
B99: 406.a / 407.c | C99: 104 | D99: Precast - Box girder segments | E99: Nos. | F99: Sualkuchi | G99: 1 | H99: MPSB/MB/2225 | I99: 46232 | J99: IPC - 34 | K99: 46234 | L99: P24-KS-S03-M | M99: =K99-I99 -> 2
B100: 406.a / 407.c | C100: 104 | D100: Precast - Box girder segments | E100: Nos. | F100: Sualkuchi | G100: 1 | H100: MPSB/MB/2241 | I100: 46234 | J100: IPC - 34 | K100: 46234 | L100: P24-KS-S04-M | M100: =K100-I100 -> 0
B101: 502 & 503.b.2 | C101: 105 | D101: For Approach Viaduct - On completion of pier-cap / pier table | E101: Nos. | F101: Palashbari | G101: 1 | H101: MPSB/Str/5228 | I101: 46232 | J101: IPC - 34 | K101: 46234 | L101: Km 9+424 - PL36 - Piercap | M101: =K101-I101 -> 2
B102: 504.a.1 | C102: 105 | D102: For Wetland Viaduct - Casting of Girders in the precast yard | E102: Nos. | F102: Sualkuchi | G102: 1 | H102: MPSB/Str/5224 | I102: 46232 | J102: IPC - 34 | K102: 46234 | L102: WV1-P0-P1-G3 | M102: =K102-I102 -> 2
... B108: 506.a.1 | C108: 106 | D108: For Wetland Viaduct - Casting of Deck Panel | E108: Span | F108: Sualkuchi | G108: 1 | H108: MPSB/Str/5254 | I108: 46234 | J108: IPC - 34 | K108: 46234 | L108: PR16 to PR17 | M108: =K108-I108 -> 0
A109: Procurement, testing and supply of Stay Cables to site | B109: 408.b | C109: 107 | D109: Testing of Material | E109: MT | G109: 354.343 | H109: As per Annexures | J109: IPC - 34
Q645: 187.82

Sheet Schedule 1
C2: Construction of 4-lane Extra-dosed PSC Bridge over river Brahmaputra connecting Palashbari and Sualkuchi including Viaduct, Approaches and River Training works etc on EPC mode
H3: =CONCATENATE('Detailed breakup'!$O$4," ",'Detailed breakup'!$Q$4) -> Period of bill : 1st Jul'26 to 31st Jul'26
B4: Schedule 1 - Preliminaries and General Items | J4: ='Abs. - PMC (For Print)'!$D$4 -> IPC - 34
B5: Measurement Sheet
B6: Item No. | C6: Item Description | D6: UoM | E6: Location | F6: Executed Quantity | G6: RFI No. / Letter No. / Period | H6: Date | I6: Bill No. | J6: Remarks
B8: 101 | C8: Provision (construction) of office facilities for the Employer
B9: 101.a | C9: Foundation | D9: Nos. | E9: Palashbari | F9: 0.5 | G9: MPSB/Temp/2 | H9: 45450 | I9: IPC - 02
B10: 101.a | C10: Foundation | D10: Nos. | E10: Palashbari | F10: 0.5 | G10: MPSB/Temp/4 | H10: 45451 | I10: IPC - 02
B11: 101.a | C11: Foundation | D11: Nos. | E11: Sualkuchi | F11: 0.5 | G11: MPSB/Temp/15 | H11: 45456 | I11: IPC - 02
B12: 101.a | C12: Foundation | D12: Nos. | E12: Sualkuchi | F12: 0.5 | G12: MPSB/Temp/21 | H12: 45458 | I12: IPC - 02
C14: Cumulative paid upto this Bill | D14: Nos. | F14: =SUM(F9:F13) -> 2
C15: Paid upto previous Bill | D15: Nos. | F15: 2
C16: To be paid in this Bill | D16: Nos. | F16: =F14-F15 -> 0
B18: 101.b | C18: Plinth | D18: Nos. | E18: Palashbari | F18: 1 | G18: MPSB/Temp/5 | H18: 45453 | I18: IPC - 02
B19: 101.b | C19: Plinth | D19: Nos. | E19: Sualkuchi | F19: 1 | G19: MPSB/Temp/39 | H19: 45485 | I19: IPC - 03
C21: Cumulative paid upto this Bill | D21: Nos. | F21: =SUM(F18:F20) -> 2
C22: Paid upto previous Bill | D22: Nos. | F22: 2
C23: To be paid in this Bill | D23: Nos. | F23: =F21-F22 -> 0
B25: 101.c | C25: Walls | D25: Nos. | E25: Palashbari | F25: 1 | G25: MPSB/Temp/11 | H25: 45455 | I25: IPC - 02
B26: 101.c | C26: Walls | D26: Nos. | E26: Sualkuchi | F26: 1 | G26: MPSB/Temp/51 | H26: 45504 | I26: IPC - 03
C28: Cumulative paid upto this Bill | D28: Nos. | F28: =SUM(F25:F27) -> 2
C29: Paid upto previous Bill | D29: Nos. | F29: 2
C30: To be paid in this Bill | D30: Nos. | F30: =F28-F29 -> 0
B32: 101.d | C32: Roof | D32: Nos. | E32: Palashbari | F32: 1 | G32: MPSB/Temp/18 | H32: 45457 | I32: IPC - 02
B33: 101.d | C33: Roof | D33: Nos. | E33: Sualkuchi | F33: 1 | G33: MPSB/Temp/52 | H33: 45504 | I33: IPC - 03
C35: Cumulative paid upto this Bill | D35: Nos. | F35: =SUM(F32:F34) -> 2
C36: Paid upto previous Bill | D36: Nos. | F36: 2
C37: To be paid in this Bill | D37: Nos. | F37: =F35-F36 -> 0
B39: 101.e | C39: Flooring | D39: Nos. | E39: Palashbari | F39: 1 | G39: MPSB/Temp/24 | H39: 45459 | I39: IPC - 02
B40: 101.e | C40: Flooring | D40: Nos. | E40: Sualkuchi | F40: 1 | G40: MPSB/Temp/62 | H40: 45504 | I40: IPC - 03
C42: Cumulative paid upto this Bill | D42: Nos. | F42: =SUM(F39:F41) -> 2
C43: Paid upto previous Bill | D43: Nos. | F43: 2
C44: To be paid in this Bill | D44: Nos. | F44: =F42-F43 -> 0
B46: 101.f.i | C46: Finishing Works - Electrical & Sanitary Works | D46: Nos. | E46: Palashbari | F46: 1 | G46: MPSB/Temp/43 | H46: 45492 | I46: IPC - 03
B47: 101.f.i | C47: Finishing Works - Electrical & Sanitary Works | D47: Nos. | E47: Sualkuchi | F47: 0.9 | G47: MPSB/Temp/64 A | H47: 45526 | I47: IPC - 04
B48: 101.f.i | C48: Finishing Works - Electrical & Sanitary Works | D48: Nos. | E48: Sualkuchi | F48: 0.1 | G48: MPSB/Temp/87 | H48: 45563 | I48: IPC - 05
C50: Cumulative paid upto this Bill | D50: Nos. | F50: =SUM(F46:F49) -> 2
C51: Paid upto previous Bill | D51: Nos. | F51: 2
C52: To be paid in this Bill | D52: Nos. | F52: =F50-F51 -> 0
B54: 101.f.ii.1 | C54: Finishing Works - Office Furniture - Executive Office Desk | D54: Nos. | E54: Palashbari | F54: 4 | G54: MPSB/Temp/48 | H54: 45502 | I54: IPC - 03
B55: 101.f.ii.1 | C55: Finishing Works - Office Furniture - Executive Office Desk | D55: Nos. | E55: Sualkuchi | F55: 4 | G55: MPSB/Temp/74 | H55: 45533 | I55: IPC - 04
C57: Cumulative paid upto this Bill | D57: Nos. | F57: =SUM(F54:F56) -> 8
C58: Paid upto previous Bill | D58: Nos. | F58: 8
C59: To be paid in this Bill | D59: Nos. | F59: =F57-F58 -> 0
B61: 101.f.ii.2 | C61: Finishing Works - Office Furniture - Executive Chairs | D61: Nos. | E61: Palashbari | F61: 4 | G61: MPSB/Temp/48 | H61: 45502 | I61: IPC - 03
B62: 101.f.ii.2 | C62: Finishing Works - Office Furniture - Executive Chairs | D62: Nos. | E62: Sualkuchi | F62: 4 | G62: MPSB/Temp/74 | H62: 45533 | I62: IPC - 04
C64: Cumulative paid upto this Bill | D64: Nos. | F64: =SUM(F61:F63) -> 8
C65: Paid upto previous Bill | D65: Nos. | F65: 8
C66: To be paid in this Bill | D66: Nos. | F66: =F64-F65 -> 0
B68: 101.f.ii.3 | C68: Finishing Works - Office Furniture - Visitors Chairs | D68: Nos. | E68: Palashbari | F68: 20 | G68: MPSB/Temp/48 | H68: 45502 | I68: IPC - 03
C70: Cumulative paid upto this Bill | D70: Nos. | F70: =SUM(F68:F69) -> 20
C71: Paid upto previous Bill | D71: Nos. | F71: 20
C72: To be paid in this Bill | D72: Nos. | F72: =F70-F71 -> 0
B74: 101.f.ii.4 | C74: Finishing Works - Office Furniture - Conference Table | D74: Nos. | E74: Palashbari | F74: 2 | G74: MPSB/Temp/48 | H74: 45502 | I74: IPC - 03
C76: Cumulative paid upto this Bill | D76: Nos. | F76: =SUM(F74:F75) -> 2
C77: Paid upto previous Bill | D77: Nos. | F77: 2
C78: To be paid in this Bill | D78: Nos. | F78: =F76-F77 -> 0
B80: 101.f.ii.5 | C80: Finishing Works - Office Furniture - Conference Chairs | D80: Nos. | E80: Palashbari | F80: 60 | G80: MPSB/Temp/48 | H80: 45502 | I80: IPC - 03
C82: Cumulative paid upto this Bill | D82: Nos. | F82: =SUM(F80:F81) -> 60
C83: Paid upto previous Bill | D83: Nos. | F83: 60
C84: To be paid in this Bill | D84: Nos. | F84: =F82-F83 -> 0
B86: 101.f.ii.6 | C86: Finishing Works - Office Furniture - Projector and Monitor in Conference Room | D86: Nos. | E86: Palashbari | F86: 1 | G86: MPSB/Temp/78 | H86: 45534 | I86: IPC - 04
C88: Cumulative paid upto this Bill | D88: Nos. | F88: =SUM(F86:F87) -> 1
C89: Paid upto previous Bill | D89: Nos. | F89: 1
C90: To be paid in this Bill | D90: Nos. | F90: =F88-F89 -> 0
B92: 101.f.ii.7 | C92: Finishing Works - Office Furniture - Display Arrangement | D92: Nos. | E92: Palashbari | F92: 2 | G92: MPSB/Temp/78 | H92: 45534 | I92: IPC - 04
C94: Cumulative paid upto this Bill | D94: Nos. | F94: =SUM(F92:F93) -> 2
C95: Paid upto previous Bill | D95: Nos. | F95: 2
C96: To be paid in this Bill | D96: Nos. | F96: =F94-F95 -> 0
B98: 101.f.ii.8 | C98: Finishing Works - Office Furniture - Steel Almirah & Racks | D98: Nos. | E98: Palashbari | F98: 5 | G98: MPSB/Temp/48 | H98: 45502 | I98: IPC - 03
B99: 101.f.ii.8 | C99: Finishing Works - Office Furniture - Steel Almirah & Racks | D99: Nos. | E99: Sualkuchi | F99: 5 | G99: MPSB/Temp/74 | H99: 45533 | I99: IPC - 04
C101: Cumulative paid upto this Bill | D101: Nos. | F101: =SUM(F98:F100) -> 10
C102: Paid upto previous Bill | D102: Nos. | F102: 10
C103: To be paid in this Bill | D103: Nos. | F103: =F101-F102 -> 0
B105: 101.f.ii.9 | C105: Finishing Works - Office Furniture - Domestic Water Purifier | D105: Nos. | E105: Palashbari | F105: 1 | G105: MPSB/Temp/74 | H105: 45533 | I105: IPC - 04
B106: 101.f.ii.9 | C106: Finishing Works - Office Furniture - Domestic Water Purifier | D106: Nos. | E106: Sualkuchi | F106: 1 | G106: MPSB/Temp/78 | H106: 45534 | I106: IPC - 04
C108: Cumulative paid upto this Bill | D108: Nos. | F108: =SUM(F105:F107) -> 2
C109: Paid upto previous Bill | D109: Nos. | F109: 2
C110: To be paid in this Bill | D110: Nos. | F110: =F108-F109 -> 0
B112: 101.f.iii.1 | C112: Finishing Works - Office Equipment - Laptops | D112: Nos. | F112: 6 | G112: MPSB/Temp/80 | H112: 45535 | I112: IPC - 04
C114: Cumulative paid upto this Bill | D114: Nos. | F114: =SUM(F112:F113) -> 6
C115: Paid upto previous Bill | D115: Nos. | F115: 6
C116: To be paid in this Bill | D116: Nos. | F116: =F114-F115 -> 0
B118: 101.f.iii.2 | C118: Finishing Works - Office Equipment - Colour Printer | D118: Nos. | F118: 2 | G118: MPSB/Temp/80 | H118: 45535 | I118: IPC - 04
C120: Cumulative paid upto this Bill | D120: Nos. | F120: =SUM(F118:F119) -> 2
C121: Paid upto previous Bill | D121: Nos. | F121: 2
C122: To be paid in this Bill | D122: Nos. | F122: =F120-F121 -> 0
B124: 102 | C124: Provision (construction) of contractor’s site office, site laboratories, labor camps etc
B125: 102.a.i | C125: Foundation - Office | D125: Nos. | E125: Palashbari | F125: 0.5 | G125: MPSB/Temp/1 | H125: 45450 | I125: IPC - 02
B126: 102.a.i | C126: Foundation - Office | D126: Nos. | E126: Palashbari | F126: 0.5 | G126: MPSB/Temp/3 | H126: 45451 | I126: IPC - 02
C128: Cumulative paid upto this Bill | D128: Nos. | F128: =SUM(F125:F127) -> 1
C129: Paid upto previous Bill | D129: Nos. | F129: 1
C130: To be paid in this Bill | D130: Nos. | F130: =F128-F129 -> 0
B132: 102.a.ii | C132: Foundation - Laboratory | D132: Nos. | E132: Palashbari | F132: 1 | G132: MPSB/Temp/54 | H132: 45504 | I132: IPC - 03
B133: 102.a.ii | C133: Foundation - Laboratory | D133: Nos. | E133: Sualkuchi | F133: 1 | G133: MPSB/Temp/82 | H133: 45562 | I133: IPC - 05
C135: Cumulative paid upto this Bill | D135: Nos. | F135: =SUM(F132:F134) -> 2
C136: Paid upto previous Bill | D136: Nos. | F136: 2
C137: To be paid in this Bill | D137: Nos. | F137: =F135-F136 -> 0
B139: 102.a.iii.1 | C139: Foundation - Labour Camp - Building | D139: Nos. | E139: Palashbari | F139: 0.5 | G139: MPSB/Temp/6 | H139: 45453 | I139: IPC - 02
B140: 102.a.iii.1 | C140: Foundation - Labour Camp - Building | D140: Nos. | E140: Sualkuchi | F140: 0.5 | G140: MPSB/Temp/9 | H140: 45454 | I140: IPC - 02
...

Sheet Schedule 2
C2: Construction of 4-lane Extra-dosed PSC Bridge over river Brahmaputra connecting Palashbari and Sualkuchi including Viaduct, Approaches and River Training works etc on EPC mode
H3: ='Schedule 1'!H3 -> Period of bill : 1st Jul'26 to 31st Jul'26
B4: Schedule 2 - Validation of Survey Data, Investigation, Design and As-Built Drawings | J4: ='Schedule 1'!J4 -> IPC - 34
B5: Measurement Sheet
B6: Item No. | C6: Item Description | D6: UoM | E6: Location | F6: Executed Quantity | G6: RFI No. / Letter No. / Period | H6: Date | I6: Bill No. | J6: Remarks
B8: 201 | C8: Site survey, establishment of bench marks, validation of ROW, identification of borrow areas
B9: 201.a | C9: Establishment of Bench Marks | D9: Kms | F9: 12.21 | G9: MPSB/SUR/1 | H9: 45450 | I9: IPC - 02
C11: Cumulative paid upto this Bill | D11: Kms | F11: =ROUND(SUM(F9:F10),3) -> 12.21
C12: Paid upto previous Bill | D12: Kms | F12: =12.21 -> 12.21
C13: To be paid in this Bill | D13: Kms | F13: =F11-F12 -> 0
B15: 201.b | C15: Completion of Site Survey | D15: Kms | F15: 12.21 | G15: MPSB/SUR/3 | H15: 45458 | I15: IPC - 02
C17: Cumulative paid upto this Bill | D17: Kms | F17: =ROUND(SUM(F15:F16),3) -> 12.21
C18: Paid upto previous Bill | D18: Kms | F18: =12.21 -> 12.21
C19: To be paid in this Bill | D19: Kms | F19: =F17-F18 -> 0
B21: 201.c | C21: Validation of ROW | D21: Kms | F21: =5.6 -> 5.6 | G21: MPSB/SUR/4 | H21: 45461 | I21: IPC - 02
B22: 201.c | C22: Validation of ROW | D22: Kms | F22: =12.21-F21 -> 6.61 | G22: MPSB/SUR/5 | H22: 45462 | I22: IPC - 02
C24: Cumulative paid upto this Bill | D24: Kms | F24: =ROUND(SUM(F21:F23),3) -> 12.21
C25: Paid upto previous Bill | D25: Kms | F25: =12.21 -> 12.21
C26: To be paid in this Bill | D26: Kms | F26: =F24-F25 -> 0
B28: 201.d | C28: Identification of Borrow Areas | D28: Nos. | F28: 2 | G28: GM/MM/86-B(40)/Pt.VIII/214-17 GM/MM/86-B(40)/Pt. V/388-92 | H28: 31-May-24 06-Jun-24 | I28: IPC - 03
B29: 201.d | C29: Identification of Borrow Areas | D29: Nos. | F29: 3 | G29: GM/MM/86-B(40)/Pt. V/378-82 GM/MM/86-B(40)/Pt.VIII/383-87 GM/MM/86-B(40)/Pt.VIII/373-77 | H29: 06-Jun-24 06-Jun-24 06-Jun-24 | I29: IPC - 04
C31: Cumulative paid upto this Bill | D31: Nos. | F31: =ROUND(SUM(F28:F30),3) -> 5
C32: Paid upto previous Bill | D32: Nos. | F32: 5
C33: To be paid in this Bill | D33: Nos. | F33: =F31-F32 -> 0
B35: 202 | C35: Site data collection, Detailed Geotechnical and Hydrological investigations and report submission & approval
B36: 202.a.i | C36: Completion of Topographical Survey - Submission | D36: Kms | F36: 12.21 | G36: MPSB/SUR/2 | H36: 45455 | I36: IPC - 02
C38: Cumulative paid upto this Bill | D38: Kms | F38: =ROUND(SUM(F36:F37),3) -> 12.21
C39: Paid upto previous Bill | D39: Kms | F39: 12.21
C40: To be paid in this Bill | D40: Kms | F40: =F38-F39 -> 0
B42: 202.a.ii | C42: Completion of Topographical Survey - Approval | D42: Kms | F42: 12.21 | G42: RI-1624-SO-HWB-BR-S&I-0010-R0-254 | H42: 45516 | I42: IPC - 04
C44: Cumulative paid upto this Bill | D44: Kms | F44: =ROUND(SUM(F42:F43),3) -> 12.21
C45: Paid upto previous Bill | D45: Kms | F45: 12.21
C46: To be paid in this Bill | D46: Kms | F46: =F44-F45 -> 0
B48: 202.b.i | C48: Detailed Geotechnical Investigation - Submission | D48: Nos. | F48: 2 | G48: MPSB/QAQC/1 | H48: 45450 | I48: IPC - 02
B49: 202.b.i | C49: Detailed Geotechnical Investigation - Submission | D49: Nos. | F49: 3 | G49: MPSB/QAQC/2 | H49: 45451 | I49: IPC - 02
B50: 202.b.i | C50: Detailed Geotechnical Investigation - Submission | D50: Nos. | F50: 4 | G50: MPSB/QAQC/3 | H50: 45453 | I50: IPC - 02
B51: 202.b.i | C51: Detailed Geotechnical Investigation - Submission | D51: Nos. | F51: 1 | G51: MPSB/QAQC/4 | H51: 45454 | I51: IPC - 02
B52: 202.b.i | C52: Detailed Geotechnical Investigation - Submission | D52: Nos. | F52: 5 | G52: MPSB/QAQC/5 | H52: 45455 | I52: IPC - 02
B53: 202.b.i | C53: Detailed Geotechnical Investigation - Submission | D53: Nos. | F53: 5 | G53: MPSB/QAQC/6 | H53: 45456 | I53: IPC - 02
B54: 202.b.i | C54: Detailed Geotechnical Investigation - Submission | D54: Nos. | F54: 5 | G54: MPSB/QAQC/7 | H54: 45457 | I54: IPC - 02
B55: 202.b.i | C55: Detailed Geotechnical Investigation - Submission | D55: Nos. | F55: 5 | G55: MPSB/QAQC/8 | H55: 45458 | I55: IPC - 02
B56: 202.b.i | C56: Detailed Geotechnical Investigation - Submission | D56: Nos. | F56: 2 | G56: MPSB/QAQC/9 | H56: 45460 | I56: IPC - 02
B57: 202.b.i | C57: Detailed Geotechnical Investigation - Submission | D57: Nos. | F57: 2 | G57: MPSB/QAQC/10 | H57: 45461 | I57: IPC - 02
B58: 202.b.i | C58: Detailed Geotechnical Investigation - Submission | D58: Nos. | F58: 2 | G58: MPSB/QAQC/11 | H58: 45462 | I58: IPC - 02
B59: 202.b.i | C59: Detailed Geotechnical Investigation - Submission | D59: Nos. | F59: 2 | G59: MPSB/QAQC/12 | H59: 45463 | I59: IPC - 02
... B69: 202.b.i | C69: Detailed Geotechnical Investigation - Submission | D69: Nos. | F69: 25 | G69: MPSB/L&T/TIIC/2024/260 | H69: 45504 | I69: IPC - 03
C71: Cumulative paid upto this Bill | D71: Nos. | F71: =ROUND(SUM(F48:F70),3) -> 96
C72: Paid upto previous Bill | D72: Nos. | F72: 96
C73: To be paid in this Bill | D73: Nos. | F73: =F71-F72 -> 0
B75: 202.b.ii | C75: Detailed Geotechnical Investigation - Approval | D75: Nos. | F75: 9 | G75: HBT/1624/SO/APR/2024/0220/415 | H75: 45593 | I75: IPC - 08 | J75: P10 to P18
B76: 202.b.ii | C76: Detailed Geotechnical Investigation - Approval | D76: Nos. | F76: 7 | G76: HBT/1624/SO/APR/2024/0251/445 | H76: 45608 | I76: IPC - 08 | J76: P19 to P26
B77: 202.b.ii | C77: Detailed Geotechnical Investigation - Approval | D77: Nos. | F77: 10 | G77: HBT/1624/SO/GIR/2024/0265/459 | H77: 45611 | I77: IPC - 08 | J77: Northern & Southern Viaduct
B78: 202.b.ii | C78: Detailed Geotechnical Investigation - Approval | D78: Nos. | F78: 1 | G78: HBT/1624/SO/APR/2024/0251/445 | H78: 45608 | I78: IPC - 11 | J78: P19 to P26
B79: 202.b.ii | C79: Detailed Geotechnical Investigation - Approval | D79: Nos. | F79: 4 | G79: HBT/1624/SO/APR/2024/0310/503 | H79: 45629 | I79: IPC - 11 | J79: P6 to P9
B80: 202.b.ii | C80: Detailed Geotechnical Investigation - Approval | D80: Nos. | F80: 4 | G80: HBT/1624/SO/APR/2024/0319/512 | H80: 45636 | I80: IPC - 11 | J80: P27 to P30
B81: 202.b.ii | C81: Detailed Geotechnical Investigation - Approval | D81: Nos. | F81: 26 | G81: HBT/1624/SO/GIR/2025/0378/569 | H81: 45660 | I81: IPC - 11 | J81: Wetland Viaducts
B82: 202.b.ii | C82: Detailed Geotechnical Investigation - Approval | D82: Nos. | F82: 2 | G82: HBT/1624/SO/GIR/2025/703 | H82: 45815 | I82: IPC - 16 | J82: P4 & P5
B83: 202.b.ii | C83: Detailed Geotechnical Investigation - Approval | D83: Nos. | F83: 4 | G83: HBT/1624/SO/GIR/2024/0265/459 | H83: 45611 | I83: IPC - 16 | J83: Rescue Span
B84: 202.b.ii | C84: Detailed Geotechnical Investigation - Approval | D84: Nos. | F84: 17 | G84: HBT/1624/SO/GIR/2025/712 HBT/1624/SO/GIR/2025/714 | H84: 45815 | I84: IPC - 16 | J84: Approach Formations
B85: 202.b.ii | C85: Detailed Geotechnical Investigation - Approval | D85: Nos. | F85: 4 | G85: HBT/1624/SO/GIR/2025/780 | H85: 4-Jul-25 | I85: IPC - 18 | J85: VUP
B86: 202.b.ii | C86: Detailed Geotechnical Investigation - Approval | D86: Nos. | F86: 2 | G86: HBT/1624/SO/GIR/2025/815 | H86: 15-Jul-25 | I86: IPC - 18 | J86: VUP
B87: 202.b.ii | C87: Detailed Geotechnical Investigation - Approval | D87: Nos. | F87: 6 | G87: HBT/1624/SO/GDV/2025/844 HBT/1624/SO/GDV/2025/865 | H87: 26-Jul-25 31-Jul-25 | I87: IPC - 18 | J87: Approach Formations
C89: Cumulative paid upto this Bill | D89: Nos. | F89: =ROUND(SUM(F75:F88),3) -> 96
C90: Paid upto previous Bill | D90: Nos. | F90: 96
C91: To be paid in this Bill | D91: Nos. | F91: =F89-F90 -> 0
B93: 202.c.i | C93: Detailed Hydrological Investigation - Submission | D93: LS | F93: 1 | G93: MPSB/L&T/TIIC/DGN/2024/033 | H93: 45546 | I93: IPC - 05
C95: Cumulative paid upto this Bill | D95: LS | F95: =ROUND(SUM(F93:F94),3) -> 1
C96: Paid upto previous Bill | D96: LS | F96: 1
C97: To be paid in this Bill | D97: LS | F97: =F95-F96 -> 0
B99: 203 | C99: Preliminary Design of the approach formations, retaining structures, drainage system, bridges, major and /or minor structure and miscellaneous work.
B100: 203.a.i | C100: Approach Formations (GAD / P&P) - Submission | D100: Kms | F100: 7.314 | G100: MPSB/L&T/TIIC/DGN/2024/022 | H100: 45534 | I100: IPC - 04
C102: Cumulative paid upto this Bill | D102: Kms | F102: =ROUND(SUM(F100:F101),3) -> 7.314
C103: Paid upto previous Bill | D103: Kms | F103: 7.314
C104: To be paid in this Bill | D104: Kms | F104: =F102-F103 -> 0
B106: 203.a.ii | C106: Approach Formations (GAD / P&P) - Approval | D106: Kms | F106: =7.314-(2*0.012+1*0.036)-Q113 -> 5.321 | G106: HBT/1624/SO/APR/2024/0167/362 | H106: 45565 | I106: IPC - 05 | K106: 0 | L106: 5392 | M106: =(L106-K106)/1000 -> 5.392 | O106: 800 | P106: 1300 | Q106: =(P106-O106)/1000 -> 0.5
B107: 203.a.ii | C107: Approach Formations (GAD / P&P) - Approval | D107: Kms | F107: 1.993 | G107: HBT/1624/SO/APR/2024/0256/450 HBT/1624/SO/APR/2024/0279/473 | H107: 12-Nov-24 18-Nov-24 | I107: IPC - 08 | K107: 9424 | L107: 10217 | M107: =(L107-K107)/1000 -> 0.793 | O107: 2600 | P107: 3052 | Q107: =(P107-O107)/1000 -> 0.452
K108: 10325 | L108: 10600 | M108: =(L108-K108)/1000 -> 0.275 | O108: 4220 | P108: 4480 | Q108: =(P108-O108)/1000 -> 0.26
C109: Cumulative paid upto this Bill | D109: Kms | F109: =ROUND(SUM(F106:F108),3) -> 7.314 | K109: 11356 | L109: 12210 | M109: =(L109-K109)/1000 -> 0.854 | O109: 4515 | P109: 4750 | Q109: =(P109-O109)/1000 -> 0.235
C110: Paid upto previous Bill | D110: Kms | F110: 7.314 | M110: =SUM(M106:M109) -> 7.314 | O110: 4750 | P110: 4780 | Q110: =(P110-O110)/1000 -> 0.03
C111: To be paid in this Bill | D111: Kms | F111: =F109-F110 -> 0 | O111: 9424 | P111: 9880 | Q111: =(P111-O111)/1000 -> 0.456
B113: 203.b.i | C113: Retaining Structures (GAD / P&P) - Submission | D113: Kms | F113: 5.2 | G113: MPSB/L&T/TIIC/DGN/2025/473 | H113: 45982 | I113: IPC - 23 | Q113: =SUM(Q106:Q111) -> 1.933
C115: Cumulative paid upto this Bill | D115: Kms | F115: =ROUND(SUM(F113:F114),3) -> 5.2
C116: Paid upto previous Bill | D116: Kms | F116: 5.2
C117: To be paid in this Bill | D117: Kms | F117: =F115-F116 -> 0
B119: 203.b.iI | C119: Retaining Structures - Documents & Reports - Approval | D119: Kms | F119: 1 | G119: HBT/1624/SO/DGV/2026/1511 | H119: 46112 | I119: IPC - 29 | J119: Toe Wall | Q119: =SUM(Q111:Q116) -> 2.389
B120: 203.b.iI | C120: Retaining Structures - Documents & Reports - Approval | D120: Kms | F120: 4.2 | G120: HBT/1624/SO/DGV/2025/1164 HBT/1624/SO/DGV/2025/1142 HBT/1624/SO/DGV/2025/1139 | H120: 13-Nov-25 8-Nov-25 8-Nov-25 | I120: IPC - 29 | J120: Box Culvert - R/W VUP - R/W
C122: Cumulative paid upto this Bill | D122: Kms | F122: =ROUND(SUM(F119:F121),3) -> 5.2
C123: Paid upto previous Bill | D123: Kms | F123: 5.2
C124: To be paid in this Bill | D124: Kms | F124: =F122-F123 -> 0
B126: 203.c.i | C126: Drainage (GAD / P&P) - Submission | D126: Kms | F126: 0.68 | G126: MPSB/L&T/TIIC/DGN/2024/64 | H126: 45603 | I126: IPC - 09
O127: 300 | P127: 800 | Q127: =P127-O127 -> 500
C128: Cumulative paid upto this Bill | D128: Kms | F128: =ROUND(SUM(F126:F127),3) -> 0.68 | O128: 950 | P128: 1130 | Q128: =P128-O128 -> 180
C129: Paid upto previous Bill | D129: Kms | F129: 0.68 | O129: 800 | P129: 950 | Q129: =P129-O129 -> 150
C130: To be paid in this Bill | D130: Kms | F130: =F128-F129 -> 0 | Q130: =SUM(Q127:Q129) -> 830
B132: 203.c.ii | C132: Drainage (GAD / P&P) - Approval | D132: Kms | F132: 0.68 | G132: HBT/1624/SO/APR/2024/0368/559 | H132: 45654 | I132: IPC - 09
C134: Cumulative paid upto this Bill | D134: Kms | F134: =ROUND(SUM(F132:F133),3) -> 0.68
C135: Paid upto previous Bill | D135: Kms | F135: 0.68
C136: To be paid in this Bill | D136: Kms | F136: =F134-F135 -> 0
B138: 203.d.i | C138: Wetland Viaduct (GAD / P&P) - Submission | D138: Nos. | F138: 2 | G138: MPSB/L&T/TIIC/DGN/2024/026 | H138: 45535 | I138: IPC - 04
C140: Cumulative paid upto this Bill | D140: Nos. | F140: =ROUND(SUM(F138:F139),3) -> 2
...

Sheet Schedule 3
C2: Construction of 4-lane Extra-dosed PSC Bridge over river Brahmaputra connecting Palashbari and Sualkuchi including Viaduct, Approaches and River Training works etc on EPC mode
H3: ='Schedule 2'!H3 -> Period of bill : 1st Jul'26 to 31st Jul'26
B4: Schedule 3 - Enabling Works for Main Works | J4: ='Schedule 1'!J4 -> IPC - 34
B5: Measurement Sheet
B6: Item No. | C6: Item Description | D6: UoM | E6: Location | F6: Executed Quantity | G6: RFI No. / Letter No. / Period | H6: Date | I6: Bill No. | J6: Remarks
B8: 301 | C8: Construction of temporary jetties/ platforms (TAB) / load out jetties etc for marine working
B9: 301.a | C9: Supply of TAB material at site | D9: MT | E9: Palashbari | F9: 1929.425 | G9: MPSB/Temp/7 | H9: 45453 | I9: IPC - 02
B10: 301.a | C10: Supply of TAB material at site | D10: MT | E10: Sualkuchi | F10: 1353.325 | G10: MPSB/Temp/10 | H10: 45454 | I10: IPC - 02
B11: 301.a | C11: Supply of TAB material at site | D11: MT | E11: Palashbari | F11: 616.6281 | G11: MPSB/Temp/49 | H11: 45502 | I11: IPC - 03
C13: Cumulative paid upto this Bill | D13: MT | F13: =SUM(F9:F12) -> 3899.3781
C14: Paid upto previous Bill | D14: MT | F14: 3899.3781
C15: To be paid in this Bill | D15: MT | F15: =F13-F14 -> 0
B17: 301.b | C17: Installation of TAB | D17: Rmt | E17: Palashbari | F17: 174.4 | G17: MPSB/Temp/72 | H17: 45533 | I17: IPC - 04 | J17: Km 5+558.6 - Km 5+733
B18: 301.b | C18: Installation of TAB | D18: Rmt | E18: Sualkuchi | F18: 36 | G18: MPSB/Temp/79 | H18: 45535 | I18: IPC - 04 | J18: Km 9+216 - Km 9+180
B19: 301.b | C19: Installation of TAB | D19: Rmt | E19: Palashbari | F19: =5756-5733 -> 23 | G19: MPSB/Temp/92 | H19: 45563 | I19: IPC - 05 | J19: Km 5+733 - Km 5+756
B20: 301.b | C20: Installation of TAB | D20: Rmt | E20: Palashbari | F20: =5781-5756 -> 25 | G20: MPSB/Temp/95 | H20: 45565 | I20: IPC - 05 | J20: Km 5+756 - Km 5+781
B21: 301.b | C21: Installation of TAB | D21: Rmt | E21: Sualkuchi | F21: =9182-9159 -> 23 | G21: MPSB/Temp/81 | H21: 45546 | I21: IPC - 05 | J21: Km 9+182 - Km 9+159
B22: 301.b | C22: Installation of TAB | D22: Rmt | E22: Sualkuchi | F22: =9159-9105 -> 54 | G22: MPSB/Temp/91 | H22: 45563 | I22: IPC - 05 | J22: Km 9+159 - Km 9+105
B23: 301.b | C23: Installation of TAB | D23: Rmt | E23: Sualkuchi | F23: =9105-9092 -> 13 | G23: MPSB/Temp/96 | H23: 45565 | I23: IPC - 05 | J23: Km 9+105 - Km 9+092
B24: 301.b | C24: Installation of TAB | D24: Rmt | E24: Sualkuchi | F24: =9080-9017.5 -> 62.5 | G24: MPSB/Temp/100 | H24: 45594 | I24: IPC - 07 | J24: Km 9+092 - Km 9+107.5
B25: 301.b | C25: Installation of TAB | D25: Rmt | E25: Palashbari | F25: =5829-5781 -> 48 | G25: MPSB/Temp/102 | H25: 45594 | I25: IPC - 07 | J25: Km 5+781 - Km 5+829
B26: 301.b | C26: Installation of TAB | D26: Rmt | E26: Sualkuchi | F26: =9017.5-8992 -> 25.5 | G26: MPSB/Temp/103 | H26: 45596 | I26: IPC - 07 | J26: Km 9+107.5 - Km 8+992
B27: 301.b | C27: Installation of TAB | D27: Rmt | E27: Palashbari | F27: =5854-5829 -> 25 | G27: MPSB/Temp/104 | H27: 45596 | I27: IPC - 07 | J27: Km 5+829 - Km 5+854
B28: 301.b | C28: Installation of TAB | D28: Rmt | E28: Sualkuchi | F28: =8992-8956 -> 36 | G28: MPSB/Temp/109 | H28: 45611 | I28: IPC - 08 | J28: Km 8+992 - Km 8+956
B29: 301.b | C29: Installation of TAB | D29: Rmt | E29: Palashbari | F29: =5929-5854 -> 75 | G29: MPSB/Temp/110 | H29: 45624 | I29: IPC - 08 | J29: Km 5+854 - Km 5+929
B30: 301.b | C30: Installation of TAB | D30: Rmt | E30: Sualkuchi | F30: =8879.9-8857.9 -> 22 | G30: MPSB/Temp/113 | H30: 45626 | I30: IPC - 08 | J30: Km 8+879.9 - Km 8+857.9
B31: 301.b | C31: Installation of TAB | D31: Rmt | E31: Palashbari | F31: =5959-5929.4 -> 29.6 | G31: MPSB/Temp/114 | H31: 45626 | I31: IPC - 08 | J31: Km 5+929 - Km 5+959
C33: Cumulative paid upto this Bill | D33: Rmt | F33: =SUM(F17:F32) -> 672
C34: Paid upto previous Bill | D34: Rmt | F34: 672
C35: To be paid in this Bill | D35: Rmt | F35: =F33-F34 -> 0
B37: 302 | C37: Establishment of batching plant, crusher (if any), rebar yards, formwork shops, fabrication shops etc for main works
B38: 302.a.i | C38: Establishment of Batching Plants - Receipt of Equipment | D38: Nos. | E38: Palashbari | F38: 2 | G38: MPSB/Gen/1 | H38: 45454 | I38: IPC - 02
B39: 302.a.i | C39: Establishment of Batching Plants - Receipt of Equipment | D39: Nos. | E39: Sualkuchi | F39: 2 | G39: MPSB/Gen/3 | H39: 45462 | I39: IPC - 02
C41: Cumulative paid upto this Bill | D41: Nos. | F41: =SUM(F38:F40) -> 4
C42: Paid upto previous Bill | D42: Nos. | F42: 4
C43: To be paid in this Bill | D43: Nos. | F43: =F41-F42 -> 0
A45: c | B45: 302.a.ii | C45: Establishment of Batching Plants - Foundation | D45: Nos. | E45: Sualkuchi | F45: 1 | G45: MPSB/Gen/5 | H45: 45473 | I45: IPC - 02
B46: 302.a.ii | C46: Establishment of Batching Plants - Foundation | D46: Nos. | E46: Palashbari | F46: 1 | G46: MPSB/Gen/6 | H46: 45473 | I46: IPC - 02
B47: 302.a.ii | C47: Establishment of Batching Plants - Foundation | D47: Nos. | E47: Sualkuchi | F47: 1 | G47: MPSB/Gen/10 | H47: 45688 | I47: IPC - 10
B48: 302.a.ii | C48: Establishment of Batching Plants - Foundation | D48: Nos. | E48: Palashbari | F48: 1 | G48: MPSB/Gen/12 | H48: 45702 | I48: IPC - 11
C50: Cumulative paid upto this Bill | D50: Nos. | F50: =SUM(F45:F49) -> 4
C51: Paid upto previous Bill | D51: Nos. | F51: 4
C52: To be paid in this Bill | D52: Nos. | F52: =F50-F51 -> 0
A54: c | B54: 302.a.iii | C54: Establishment of Batching Plants - Installation and Commissioning | D54: Nos. | E54: Palashbari | F54: 1 | G54: MPSB/Gen/8 | H54: 45626 | I54: IPC - 08
B55: 302.a.iii | C55: Establishment of Batching Plants - Installation and Commissioning | D55: Nos. | E55: Sualkuchi | F55: 1 | G55: MPSB/Gen/11 | H55: 45688 | I55: IPC - 10
B56: 302.a.iii | C56: Establishment of Batching Plants - Installation and Commissioning | D56: Nos. | E56: Palashbari | F56: 1 | G56: MPSB/Gen/16 | H56: 45716 | I56: IPC - 11
B57: 302.a.iii | C57: Establishment of Batching Plants - Installation and Commissioning | D57: Nos. | E57: Sualkuchi | F57: 1 | G57: MPSB/Gen/15 | H57: 45716 | I57: IPC - 11
C59: Cumulative paid upto this Bill | D59: Nos. | F59: =SUM(F54:F58) -> 4
C60: Paid upto previous Bill | D60: Nos. | F60: 4
C61: To be paid in this Bill | D61: Nos. | F61: =F59-F60 -> 0
B63: 302.b.i | C63: Establishment of Crusher Plant - Receipt of Equipment | D63: Nos. | E63: Rangia | F63: 1 | G63: MPSB/Gen/7 | H63: 45625 | I63: IPC - 08
C65: Cumulative paid upto this Bill | D65: Nos. | F65: =SUM(F63:F64) -> 1
C66: Paid upto previous Bill | D66: Nos. | F66: 1
C67: To be paid in this Bill | D67: Nos. | F67: =F65-F66 -> 0
B69: 302.b.ii | C69: Establishment of Crusher Plant - Foundation | D69: Nos. | E69: Rangia | F69: 1 | G69: MPSB/Temp/112 | H69: 45625 | I69: IPC - 08
C71: Cumulative paid upto this Bill | D71: Nos. | F71: =SUM(F69:F70) -> 1
C72: Paid upto previous Bill | D72: Nos. | F72: 1
C73: To be paid in this Bill | D73: Nos. | F73: =F71-F72 -> 0
B75: 302.b.iii | C75: Establishment of Crusher Plant - Installation and Commissioning | D75: Nos. | E75: Rangia | F75: 1 | G75: MPSB/Temp/148 | H75: 45747 | I75: IPC - 13
C77: Cumulative paid upto this Bill | D77: Nos. | F77: =SUM(F75:F76) -> 1
C78: Paid upto previous Bill | D78: Nos. | F78: 1
C79: To be paid in this Bill | D79: Nos. | F79: =F77-F78 -> 0
B81: 302.c | C81: Commissioning of Rebar Yard | D81: Nos. | E81: Palashbari | F81: 1 | G81: MPSB/Temp/105 | H81: 45596 | I81: IPC - 07
B82: 302.c | C82: Commissioning of Rebar Yard | D82: Nos. | E82: Sualkuchi | F82: 1 | G82: MPSB/Temp/107 | H82: 45596 | I82: IPC - 07
C84: Cumulative paid upto this Bill | D84: Nos. | F84: =SUM(F81:F83) -> 2
C85: Paid upto previous Bill | D85: Nos. | F85: 2
C86: To be paid in this Bill | D86: Nos. | F86: =F84-F85 -> 0
B88: 302.d | C88: Commissioning of Formwork Yard | D88: Nos. | E88: Palashbari | F88: 1 | G88: MPSB/Temp/106 | H88: 45596 | I88: IPC - 07
B89: 302.d | C89: Commissioning of Formwork Yard | D89: Nos. | E89: Sualkuchi | F89: 1 | G89: MPSB/Temp/108 | H89: 45596 | I89: IPC - 07
C91: Cumulative paid upto this Bill | D91: Nos. | F91: =SUM(F88:F90) -> 2
C92: Paid upto previous Bill | D92: Nos. | F92: 2
C93: To be paid in this Bill | D93: Nos. | F93: =F91-F92 -> 0
B95: 302.e | C95: Commissioning of Fabrication Yard | D95: Nos. | E95: Palashbari | F95: 1 | G95: MPSB/Temp/47 | H95: 45500 | I95: IPC - 03
C97: Cumulative paid upto this Bill | D97: Nos. | F97: =SUM(F95:F96) -> 1
C98: Paid upto previous Bill | D98: Nos. | F98: 1
C99: To be paid in this Bill | D99: Nos. | F99: =F97-F98 -> 0
B101: 303 | C101: Establishment of Casting yards for casting of PSC Box girders, I-Girders etc as per requirement
B102: 303.a.i | C102: Construction of Casting Yard - Area Development | D102: Nos. | E102: Palashbari | F102: 0.75 | G102: MPSB/Temp/126 | H102: 45656 | I102: IPC - 09
B103: 303.a.i | C103: Construction of Casting Yard - Area Development | D103: Nos. | E103: Palashbari | F103: 0.25 | G103: MPSB/Temp/129 | H103: 45688 | I103: IPC - 10
B104: 303.a.i | C104: Construction of Casting Yard - Area Development | D104: Nos. | E104: Sualkuchi | F104: 0.75 | G104: MPSB/Temp/128 | H104: 45688 | I104: IPC - 10 | K104: RFI to be adjusted
B105: 303.a.i | C105: Construction of Casting Yard - Area Development | D105: Nos. | E105: Sualkuchi | F105: 0.25 | G105: MPSB/Temp/133 | H105: 45716 | I105: IPC - 11
C107: Cumulative paid upto this Bill | D107: Nos. | F107: =SUM(F102:F106) -> 2
C108: Paid upto previous Bill | D108: Nos. | F108: 2
C109: To be paid in this Bill | D109: Nos. | F109: =F107-F108 -> 0
B111: 303.a.ii | C111: Construction of Casting Yard - Foundation of Gantry | D111: Nos. | E111: Palashbari | F111: =600/1600 -> 0.375 | G111: MPSB/Temp/134 | H111: 45716 | I111: IPC - 11 | J111: 600 / 1600 Rmt
B112: 303.a.ii | C112: Construction of Casting Yard - Foundation of Gantry | D112: Nos. | E112: Sualkuchi | F112: =250/1600 -> 0.15625 | G112: MPSB/Temp/135 | H112: 45716 | I112: IPC - 11 | J112: 250 / 1600 Rmt
B113: 303.a.ii | C113: Construction of Casting Yard - Foundation of Gantry | D113: Nos. | E113: Palashbari | F113: =600/1600 -> 0.375 | G113: MPSB/Temp/140 | H113: 45744 | I113: IPC - 13 | J113: 600 / 1600 Rmt
B114: 303.a.ii | C114: Construction of Casting Yard - Foundation of Gantry | D114: Nos. | E114: Sualkuchi | F114: =750/1600 -> 0.46875 | G114: MPSB/Temp/141 MPSB/Temp/142 | H114: 28-Mar-25 31-Mar-25 | I114: IPC - 13 | J114: 750 / 1600 Rmt
B115: 303.a.ii | C115: Construction of Casting Yard - Foundation of Gantry | D115: Nos. | E115: Palashbari | F115: =400/1600 -> 0.25 | G115: MPSB/Temp/159 | H115: 45777 | I115: IPC - 14 | J115: 400 / 1600 Rmt
B116: 303.a.ii | C116: Construction of Casting Yard - Foundation of Gantry | D116: Nos. | E116: Sualkuchi | F116: =350/1600 -> 0.21875 | G116: MPSB/Str/1345 | H116: 45777 | I116: IPC - 14 | J116: 350 / 1600 Rmt
B117: 303.a.ii | C117: Construction of Casting Yard - Foundation of Gantry | D117: Nos. | E117: Sualkuchi | F117: =250/1600 -> 0.15625 | G117: MPSB/Temp/183 | H117: 45838 | I117: IPC - 16 | J117: 250 / 1600 Rmt
C119: Cumulative paid upto this Bill | D119: Nos. | F119: =ROUND(SUM(F111:F118),0) -> 2
C120: Paid upto previous Bill | D120: Nos. | F120: 2
C121: To be paid in this Bill | D121: Nos. | F121: =F119-F120 -> 0
B123: 303.a.iii | C123: Construction of Casting Yard - Casting Bed Foundation | D123: Nos. | E123: Palashbari | F123: 1 | G123: MPSB/Str/946 | H123: 45744 | I123: IPC - 13
B124: 303.a.iii | C124: Construction of Casting Yard - Casting Bed Foundation | D124: Nos. | E124: Sualkuchi | F124: 1 | G124: MPSB/Str/1346 | H124: 45777 | I124: IPC - 14
C126: Cumulative paid upto this Bill | D126: Nos. | F126: =SUM(F123:F125) -> 2
C127: Paid upto previous Bill | D127: Nos. | F127: 2
C128: To be paid in this Bill | D128: Nos. | F128: =F126-F127 -> 0
B130: 303.a.iv | C130: Construction of Casting Yard - Stacking Bed Foundation | D130: Nos. | E130: Palashbari | F130: =1 -> 1 | G130: MPSB/Temp/170 | H130: 45808 | I130: IPC - 15
...

Sheet Segment Summary
A1: Main Bridge - Segments Scope Vs Casting
A3: P6 | C3: P7 | E3: P8 | G3: P9 | I3: P10 | K3: P11 | M3: P12 | O3: P13 | Q3: P14 | S3: P15 | U3: P16 | W3: P17 | Y3: P18
A4: Seg. ID | B4: Casted in | C4: Seg. ID | D4: Casted in | E4: Seg. ID | F4: Casted in | G4: Seg. ID | H4: Casted in | I4: Seg. ID | J4: Casted in | K4: Seg. ID | L4: Casted in | M4: Seg. ID | N4: Casted in | O4: Seg. ID | P4: Casted in | Q4: Seg. ID | R4: Casted in | S4: Seg. ID | T4: Casted in | U4: Seg. ID | V4: Casted in | W4: Seg. ID | X4: Casted in | Y4: Seg. ID | Z4: Casted in
A5: P6-S01a-E | B5: =VLOOKUP(A5,'Segment Abs.'!$B:$C,2,0) -> #N/A | C5: P7-S01a-O | D5: =VLOOKUP(C5,'Segment Abs.'!$B:$C,2,0) -> #N/A | E5: P8-S01a-M | F5: =VLOOKUP(E5,'Segment Abs.'!$B:$C,2,0) -> #N/A | G5: P9-S01a-O | H5: =VLOOKUP(G5,'Segment Abs.'!$B:$C,2,0) -> #N/A | I5: P10-S01a-E | J5: =VLOOKUP(I5,'Segment Abs.'!$B:$C,2,0) -> #N/A | K5: P11-S01a-O | L5: =VLOOKUP(K5,'Segment Abs.'!$B:$C,2,0) -> #N/A | M5: P12-S01a-M | N5: =VLOOKUP(M5,'Segment Abs.'!$B:$C,2,0) -> #N/A | O5: P13-S01a-O | P5: =VLOOKUP(O5,'Segment Abs.'!$B:$C,2,0) -> #N/A | Q5: P14-S01a-E | R5: =VLOOKUP(Q5,'Segment Abs.'!$B:$C,2,0) -> #N/A | S5: P15-S01a-O | T5: =VLOOKUP(S5,'Segment Abs.'!$B:$C,2,0) -> #N/A | U5: P16-S01a-M | V5: =VLOOKUP(U5,'Segment Abs.'!$B:$C,2,0) -> #N/A | W5: P17-S01a-O | X5: =VLOOKUP(W5,'Segment Abs.'!$B:$C,2,0) -> #N/A | Y5: P18-S01a-E | Z5: =VLOOKUP(Y5,'Segment Abs.'!$B:$C,2,0) -> #N/A
A6: P6-S01-E | B6: =VLOOKUP(A6,'Segment Abs.'!$B:$C,2,0) -> #N/A | C6: P7-S02a-O | D6: =VLOOKUP(C6,'Segment Abs.'!$B:$C,2,0) -> #N/A | E6: P8-S02a-M | F6: =VLOOKUP(E6,'Segment Abs.'!$B:$C,2,0) -> #N/A | G6: P9-S02a-O | H6: =VLOOKUP(G6,'Segment Abs.'!$B:$C,2,0) -> #N/A | I6: P10-S01-E | J6: =VLOOKUP(I6,'Segment Abs.'!$B:$C,2,0) -> #N/A | K6: P11-S02a-O | L6: =VLOOKUP(K6,'Segment Abs.'!$B:$C,2,0) -> #N/A | M6: P12-S02a-M | N6: =VLOOKUP(M6,'Segment Abs.'!$B:$C,2,0) -> #N/A | O6: P13-S02a-O | P6: =VLOOKUP(O6,'Segment Abs.'!$B:$C,2,0) -> #N/A | Q6: P14-S01-E | R6: =VLOOKUP(Q6,'Segment Abs.'!$B:$C,2,0) -> #N/A | S6: P15-S02a-O | T6: =VLOOKUP(S6,'Segment Abs.'!$B:$C,2,0) -> #N/A | U6: P16-S02a-M | V6: =VLOOKUP(U6,'Segment Abs.'!$B:$C,2,0) -> #N/A | W6: P17-S02a-O | X6: =VLOOKUP(W6,'Segment Abs.'!$B:$C,2,0) -> #N/A | Y6: P18-S01-E | Z6: =VLOOKUP(Y6,'Segment Abs.'!$B:$C,2,0) -> #N/A
A7: P6-S02a-E | B7: =VLOOKUP(A7,'Segment Abs.'!$B:$C,2,0) -> #N/A | C7: P7-S03a-O | D7: =VLOOKUP(C7,'Segment Abs.'!$B:$C,2,0) -> #N/A | E7: P8-S03a-M | F7: =VLOOKUP(E7,'Segment Abs.'!$B:$C,2,0) -> #N/A | G7: P9-S03a-O | H7: =VLOOKUP(G7,'Segment Abs.'!$B:$C,2,0) -> #N/A | I7: P10-S02a-E | J7: =VLOOKUP(I7,'Segment Abs.'!$B:$C,2,0) -> #N/A | K7: P11-S03a-O | L7: =VLOOKUP(K7,'Segment Abs.'!$B:$C,2,0) -> #N/A | M7: P12-S03a-M | N7: =VLOOKUP(M7,'Segment Abs.'!$B:$C,2,0) -> #N/A | O7: P13-S03a-O | P7: =VLOOKUP(O7,'Segment Abs.'!$B:$C,2,0) -> #N/A | Q7: P14-S02a-E | R7: =VLOOKUP(Q7,'Segment Abs.'!$B:$C,2,0) -> #N/A | S7: P15-S03a-O | T7: =VLOOKUP(S7,'Segment Abs.'!$B:$C,2,0) -> #N/A | U7: P16-S03a-M | V7: =VLOOKUP(U7,'Segment Abs.'!$B:$C,2,0) -> #N/A | W7: P17-S03a-O | X7: =VLOOKUP(W7,'Segment Abs.'!$B:$C,2,0) -> #N/A | Y7: P18-S02a-E | Z7: =VLOOKUP(Y7,'Segment Abs.'!$B:$C,2,0) -> #N/A
A8: P6-S03a-E | B8: =VLOOKUP(A8,'Segment Abs.'!$B:$C,2,0) -> #N/A | C8: P7-S04a-O | D8: =VLOOKUP(C8,'Segment Abs.'!$B:$C,2,0) -> #N/A | E8: P8-S04a-M | F8: =VLOOKUP(E8,'Segment Abs.'!$B:$C,2,0) -> #N/A | G8: P9-S04a-O | H8: =VLOOKUP(G8,'Segment Abs.'!$B:$C,2,0) -> #N/A | I8: P10-S03a-E | J8: =VLOOKUP(I8,'Segment Abs.'!$B:$C,2,0) -> #N/A | K8: P11-S04a-O | L8: =VLOOKUP(K8,'Segment Abs.'!$B:$C,2,0) -> #N/A | M8: P12-S04a-M | N8: =VLOOKUP(M8,'Segment Abs.'!$B:$C,2,0) -> #N/A | O8: P13-S04a-O | P8: =VLOOKUP(O8,'Segment Abs.'!$B:$C,2,0) -> #N/A | Q8: P14-S03a-E | R8: =VLOOKUP(Q8,'Segment Abs.'!$B:$C,2,0) -> #N/A | S8: P15-S04a-O | T8: =VLOOKUP(S8,'Segment Abs.'!$B:$C,2,0) -> #N/A | U8: P16-S04a-M | V8: =VLOOKUP(U8,'Segment Abs.'!$B:$C,2,0) -> #N/A | W8: P17-S04a-O | X8: =VLOOKUP(W8,'Segment Abs.'!$B:$C,2,0) -> #N/A | Y8: P18-S03a-E | Z8: =VLOOKUP(Y8,'Segment Abs.'!$B:$C,2,0) -> #N/A
A9: P6-S04a-E | B9: =VLOOKUP(A9,'Segment Abs.'!$B:$C,2,0) -> #N/A | C9: P7-S05a-O | D9: =VLOOKUP(C9,'Segment Abs.'!$B:$C,2,0) -> #N/A | E9: P8-S05a-M | F9: =VLOOKUP(E9,'Segment Abs.'!$B:$C,2,0) -> #N/A | G9: P9-S05a-O | H9: =VLOOKUP(G9,'Segment Abs.'!$B:$C,2,0) -> #N/A | I9: P10-S04a-E | J9: =VLOOKUP(I9,'Segment Abs.'!$B:$C,2,0) -> #N/A | K9: P11-S05a-O | L9: =VLOOKUP(K9,'Segment Abs.'!$B:$C,2,0) -> #N/A | M9: P12-S05a-M | N9: =VLOOKUP(M9,'Segment Abs.'!$B:$C,2,0) -> #N/A | O9: P13-S05a-O | P9: =VLOOKUP(O9,'Segment Abs.'!$B:$C,2,0) -> #N/A | Q9: P14-S04a-E | R9: =VLOOKUP(Q9,'Segment Abs.'!$B:$C,2,0) -> #N/A | S9: P15-S05a-O | T9: =VLOOKUP(S9,'Segment Abs.'!$B:$C,2,0) -> #N/A | U9: P16-S05a-M | V9: =VLOOKUP(U9,'Segment Abs.'!$B:$C,2,0) -> #N/A | W9: P17-S05a-O | X9: =VLOOKUP(W9,'Segment Abs.'!$B:$C,2,0) -> #N/A | Y9: P18-S04a-E | Z9: =VLOOKUP(Y9,'Segment Abs.'!$B:$C,2,0) -> #N/A
A10: P6-S05a-E | B10: =VLOOKUP(A10,'Segment Abs.'!$B:$C,2,0) -> #N/A | C10: P7-S06a-O | D10: =VLOOKUP(C10,'Segment Abs.'!$B:$C,2,0) -> #N/A | E10: P8-S06a-M | F10: =VLOOKUP(E10,'Segment Abs.'!$B:$C,2,0) -> #N/A | G10: P9-S06a-O | H10: =VLOOKUP(G10,'Segment Abs.'!$B:$C,2,0) -> #N/A | I10: P10-S05a-E | J10: =VLOOKUP(I10,'Segment Abs.'!$B:$C,2,0) -> #N/A | K10: P11-S06a-O | L10: =VLOOKUP(K10,'Segment Abs.'!$B:$C,2,0) -> #N/A | M10: P12-S06a-M | N10: =VLOOKUP(M10,'Segment Abs.'!$B:$C,2,0) -> #N/A | O10: P13-S06a-O | P10: =VLOOKUP(O10,'Segment Abs.'!$B:$C,2,0) -> #N/A | Q10: P14-S05a-E | R10: =VLOOKUP(Q10,'Segment Abs.'!$B:$C,2,0) -> #N/A | S10: P15-S06a-O | T10: =VLOOKUP(S10,'Segment Abs.'!$B:$C,2,0) -> #N/A | U10: P16-S06a-M | V10: =VLOOKUP(U10,'Segment Abs.'!$B:$C,2,0) -> #N/A | W10: P17-S06a-O | X10: =VLOOKUP(W10,'Segment Abs.'!$B:$C,2,0) -> #N/A | Y10: P18-S05a-E | Z10: =VLOOKUP(Y10,'Segment Abs.'!$B:$C,2,0) -> #N/A
A11: P6-S06a-E | B11: =VLOOKUP(A11,'Segment Abs.'!$B:$C,2,0) -> #N/A | C11: P7-S07a-O | D11: =VLOOKUP(C11,'Segment Abs.'!$B:$C,2,0) -> #N/A | E11: P8-S07a-M | F11: =VLOOKUP(E11,'Segment Abs.'!$B:$C,2,0) -> #N/A | G11: P9-S07a-O | H11: =VLOOKUP(G11,'Segment Abs.'!$B:$C,2,0) -> #N/A | I11: P10-S06a-E | J11: =VLOOKUP(I11,'Segment Abs.'!$B:$C,2,0) -> #N/A | K11: P11-S07a-O | L11: =VLOOKUP(K11,'Segment Abs.'!$B:$C,2,0) -> #N/A | M11: P12-S07a-M | N11: =VLOOKUP(M11,'Segment Abs.'!$B:$C,2,0) -> #N/A | O11: P13-S07a-O | P11: =VLOOKUP(O11,'Segment Abs.'!$B:$C,2,0) -> #N/A | Q11: P14-S06a-E | R11: =VLOOKUP(Q11,'Segment Abs.'!$B:$C,2,0) -> #N/A | S11: P15-S07a-O | T11: =VLOOKUP(S11,'Segment Abs.'!$B:$C,2,0) -> #N/A | U11: P16-S07a-M | V11: =VLOOKUP(U11,'Segment Abs.'!$B:$C,2,0) -> #N/A | W11: P17-S07a-O | X11: =VLOOKUP(W11,'Segment Abs.'!$B:$C,2,0) -> #N/A | Y11: P18-S06a-E | Z11: =VLOOKUP(Y11,'Segment Abs.'!$B:$C,2,0) -> #N/A
A12: P6-S34a-O | B12: =VLOOKUP(A12,'Segment Abs.'!$B:$C,2,0) -> #N/A | C12: P7-S08a-O | D12: =VLOOKUP(C12,'Segment Abs.'!$B:$C,2,0) -> #N/A | E12: P8-S08a-M© | F12: =VLOOKUP(E12,'Segment Abs.'!$B:$C,2,0) -> #N/A | G12: P9-S08a-O | H12: =VLOOKUP(G12,'Segment Abs.'!$B:$C,2,0) -> #N/A | I12: P10-S34a-O | J12: =VLOOKUP(I12,'Segment Abs.'!$B:$C,2,0) -> #N/A | K12: P11-S08a-O | L12: =VLOOKUP(K12,'Segment Abs.'!$B:$C,2,0) -> #N/A | M12: P12-S08a-M© | N12: =VLOOKUP(M12,'Segment Abs.'!$B:$C,2,0) -> #N/A | O12: P13-S08a-O | P12: =VLOOKUP(O12,'Segment Abs.'!$B:$C,2,0) -> #N/A | Q12: P14-S34a-O | R12: =VLOOKUP(Q12,'Segment Abs.'!$B:$C,2,0) -> #N/A | S12: P15-S08a-O | T12: =VLOOKUP(S12,'Segment Abs.'!$B:$C,2,0) -> #N/A | U12: P16-S08a-M© | V12: =VLOOKUP(U12,'Segment Abs.'!$B:$C,2,0) -> #N/A | W12: P17-S08a-O | X12: =VLOOKUP(W12,'Segment Abs.'!$B:$C,2,0) -> #N/A | Y12: P18-S34a-O | Z12: =VLOOKUP(Y12,'Segment Abs.'!$B:$C,2,0) -> #N/A
A13: P6-S33a-O© | B13: =VLOOKUP(A13,'Segment Abs.'!$B:$C,2,0) -> #N/A | C13: P7-S09a-O© | D13: =VLOOKUP(C13,'Segment Abs.'!$B:$C,2,0) -> #N/A | E13: P8-S09a-M | F13: =VLOOKUP(E13,'Segment Abs.'!$B:$C,2,0) -> #N/A | G13: P9-S09a-O© | H13: =VLOOKUP(G13,'Segment Abs.'!$B:$C,2,0) -> #N/A | I13: P10-S33a-O© | J13: =VLOOKUP(I13,'Segment Abs.'!$B:$C,2,0) -> #N/A | K13: P11-S09a-O© | L13: =VLOOKUP(K13,'Segment Abs.'!$B:$C,2,0) -> #N/A | M13: P12-S09a-M | N13: =VLOOKUP(M13,'Segment Abs.'!$B:$C,2,0) -> #N/A | O13: P13-S09a-O© | P13: =VLOOKUP(O13,'Segment Abs.'!$B:$C,2,0) -> #N/A | Q13: P14-S33a-O© | R13: =VLOOKUP(Q13,'Segment Abs.'!$B:$C,2,0) -> #N/A | S13: P15-S09a-O© | T13: =VLOOKUP(S13,'Segment Abs.'!$B:$C,2,0) -> #N/A | U13: P16-S09a-M | V13: =VLOOKUP(U13,'Segment Abs.'!$B:$C,2,0) -> #N/A | W13: P17-S09a-O© | X13: =VLOOKUP(W13,'Segment Abs.'!$B:$C,2,0) -> #N/A | Y13: P18-S33a-O© | Z13: =VLOOKUP(Y13,'Segment Abs.'!$B:$C,2,0) -> #N/A
A14: P6-S32a-O | B14: =VLOOKUP(A14,'Segment Abs.'!$B:$C,2,0) -> #N/A | C14: P7-S10a-O | D14: =VLOOKUP(C14,'Segment Abs.'!$B:$C,2,0) -> #N/A | E14: P8-S10a-M© | F14: =VLOOKUP(E14,'Segment Abs.'!$B:$C,2,0) -> #N/A | G14: P9-S10a-O | H14: =VLOOKUP(G14,'Segment Abs.'!$B:$C,2,0) -> #N/A | I14: P10-S32a-O | J14: =VLOOKUP(I14,'Segment Abs.'!$B:$C,2,0) -> #N/A | K14: P11-S10a-O | L14: =VLOOKUP(K14,'Segment Abs.'!$B:$C,2,0) -> #N/A | M14: P12-S10a-M© | N14: =VLOOKUP(M14,'Segment Abs.'!$B:$C,2,0) -> #N/A | O14: P13-S10a-O | P14: =VLOOKUP(O14,'Segment Abs.'!$B:$C,2,0) -> #N/A | Q14: P14-S32a-O | R14: =VLOOKUP(Q14,'Segment Abs.'!$B:$C,2,0) -> #N/A | S14: P15-S10a-O | T14: =VLOOKUP(S14,'Segment Abs.'!$B:$C,2,0) -> #N/A | U14: P16-S10a-M© | V14: =VLOOKUP(U14,'Segment Abs.'!$B:$C,2,0) -> #N/A | W14: P17-S10a-O | X14: =VLOOKUP(W14,'Segment Abs.'!$B:$C,2,0) -> #N/A | Y14: P18-S32a-O | Z14: =VLOOKUP(Y14,'Segment Abs.'!$B:$C,2,0) -> #N/A
A15: P6-S31a-O© | B15: =VLOOKUP(A15,'Segment Abs.'!$B:$C,2,0) -> #N/A | C15: P7-S11a-O© | D15: =VLOOKUP(C15,'Segment Abs.'!$B:$C,2,0) -> #N/A | E15: P8-S11a-M | F15: =VLOOKUP(E15,'Segment Abs.'!$B:$C,2,0) -> #N/A | G15: P9-S11a-O© | H15: =VLOOKUP(G15,'Segment Abs.'!$B:$C,2,0) -> #N/A | I15: P10-S31a-O© | J15: =VLOOKUP(I15,'Segment Abs.'!$B:$C,2,0) -> #N/A | K15: P11-S11a-O© | L15: =VLOOKUP(K15,'Segment Abs.'!$B:$C,2,0) -> #N/A | M15: P12-S11a-M | N15: =VLOOKUP(M15,'Segment Abs.'!$B:$C,2,0) -> #N/A | O15: P13-S11a-O© | P15: =VLOOKUP(O15,'Segment Abs.'!$B:$C,2,0) -> #N/A | Q15: P14-S31a-O© | R15: =VLOOKUP(Q15,'Segment Abs.'!$B:$C,2,0) -> #N/A | S15: P15-S11a-O© | T15: =VLOOKUP(S15,'Segment Abs.'!$B:$C,2,0) -> #N/A | U15: P16-S11a-M | V15: =VLOOKUP(U15,'Segment Abs.'!$B:$C,2,0) -> #N/A | W15: P17-S11a-O© | X15: =VLOOKUP(W15,'Segment Abs.'!$B:$C,2,0) -> #N/A | Y15: P18-S31a-O© | Z15: =VLOOKUP(Y15,'Segment Abs.'!$B:$C,2,0) -> #N/A
A16: P6-S30a-O | B16: =VLOOKUP(A16,'Segment Abs.'!$B:$C,2,0) -> #N/A | C16: P7-S12a-O | D16: =VLOOKUP(C16,'Segment Abs.'!$B:$C,2,0) -> #N/A | E16: P8-S12a-M© | F16: =VLOOKUP(E16,'Segment Abs.'!$B:$C,2,0) -> #N/A | G16: P9-S12a-O | H16: =VLOOKUP(G16,'Segment Abs.'!$B:$C,2,0) -> #N/A | I16: P10-S30a-O | J16: =VLOOKUP(I16,'Segment Abs.'!$B:$C,2,0) -> #N/A | K16: P11-S12a-O | L16: =VLOOKUP(K16,'Segment Abs.'!$B:$C,2,0) -> #N/A | M16: P12-S12a-M© | N16: =VLOOKUP(M16,'Segment Abs.'!$B:$C,2,0) -> #N/A | O16: P13-S12a-O | P16: =VLOOKUP(O16,'Segment Abs.'!$B:$C,2,0) -> #N/A | Q16: P14-S30a-O | R16: =VLOOKUP(Q16,'Segment Abs.'!$B:$C,2,0) -> #N/A | S16: P15-S12a-O | T16: =VLOOKUP(S16,'Segment Abs.'!$B:$C,2,0) -> #N/A | U16: P16-S12a-M© | V16: =VLOOKUP(U16,'Segment Abs.'!$B:$C,2,0) -> #N/A | W16: P17-S12a-O | X16: =VLOOKUP(W16,'Segment Abs.'!$B:$C,2,0) -> #N/A | Y16: P18-S30a-O | Z16: =VLOOKUP(Y16,'Segment Abs.'!$B:$C,2,0) -> #N/A
... A45: P6-S01a-O | B45: =VLOOKUP(A45,'Segment Abs.'!$B:$C,2,0) -> #N/A | C45: P7-S12a-M© | D45: =VLOOKUP(C45,'Segment Abs.'!$B:$C,2,0) -> #N/A | E45: P8-S12a-O | F45: =VLOOKUP(E45,'Segment Abs.'!$B:$C,2,0) -> #N/A | G45: P9-S01a-E | H45: =VLOOKUP(G45,'Segment Abs.'!$B:$C,2,0) -> #N/A | I45: P10-S01a-O | J45: =VLOOKUP(I45,'Segment Abs.'!$B:$C,2,0) -> #N/A | K45: P11-S12a-M© | L45: =VLOOKUP(K45,'Segment Abs.'!$B:$C,2,0) -> #N/A | M45: P12-S12a-O | N45: =VLOOKUP(M45,'Segment Abs.'!$B:$C,2,0) -> #N/A | O45: P13-S01a-E | P45: =VLOOKUP(O45,'Segment Abs.'!$B:$C,2,0) -> #N/A | Q45: P14-S01a-O | R45: =VLOOKUP(Q45,'Segment Abs.'!$B:$C,2,0) -> #N/A | S45: P15-S12a-M© | T45: =VLOOKUP(S45,'Segment Abs.'!$B:$C,2,0) -> #N/A | U45: P16-S12a-O | V45: =VLOOKUP(U45,'Segment Abs.'!$B:$C,2,0) -> #N/A | W45: P17-S01a-E | X45: =VLOOKUP(W45,'Segment Abs.'!$B:$C,2,0) -> #N/A | Y45: P18-S01a-O | Z45: =VLOOKUP(Y45,'Segment Abs.'!$B:$C,2,0) -> #N/A
C46: P7-S11a-M | D46: =VLOOKUP(C46,'Segment Abs.'!$B:$C,2,0) -> #N/A | E46: P8-S11a-O© | F46: =VLOOKUP(E46,'Segment Abs.'!$B:$C,2,0) -> #N/A | K46: P11-S11a-M | L46: =VLOOKUP(K46,'Segment Abs.'!$B:$C,2,0) -> #N/A | M46: P12-S11a-O© | N46: =VLOOKUP(M46,'Segment Abs.'!$B:$C,2,0) -> #N/A | S46: P15-S11a-M | T46: =VLOOKUP(S46,'Segment Abs.'!$B:$C,2,0) -> #N/A | U46: P16-S11a-O© | V46: =VLOOKUP(U46,'Segment Abs.'!$B:$C,2,0) -> #N/A
C47: P7-S10a-M© | D47: =VLOOKUP(C47,'Segment Abs.'!$B:$C,2,0) -> #N/A | E47: P8-S10a-O | F47: =VLOOKUP(E47,'Segment Abs.'!$B:$C,2,0) -> #N/A | K47: P11-S10a-M© | L47: =VLOOKUP(K47,'Segment Abs.'!$B:$C,2,0) -> #N/A | M47: P12-S10a-O | N47: =VLOOKUP(M47,'Segment Abs.'!$B:$C,2,0) -> #N/A | S47: P15-S10a-M© | T47: =VLOOKUP(S47,'Segment Abs.'!$B:$C,2,0) -> #N/A | U47: P16-S10a-O | V47: =VLOOKUP(U47,'Segment Abs.'!$B:$C,2,0) -> #N/A
C48: P7-S09a-M | D48: =VLOOKUP(C48,'Segment Abs.'!$B:$C,2,0) -> #N/A | E48: P8-S09a-O© | F48: =VLOOKUP(E48,'Segment Abs.'!$B:$C,2,0) -> #N/A | K48: P11-S09a-M | L48: =VLOOKUP(K48,'Segment Abs.'!$B:$C,2,0) -> #N/A | M48: P12-S09a-O© | N48: =VLOOKUP(M48,'Segment Abs.'!$B:$C,2,0) -> #N/A | S48: P15-S09a-M | T48: =VLOOKUP(S48,'Segment Abs.'!$B:$C,2,0) -> #N/A | U48: P16-S09a-O© | V48: =VLOOKUP(U48,'Segment Abs.'!$B:$C,2,0) -> #N/A
C49: P7-S08a-M© | D49: =VLOOKUP(C49,'Segment Abs.'!$B:$C,2,0) -> #N/A | E49: P8-S08a-O | F49: =VLOOKUP(E49,'Segment Abs.'!$B:$C,2,0) -> #N/A | K49: P11-S08a-M© | L49: =VLOOKUP(K49,'Segment Abs.'!$B:$C,2,0) -> #N/A | M49: P12-S08a-O | N49: =VLOOKUP(M49,'Segment Abs.'!$B:$C,2,0) -> #N/A | S49: P15-S08a-M© | T49: =VLOOKUP(S49,'Segment Abs.'!$B:$C,2,0) -> #N/A | U49: P16-S08a-O | V49: =VLOOKUP(U49,'Segment Abs.'!$B:$C,2,0) -> #N/A
C50: P7-S07a-M | D50: =VLOOKUP(C50,'Segment Abs.'!$B:$C,2,0) -> #N/A | E50: P8-S07a-O | F50: =VLOOKUP(E50,'Segment Abs.'!$B:$C,2,0) -> #N/A | K50: P11-S07a-M | L50: =VLOOKUP(K50,'Segment Abs.'!$B:$C,2,0) -> #N/A | M50: P12-S07a-O | N50: =VLOOKUP(M50,'Segment Abs.'!$B:$C,2,0) -> #N/A | S50: P15-S07a-M | T50: =VLOOKUP(S50,'Segment Abs.'!$B:$C,2,0) -> #N/A | U50: P16-S07a-O | V50: =VLOOKUP(U50,'Segment Abs.'!$B:$C,2,0) -> #N/A
C51: P7-S06a-M | D51: =VLOOKUP(C51,'Segment Abs.'!$B:$C,2,0) -> #N/A | E51: P8-S06a-O | F51: =VLOOKUP(E51,'Segment Abs.'!$B:$C,2,0) -> #N/A | K51: P11-S06a-M | L51: =VLOOKUP(K51,'Segment Abs.'!$B:$C,2,0) -> #N/A | M51: P12-S06a-O | N51: =VLOOKUP(M51,'Segment Abs.'!$B:$C,2,0) -> #N/A | S51: P15-S06a-M | T51: =VLOOKUP(S51,'Segment Abs.'!$B:$C,2,0) -> #N/A | U51: P16-S06a-O | V51: =VLOOKUP(U51,'Segment Abs.'!$B:$C,2,0) -> #N/A
C52: P7-S05a-M | D52: =VLOOKUP(C52,'Segment Abs.'!$B:$C,2,0) -> #N/A | E52: P8-S05a-O | F52: =VLOOKUP(E52,'Segment Abs.'!$B:$C,2,0) -> #N/A | K52: P11-S05a-M | L52: =VLOOKUP(K52,'Segment Abs.'!$B:$C,2,0) -> #N/A | M52: P12-S05a-O | N52: =VLOOKUP(M52,'Segment Abs.'!$B:$C,2,0) -> #N/A | S52: P15-S05a-M | T52: =VLOOKUP(S52,'Segment Abs.'!$B:$C,2,0) -> #N/A | U52: P16-S05a-O | V52: =VLOOKUP(U52,'Segment Abs.'!$B:$C,2,0) -> #N/A
C53: P7-S04a-M | D53: =VLOOKUP(C53,'Segment Abs.'!$B:$C,2,0) -> #N/A | E53: P8-S04a-O | F53: =VLOOKUP(E53,'Segment Abs.'!$B:$C,2,0) -> #N/A | K53: P11-S04a-M | L53: =VLOOKUP(K53,'Segment Abs.'!$B:$C,2,0) -> #N/A | M53: P12-S04a-O | N53: =VLOOKUP(M53,'Segment Abs.'!$B:$C,2,0) -> #N/A | S53: P15-S04a-M | T53: =VLOOKUP(S53,'Segment Abs.'!$B:$C,2,0) -> #N/A | U53: P16-S04a-O | V53: =VLOOKUP(U53,'Segment Abs.'!$B:$C,2,0) -> #N/A
C54: P7-S03a-M | D54: =VLOOKUP(C54,'Segment Abs.'!$B:$C,2,0) -> #N/A | E54: P8-S03a-O | F54: =VLOOKUP(E54,'Segment Abs.'!$B:$C,2,0) -> #N/A | K54: P11-S03a-M | L54: =VLOOKUP(K54,'Segment Abs.'!$B:$C,2,0) -> #N/A | M54: P12-S03a-O | N54: =VLOOKUP(M54,'Segment Abs.'!$B:$C,2,0) -> #N/A | S54: P15-S03a-M | T54: =VLOOKUP(S54,'Segment Abs.'!$B:$C,2,0) -> #N/A | U54: P16-S03a-O | V54: =VLOOKUP(U54,'Segment Abs.'!$B:$C,2,0) -> #N/A
C55: P7-S02a-M | D55: =VLOOKUP(C55,'Segment Abs.'!$B:$C,2,0) -> #N/A | E55: P8-S02a-O | F55: =VLOOKUP(E55,'Segment Abs.'!$B:$C,2,0) -> #N/A | K55: P11-S02a-M | L55: =VLOOKUP(K55,'Segment Abs.'!$B:$C,2,0) -> #N/A | M55: P12-S02a-O | N55: =VLOOKUP(M55,'Segment Abs.'!$B:$C,2,0) -> #N/A | S55: P15-S02a-M | T55: =VLOOKUP(S55,'Segment Abs.'!$B:$C,2,0) -> #N/A | U55: P16-S02a-O | V55: =VLOOKUP(U55,'Segment Abs.'!$B:$C,2,0) -> #N/A
C56: P7-S01a-M | D56: =VLOOKUP(C56,'Segment Abs.'!$B:$C,2,0) -> #N/A | E56: P8-S01a-O | F56: =VLOOKUP(E56,'Segment Abs.'!$B:$C,2,0) -> #N/A | K56: P11-S01a-M | L56: =VLOOKUP(K56,'Segment Abs.'!$B:$C,2,0) -> #N/A | M56: P12-S01a-O | N56: =VLOOKUP(M56,'Segment Abs.'!$B:$C,2,0) -> #N/A | S56: P15-S01a-M | T56: =VLOOKUP(S56,'Segment Abs.'!$B:$C,2,0) -> #N/A | U56: P16-S01a-O | V56: =VLOOKUP(U56,'Segment Abs.'!$B:$C,2,0) -> #N/A
A57: =COUNTA(A$5:A$56) -> 41 | B57: =COUNTIF(B$5:B$56,">0") -> 0 | C57: =COUNTA(C$5:C$56) -> 52 | D57: =COUNTIF(D$5:D$56,">0") -> 0 | E57: =COUNTA(E$5:E$56) -> 52 | F57: =COUNTIF(F$5:F$56,">0") -> 0 | G57: =COUNTA(G$5:G$56) -> 41 | H57: =COUNTIF(H$5:H$56,">0") -> 0 | I57: =COUNTA(I$5:I$56) -> 41 | J57: =COUNTIF(J$5:J$56,">0") -> 0 | K57: =COUNTA(K$5:K$56) -> 52 | L57: =COUNTIF(L$5:L$56,">0") -> 0 | M57: =COUNTA(M$5:M$56) -> 52 | N57: =COUNTIF(N$5:N$56,">0") -> 0 | O57: =COUNTA(O$5:O$56) -> 41 | P57: =COUNTIF(P$5:P$56,">0") -> 0 | Q57: =COUNTA(Q$5:Q$56) -> 41 | R57: =COUNTIF(R$5:R$56,">0") -> 0 | S57: =COUNTA(S$5:S$56) -> 52 | T57: =COUNTIF(T$5:T$56,">0") -> 0 | U57: =COUNTA(U$5:U$56) -> 52 | V57: =COUNTIF(V$5:V$56,">0") -> 0 | W57: =COUNTA(W$5:W$56) -> 41 | X57: =COUNTIF(X$5:X$56,">0") -> 0 | Y57: =COUNTA(Y$5:Y$56) -> 41 | Z57: =COUNTIF(Z$5:Z$56,">0") -> 0
A58: =COUNTIF(A$5:A$56,"*©*") -> 13 | B58: =COUNTIFS(A$5:A$56,"*©*",B$5:B$56,">10") -> 0 | C58: =COUNTIF(C$5:C$56,"*©*") -> 18 | D58: =COUNTIFS(C$5:C$56,"*©*",D$5:D$56,">10") -> 0 | E58: =COUNTIF(E$5:E$56,"*©*") -> 18 | F58: =COUNTIFS(E$5:E$56,"*©*",F$5:F$56,">10") -> 0 | G58: =COUNTIF(G$5:G$56,"*©*") -> 13 | H58: =COUNTIFS(G$5:G$56,"*©*",H$5:H$56,">10") -> 0 | I58: =COUNTIF(I$5:I$56,"*©*") -> 13 | J58: =COUNTIFS(I$5:I$56,"*©*",J$5:J$56,">10") -> 0 | K58: =COUNTIF(K$5:K$56,"*©*") -> 18 | L58: =COUNTIFS(K$5:K$56,"*©*",L$5:L$56,">10") -> 0 | M58: =COUNTIF(M$5:M$56,"*©*") -> 18 | N58: =COUNTIFS(M$5:M$56,"*©*",N$5:N$56,">10") -> 0 | O58: =COUNTIF(O$5:O$56,"*©*") -> 13 | P58: =COUNTIFS(O$5:O$56,"*©*",P$5:P$56,">10") -> 0 | Q58: =COUNTIF(Q$5:Q$56,"*©*") -> 13 | R58: =COUNTIFS(Q$5:Q$56,"*©*",R$5:R$56,">10") -> 0 | S58: =COUNTIF(S$5:S$56,"*©*") -> 18 | T58: =COUNTIFS(S$5:S$56,"*©*",T$5:T$56,">10") -> 0 | U58: =COUNTIF(U$5:U$56,"*©*") -> 18 | V58: =COUNTIFS(U$5:U$56,"*©*",V$5:V$56,">10") -> 0 | W58: =COUNTIF(W$5:W$56,"*©*") -> 13 | X58: =COUNTIFS(W$5:W$56,"*©*",X$5:X$56,">10") -> 0 | Y58: =COUNTIF(Y$5:Y$56,"*©*") -> 13 | Z58: =COUNTIFS(Y$5:Y$56,"*©*",Z$5:Z$56,">10") -> 0
A60: Main Bridge - Segments Scope Vs Casting
A62: P19 | C62: P20 | E62: P21 | G62: P22 | I62: P23 | K62: P24 | M62: P25 | O62: P26 | Q62: P27 | S62: P28 | U62: P29 | W62: Total
A63: Seg. ID | B63: Casted in | C63: Seg. ID | D63: Casted in | E63: Seg. ID | F63: Casted in | G63: Seg. ID | H63: Casted in | I63: Seg. ID | J63: Casted in | K63: Seg. ID | L63: Casted in | M63: Seg. ID | N63: Casted in | O63: Seg. ID | P63: Casted in | Q63: Seg. ID | R63: Casted in | S63: Seg. ID | T63: Casted in | U63: Seg. ID | V63: Casted in | W63: Segments | X63: Casted
A64: P19-S01a-O | B64: =VLOOKUP(A64,'Segment Abs.'!$B:$C,2,0) -> #N/A | C64: P20-S01a-M | D64: =VLOOKUP(C64,'Segment Abs.'!$B:$C,2,0) -> #N/A | E64: P21-S01a-O | F64: =VLOOKUP(E64,'Segment Abs.'!$B:$C,2,0) -> #N/A | G64: P22-S01a-E | H64: =VLOOKUP(G64,'Segment Abs.'!$B:$C,2,0) -> #N/A | I64: P23-S01a-O | J64: =VLOOKUP(I64,'Segment Abs.'!$B:$C,2,0) -> #N/A | K64: P24-S01a-M | L64: =VLOOKUP(K64,'Segment Abs.'!$B:$C,2,0) -> #N/A | M64: P25-S01a-O | N64: =VLOOKUP(M64,'Segment Abs.'!$B:$C,2,0) -> #N/A | O64: P26-S01a-E | P64: =VLOOKUP(O64,'Segment Abs.'!$B:$C,2,0) -> #N/A | Q64: P27-S01a-O | R64: =VLOOKUP(Q64,'Segment Abs.'!$B:$C,2,0) -> #N/A | S64: P28-S01a-M | T64: =VLOOKUP(S64,'Segment Abs.'!$B:$C,2,0) -> #N/A | U64: P29-S01a-O | V64: =VLOOKUP(U64,'Segment Abs.'!$B:$C,2,0) -> #N/A | W64: =COUNTA(A5,C5,E5,G5,I5,K5,M5,O5,Q5,S5,U5,W5,Y5,A64,C64,E64,G64,I64,K64,M64,O64,Q64,S64,U64) -> 24 | X64: =COUNT(V64,T64,R64,P64,N64,L64,J64,H64,F64,D64,B64,Z5,X5,V5,T5,R5,P5,L5,J5,H5,F5,D5,B5) -> 0
A65: P19-S02a-O | B65: =VLOOKUP(A65,'Segment Abs.'!$B:$C,2,0) -> #N/A | C65: P20-S02a-M | D65: =VLOOKUP(C65,'Segment Abs.'!$B:$C,2,0) -> #N/A | E65: P21-S02a-O | F65: =VLOOKUP(E65,'Segment Abs.'!$B:$C,2,0) -> #N/A | G65: P22-S01-E | H65: =VLOOKUP(G65,'Segment Abs.'!$B:$C,2,0) -> #N/A | I65: P23-S02a-O | J65: =VLOOKUP(I65,'Segment Abs.'!$B:$C,2,0) -> #N/A | K65: P24-S02a-M | L65: =VLOOKUP(K65,'Segment Abs.'!$B:$C,2,0) -> #N/A | M65: P25-S02a-O | N65: =VLOOKUP(M65,'Segment Abs.'!$B:$C,2,0) -> #N/A | O65: P26-S01-E | P65: =VLOOKUP(O65,'Segment Abs.'!$B:$C,2,0) -> #N/A | Q65: P27-S02a-O | R65: =VLOOKUP(Q65,'Segment Abs.'!$B:$C,2,0) -> #N/A | S65: P28-S02a-M | T65: =VLOOKUP(S65,'Segment Abs.'!$B:$C,2,0) -> #N/A | U65: P29-S02a-O | V65: =VLOOKUP(U65,'Segment Abs.'!$B:$C,2,0) -> #N/A | W65: =COUNTA(A6,C6,E6,G6,I6,K6,M6,O6,Q6,S6,U6,W6,Y6,A65,C65,E65,G65,I65,K65,M65,O65,Q65,S65,U65) -> 24 | X65: =COUNT(V65,T65,R65,P65,N65,L65,J65,H65,F65,D65,B65,Z6,X6,V6,T6,R6,P6,L6,J6,H6,F6,D6,B6) -> 0
A66: P19-S03a-O | B66: =VLOOKUP(A66,'Segment Abs.'!$B:$C,2,0) -> #N/A | C66: P20-S03a-M | D66: =VLOOKUP(C66,'Segment Abs.'!$B:$C,2,0) -> #N/A | E66: P21-S03a-O | F66: =VLOOKUP(E66,'Segment Abs.'!$B:$C,2,0) -> #N/A | G66: P22-S02a-E | H66: =VLOOKUP(G66,'Segment Abs.'!$B:$C,2,0) -> #N/A | I66: P23-S03a-O | J66: =VLOOKUP(I66,'Segment Abs.'!$B:$C,2,0) -> #N/A | K66: P24-S03a-M | L66: =VLOOKUP(K66,'Segment Abs.'!$B:$C,2,0) -> #N/A | M66: P25-S03a-O | N66: =VLOOKUP(M66,'Segment Abs.'!$B:$C,2,0) -> #N/A | O66: P26-S02a-E | P66: =VLOOKUP(O66,'Segment Abs.'!$B:$C,2,0) -> #N/A | Q66: P27-S03a-O | R66: =VLOOKUP(Q66,'Segment Abs.'!$B:$C,2,0) -> #N/A | S66: P28-S03a-M | T66: =VLOOKUP(S66,'Segment Abs.'!$B:$C,2,0) -> #N/A | U66: P29-S03a-O | V66: =VLOOKUP(U66,'Segment Abs.'!$B:$C,2,0) -> #N/A | W66: =COUNTA(A7,C7,E7,G7,I7,K7,M7,O7,Q7,S7,U7,W7,Y7,A66,C66,E66,G66,I66,K66,M66,O66,Q66,S66,U66) -> 24 | X66: =COUNT(V66,T66,R66,P66,N66,L66,J66,H66,F66,D66,B66,Z7,X7,V7,T7,R7,P7,L7,J7,H7,F7,D7,B7) -> 0
A67: P19-S04a-O | B67: =VLOOKUP(A67,'Segment Abs.'!$B:$C,2,0) -> #N/A | C67: P20-S04a-M | D67: =VLOOKUP(C67,'Segment Abs.'!$B:$C,2,0) -> #N/A | E67: P21-S04a-O | F67: =VLOOKUP(E67,'Segment Abs.'!$B:$C,2,0) -> #N/A | G67: P22-S03a-E | H67: =VLOOKUP(G67,'Segment Abs.'!$B:$C,2,0) -> #N/A | I67: P23-S04a-O | J67: =VLOOKUP(I67,'Segment Abs.'!$B:$C,2,0) -> #N/A | K67: P24-S04a-M | L67: =VLOOKUP(K67,'Segment Abs.'!$B:$C,2,0) -> #N/A | M67: P25-S04a-O | N67: =VLOOKUP(M67,'Segment Abs.'!$B:$C,2,0) -> #N/A | O67: P26-S03a-E | P67: =VLOOKUP(O67,'Segment Abs.'!$B:$C,2,0) -> #N/A | Q67: P27-S04a-O | R67: =VLOOKUP(Q67,'Segment Abs.'!$B:$C,2,0) -> #N/A | S67: P28-S04a-M | T67: =VLOOKUP(S67,'Segment Abs.'!$B:$C,2,0) -> #N/A | U67: P29-S04a-O | V67: =VLOOKUP(U67,'Segment Abs.'!$B:$C,2,0) -> #N/A | W67: =COUNTA(A8,C8,E8,G8,I8,K8,M8,O8,Q8,S8,U8,W8,Y8,A67,C67,E67,G67,I67,K67,M67,O67,Q67,S67,U67) -> 24 | X67: =COUNT(V67,T67,R67,P67,N67,L67,J67,H67,F67,D67,B67,Z8,X8,V8,T8,R8,P8,L8,J8,H8,F8,D8,B8) -> 0
A68: P19-S05a-O | B68: =VLOOKUP(A68,'Segment Abs.'!$B:$C,2,0) -> #N/A | C68: P20-S05a-M | D68: =VLOOKUP(C68,'Segment Abs.'!$B:$C,2,0) -> #N/A | E68: P21-S05a-O | F68: =VLOOKUP(E68,'Segment Abs.'!$B:$C,2,0) -> #N/A | G68: P22-S04a-E | H68: =VLOOKUP(G68,'Segment Abs.'!$B:$C,2,0) -> #N/A | I68: P23-S05a-O | J68: =VLOOKUP(I68,'Segment Abs.'!$B:$C,2,0) -> #N/A | K68: P24-S05a-M | L68: =VLOOKUP(K68,'Segment Abs.'!$B:$C,2,0) -> #N/A | M68: P25-S05a-O | N68: =VLOOKUP(M68,'Segment Abs.'!$B:$C,2,0) -> #N/A | O68: P26-S04a-E | P68: =VLOOKUP(O68,'Segment Abs.'!$B:$C,2,0) -> #N/A | Q68: P27-S05a-O | R68: =VLOOKUP(Q68,'Segment Abs.'!$B:$C,2,0) -> #N/A | S68: P28-S05a-M | T68: =VLOOKUP(S68,'Segment Abs.'!$B:$C,2,0) -> #N/A | U68: P29-S05a-O | V68: =VLOOKUP(U68,'Segment Abs.'!$B:$C,2,0) -> #N/A | W68: =COUNTA(A9,C9,E9,G9,I9,K9,M9,O9,Q9,S9,U9,W9,Y9,A68,C68,E68,G68,I68,K68,M68,O68,Q68,S68,U68) -> 24 | X68: =COUNT(V68,T68,R68,P68,N68,L68,J68,H68,F68,D68,B68,Z9,X9,V9,T9,R9,P9,L9,J9,H9,F9,D9,B9) -> 0
A69: P19-S06a-O | B69: =VLOOKUP(A69,'Segment Abs.'!$B:$C,2,0) -> #N/A | C69: P20-S06a-M | D69: =VLOOKUP(C69,'Segment Abs.'!$B:$C,2,0) -> #N/A | E69: P21-S06a-O | F69: =VLOOKUP(E69,'Segment Abs.'!$B:$C,2,0) -> #N/A | G69: P22-S05a-E | H69: =VLOOKUP(G69,'Segment Abs.'!$B:$C,2,0) -> #N/A | I69: P23-S06a-O | J69: =VLOOKUP(I69,'Segment Abs.'!$B:$C,2,0) -> #N/A | K69: P24-S06a-M | L69: =VLOOKUP(K69,'Segment Abs.'!$B:$C,2,0) -> #N/A | M69: P25-S06a-O | N69: =VLOOKUP(M69,'Segment Abs.'!$B:$C,2,0) -> #N/A | O69: P26-S05a-E | P69: =VLOOKUP(O69,'Segment Abs.'!$B:$C,2,0) -> #N/A | Q69: P27-S06a-O | R69: =VLOOKUP(Q69,'Segment Abs.'!$B:$C,2,0) -> #N/A | S69: P28-S06a-M | T69: =VLOOKUP(S69,'Segment Abs.'!$B:$C,2,0) -> #N/A | U69: P29-S06a-O | V69: =VLOOKUP(U69,'Segment Abs.'!$B:$C,2,0) -> #N/A | W69: =COUNTA(A10,C10,E10,G10,I10,K10,M10,O10,Q10,S10,U10,W10,Y10,A69,C69,E69,G69,I69,K69,M69,O69,Q69,S69,U69) -> 24 | X69: =COUNT(V69,T69,R69,P69,N69,L69,J69,H69,F69,D69,B69,Z10,X10,V10,T10,R10,P10,L10,J10,H10,F10,D10,B10) -> 0
A70: P19-S07a-O | B70: =VLOOKUP(A70,'Segment Abs.'!$B:$C,2,0) -> #N/A | C70: P20-S07a-M | D70: =VLOOKUP(C70,'Segment Abs.'!$B:$C,2,0) -> #N/A | E70: P21-S07a-O | F70: =VLOOKUP(E70,'Segment Abs.'!$B:$C,2,0) -> #N/A | G70: P22-S06a-E | H70: =VLOOKUP(G70,'Segment Abs.'!$B:$C,2,0) -> #N/A | I70: P23-S07a-O | J70: =VLOOKUP(I70,'Segment Abs.'!$B:$C,2,0) -> #N/A | K70: P24-S07a-M | L70: =VLOOKUP(K70,'Segment Abs.'!$B:$C,2,0) -> #N/A | M70: P25-S07a-O | N70: =VLOOKUP(M70,'Segment Abs.'!$B:$C,2,0) -> #N/A | O70: P26-S06a-E | P70: =VLOOKUP(O70,'Segment Abs.'!$B:$C,2,0) -> #N/A | Q70: P27-S07a-O | R70: =VLOOKUP(Q70,'Segment Abs.'!$B:$C,2,0) -> #N/A | S70: P28-S07a-M | T70: =VLOOKUP(S70,'Segment Abs.'!$B:$C,2,0) -> #N/A | U70: P29-S07a-O | V70: =VLOOKUP(U70,'Segment Abs.'!$B:$C,2,0) -> #N/A | W70: =COUNTA(A11,C11,E11,G11,I11,K11,M11,O11,Q11,S11,U11,W11,Y11,A70,C70,E70,G70,I70,K70,M70,O70,Q70,S70,U70) -> 24 | X70: =COUNT(V70,T70,R70,P70,N70,L70,J70,H70,F70,D70,B70,Z11,X11,V11,T11,R11,P11,L11,J11,H11,F11,D11,B11) -> 0
A71: P19-S08a-O | B71: =VLOOKUP(A71,'Segment Abs.'!$B:$C,2,0) -> #N/A | C71: P20-S08a-M© | D71: =VLOOKUP(C71,'Segment Abs.'!$B:$C,2,0) -> #N/A | E71: P21-S08a-O | F71: =VLOOKUP(E71,'Segment Abs.'!$B:$C,2,0) -> #N/A | G71: P22-S34a-O | H71: =VLOOKUP(G71,'Segment Abs.'!$B:$C,2,0) -> #N/A | I71: P23-S08a-O | J71: =VLOOKUP(I71,'Segment Abs.'!$B:$C,2,0) -> #N/A | K71: P24-S08a-M© | L71: =VLOOKUP(K71,'Segment Abs.'!$B:$C,2,0) -> #N/A | M71: P25-S08a-O | N71: =VLOOKUP(M71,'Segment Abs.'!$B:$C,2,0) -> #N/A | O71: P26-S34a-O | P71: =VLOOKUP(O71,'Segment Abs.'!$B:$C,2,0) -> #N/A | Q71: P27-S08a-O | R71: =VLOOKUP(Q71,'Segment Abs.'!$B:$C,2,0) -> #N/A | S71: P28-S08a-M© | T71: =VLOOKUP(S71,'Segment Abs.'!$B:$C,2,0) -> #N/A | U71: P29-S08a-O | V71: =VLOOKUP(U71,'Segment Abs.'!$B:$C,2,0) -> #N/A | W71: =COUNTA(A12,C12,E12,G12,I12,K12,M12,O12,Q12,S12,U12,W12,Y12,A71,C71,E71,G71,I71,K71,M71,O71,Q71,S71,U71) -> 24 | X71: =COUNT(V71,T71,R71,P71,N71,L71,J71,H71,F71,D71,B71,Z12,X12,V12,T12,R12,P12,L12,J12,H12,F12,D12,B12) -> 0
A72: P19-S09a-O© | B72: =VLOOKUP(A72,'Segment Abs.'!$B:$C,2,0) -> #N/A | C72: P20-S09a-M | D72: =VLOOKUP(C72,'Segment Abs.'!$B:$C,2,0) -> #N/A | E72: P21-S09a-O© | F72: =VLOOKUP(E72,'Segment Abs.'!$B:$C,2,0) -> #N/A | G72: P22-S33a-O© | H72: =VLOOKUP(G72,'Segment Abs.'!$B:$C,2,0) -> #N/A | I72: P23-S09a-O© | J72: =VLOOKUP(I72,'Segment Abs.'!$B:$C,2,0) -> #N/A | K72: P24-S09a-M | L72: =VLOOKUP(K72,'Segment Abs.'!$B:$C,2,0) -> #N/A | M72: P25-S09a-O© | N72: =VLOOKUP(M72,'Segment Abs.'!$B:$C,2,0) -> #N/A | O72: P26-S33a-O© | P72: =VLOOKUP(O72,'Segment Abs.'!$B:$C,2,0) -> #N/A | Q72: P27-S09a-O© | R72: =VLOOKUP(Q72,'Segment Abs.'!$B:$C,2,0) -> #N/A | S72: P28-S09a-M | T72: =VLOOKUP(S72,'Segment Abs.'!$B:$C,2,0) -> #N/A | U72: P29-S09a-O© | V72: =VLOOKUP(U72,'Segment Abs.'!$B:$C,2,0) -> #N/A | W72: =COUNTA(A13,C13,E13,G13,I13,K13,M13,O13,Q13,S13,U13,W13,Y13,A72,C72,E72,G72,I72,K72,M72,O72,Q72,S72,U72) -> 24 | X72: =COUNT(V72,T72,R72,P72,N72,L72,J72,H72,F72,D72,B72,Z13,X13,V13,T13,R13,P13,L13,J13,H13,F13,D13,B13) -> 0
A73: P19-S10a-O | B73: =VLOOKUP(A73,'Segment Abs.'!$B:$C,2,0) -> #N/A | C73: P20-S10a-M© | D73: =VLOOKUP(C73,'Segment Abs.'!$B:$C,2,0) -> #N/A | E73: P21-S10a-O | F73: =VLOOKUP(E73,'Segment Abs.'!$B:$C,2,0) -> #N/A | G73: P22-S32a-O | H73: =VLOOKUP(G73,'Segment Abs.'!$B:$C,2,0) -> #N/A | I73: P23-S10a-O | J73: =VLOOKUP(I73,'Segment Abs.'!$B:$C,2,0) -> #N/A | K73: P24-S10a-M© | L73: =VLOOKUP(K73,'Segment Abs.'!$B:$C,2,0) -> #N/A | M73: P25-S10a-O | N73: =VLOOKUP(M73,'Segment Abs.'!$B:$C,2,0) -> #N/A | O73: P26-S32a-O | P73: =VLOOKUP(O73,'Segment Abs.'!$B:$C,2,0) -> #N/A | Q73: P27-S10a-O | R73: =VLOOKUP(Q73,'Segment Abs.'!$B:$C,2,0) -> #N/A | S73: P28-S10a-M© | T73: =VLOOKUP(S73,'Segment Abs.'!$B:$C,2,0) -> #N/A | U73: P29-S10a-O | V73: =VLOOKUP(U73,'Segment Abs.'!$B:$C,2,0) -> #N/A | W73: =COUNTA(A14,C14,E14,G14,I14,K14,M14,O14,Q14,S14,U14,W14,Y14,A73,C73,E73,G73,I73,K73,M73,O73,Q73,S73,U73) -> 24 | X73: =COUNT(V73,T73,R73,P73,N73,L73,J73,H73,F73,D73,B73,Z14,X14,V14,T14,R14,P14,L14,J14,H14,F14,D14,B14) -> 0
A74: P19-S11a-O© | B74: =VLOOKUP(A74,'Segment Abs.'!$B:$C,2,0) -> #N/A | C74: P20-S11a-M | D74: =VLOOKUP(C74,'Segment Abs.'!$B:$C,2,0) -> #N/A | E74: P21-S11a-O© | F74: =VLOOKUP(E74,'Segment Abs.'!$B:$C,2,0) -> #N/A | G74: P22-S31a-O© | H74: =VLOOKUP(G74,'Segment Abs.'!$B:$C,2,0) -> #N/A | I74: P23-S11a-O© | J74: =VLOOKUP(I74,'Segment Abs.'!$B:$C,2,0) -> #N/A | K74: P24-S11a-M | L74: =VLOOKUP(K74,'Segment Abs.'!$B:$C,2,0) -> #N/A | M74: P25-S11a-O© | N74: =VLOOKUP(M74,'Segment Abs.'!$B:$C,2,0) -> #N/A | O74: P26-S31a-O© | P74: =VLOOKUP(O74,'Segment Abs.'!$B:$C,2,0) -> #N/A | Q74: P27-S11a-O© | R74: =VLOOKUP(Q74,'Segment Abs.'!$B:$C,2,0) -> #N/A | S74: P28-S11a-M | T74: =VLOOKUP(S74,'Segment Abs.'!$B:$C,2,0) -> #N/A | U74: P29-S11a-O© | V74: =VLOOKUP(U74,'Segment Abs.'!$B:$C,2,0) -> #N/A | W74: =COUNTA(A15,C15,E15,G15,I15,K15,M15,O15,Q15,S15,U15,W15,Y15,A74,C74,E74,G74,I74,K74,M74,O74,Q74,S74,U74) -> 24 | X74: =COUNT(V74,T74,R74,P74,N74,L74,J74,H74,F74,D74,B74,Z15,X15,V15,T15,R15,P15,L15,J15,H15,F15,D15,B15) -> 0
A75: P19-S12a-O | B75: =VLOOKUP(A75,'Segment Abs.'!$B:$C,2,0) -> #N/A | C75: P20-S12a-M© | D75: =VLOOKUP(C75,'Segment Abs.'!$B:$C,2,0) -> #N/A | E75: P21-S12a-O | F75: =VLOOKUP(E75,'Segment Abs.'!$B:$C,2,0) -> #N/A | G75: P22-S30a-O | H75: =VLOOKUP(G75,'Segment Abs.'!$B:$C,2,0) -> #N/A | I75: P23-S12a-O | J75: =VLOOKUP(I75,'Segment Abs.'!$B:$C,2,0) -> #N/A | K75: P24-S12a-M© | L75: =VLOOKUP(K75,'Segment Abs.'!$B:$C,2,0) -> #N/A | M75: P25-S12a-O | N75: =VLOOKUP(M75,'Segment Abs.'!$B:$C,2,0) -> #N/A | O75: P26-S30a-O | P75: =VLOOKUP(O75,'Segment Abs.'!$B:$C,2,0) -> #N/A | Q75: P27-S12a-O | R75: =VLOOKUP(Q75,'Segment Abs.'!$B:$C,2,0) -> #N/A | S75: P28-S12a-M© | T75: =VLOOKUP(S75,'Segment Abs.'!$B:$C,2,0) -> #N/A | U75: P29-S12a-O | V75: =VLOOKUP(U75,'Segment Abs.'!$B:$C,2,0) -> #N/A | W75: =COUNTA(A16,C16,E16,G16,I16,K16,M16,O16,Q16,S16,U16,W16,Y16,A75,C75,E75,G75,I75,K75,M75,O75,Q75,S75,U75) -> 24 | X75: =COUNT(V75,T75,R75,P75,N75,L75,J75,H75,F75,D75,B75,Z16,X16,V16,T16,R16,P16,L16,J16,H16,F16,D16,B16) -> 0
... A104: P19-S12a-M© | B104: =VLOOKUP(A104,'Segment Abs.'!$B:$C,2,0) -> #N/A | C104: P20-S12a-O | D104: =VLOOKUP(C104,'Segment Abs.'!$B:$C,2,0) -> #N/A | E104: P21-S01a-E | F104: =VLOOKUP(E104,'Segment Abs.'!$B:$C,2,0) -> #N/A | G104: P22-S01a-O | H104: =VLOOKUP(G104,'Segment Abs.'!$B:$C,2,0) -> #N/A | I104: P23-S12a-M© | J104: =VLOOKUP(I104,'Segment Abs.'!$B:$C,2,0) -> #N/A | K104: P24-S12a-O | L104: =VLOOKUP(K104,'Segment Abs.'!$B:$C,2,0) -> #N/A | M104: P25-S01a-E | N104: =VLOOKUP(M104,'Segment Abs.'!$B:$C,2,0) -> #N/A | O104: P26-S01a-O | P104: =VLOOKUP(O104,'Segment Abs.'!$B:$C,2,0) -> #N/A | Q104: P27-S12a-M© | R104: =VLOOKUP(Q104,'Segment Abs.'!$B:$C,2,0) -> #N/A | S104: P28-S12a-O | T104: =VLOOKUP(S104,'Segment Abs.'!$B:$C,2,0) -> #N/A | U104: P29-S01a-E | V104: =VLOOKUP(U104,'Segment Abs.'!$B:$C,2,0) -> #N/A | W104: =COUNTA(A45,C45,E45,G45,I45,K45,M45,O45,Q45,S45,U45,W45,Y45,A104,C104,E104,G104,I104,K104,M104,O104,Q104,S104,U104) -> 24 | X104: =COUNT(V104,T104,R104,P104,N104,L104,J104,H104,F104,D104,B104,Z45,X45,V45,T45,R45,P45,L45,J45,H45,F45,D45,B45) -> 0
A105: P19-S11a-M | B105: =VLOOKUP(A105,'Segment Abs.'!$B:$C,2,0) -> #N/A | C105: P20-S11a-O© | D105: =VLOOKUP(C105,'Segment Abs.'!$B:$C,2,0) -> #N/A | I105: P23-S11a-M | J105: =VLOOKUP(I105,'Segment Abs.'!$B:$C,2,0) -> #N/A | K105: P24-S11a-O© | L105: =VLOOKUP(K105,'Segment Abs.'!$B:$C,2,0) -> #N/A | Q105: P27-S11a-M | R105: =VLOOKUP(Q105,'Segment Abs.'!$B:$C,2,0) -> #N/A | S105: P28-S11a-O© | T105: =VLOOKUP(S105,'Segment Abs.'!$B:$C,2,0) -> #N/A | W105: =COUNTA(A46,C46,E46,G46,I46,K46,M46,O46,Q46,S46,U46,W46,Y46,A105,C105,E105,G105,I105,K105,M105,O105,Q105,S105,U105) -> 12 | X105: =COUNT(V105,T105,R105,P105,N105,L105,J105,H105,F105,D105,B105,Z46,X46,V46,T46,R46,P46,L46,J46,H46,F46,D46,B46) -> 0
A106: P19-S10a-M© | B106: =VLOOKUP(A106,'Segment Abs.'!$B:$C,2,0) -> #N/A | C106: P20-S10a-O | D106: =VLOOKUP(C106,'Segment Abs.'!$B:$C,2,0) -> #N/A | I106: P23-S10a-M© | J106: =VLOOKUP(I106,'Segment Abs.'!$B:$C,2,0) -> #N/A | K106: P24-S10a-O | L106: =VLOOKUP(K106,'Segment Abs.'!$B:$C,2,0) -> #N/A | Q106: P27-S10a-M© | R106: =VLOOKUP(Q106,'Segment Abs.'!$B:$C,2,0) -> #N/A | S106: P28-S10a-O | T106: =VLOOKUP(S106,'Segment Abs.'!$B:$C,2,0) -> #N/A | W106: =COUNTA(A47,C47,E47,G47,I47,K47,M47,O47,Q47,S47,U47,W47,Y47,A106,C106,E106,G106,I106,K106,M106,O106,Q106,S106,U106) -> 12 | X106: =COUNT(V106,T106,R106,P106,N106,L106,J106,H106,F106,D106,B106,Z47,X47,V47,T47,R47,P47,L47,J47,H47,F47,D47,B47) -> 0
A107: P19-S09a-M | B107: =VLOOKUP(A107,'Segment Abs.'!$B:$C,2,0) -> #N/A | C107: P20-S09a-O© | D107: =VLOOKUP(C107,'Segment Abs.'!$B:$C,2,0) -> #N/A | I107: P23-S09a-M | J107: =VLOOKUP(I107,'Segment Abs.'!$B:$C,2,0) -> #N/A | K107: P24-S09a-O© | L107: =VLOOKUP(K107,'Segment Abs.'!$B:$C,2,0) -> #N/A | Q107: P27-S09a-M | R107: =VLOOKUP(Q107,'Segment Abs.'!$B:$C,2,0) -> #N/A | S107: P28-S09a-O© | T107: =VLOOKUP(S107,'Segment Abs.'!$B:$C,2,0) -> #N/A | W107: =COUNTA(A48,C48,E48,G48,I48,K48,M48,O48,Q48,S48,U48,W48,Y48,A107,C107,E107,G107,I107,K107,M107,O107,Q107,S107,U107) -> 12 | X107: =COUNT(V107,T107,R107,P107,N107,L107,J107,H107,F107,D107,B107,Z48,X48,V48,T48,R48,P48,L48,J48,H48,F48,D48,B48) -> 0
A108: P19-S08a-M© | B108: =VLOOKUP(A108,'Segment Abs.'!$B:$C,2,0) -> #N/A | C108: P20-S08a-O | D108: =VLOOKUP(C108,'Segment Abs.'!$B:$C,2,0) -> #N/A | I108: P23-S08a-M© | J108: =VLOOKUP(I108,'Segment Abs.'!$B:$C,2,0) -> #N/A | K108: P24-S08a-O | L108: =VLOOKUP(K108,'Segment Abs.'!$B:$C,2,0) -> #N/A | Q108: P27-S08a-M© | R108: =VLOOKUP(Q108,'Segment Abs.'!$B:$C,2,0) -> #N/A | S108: P28-S08a-O | T108: =VLOOKUP(S108,'Segment Abs.'!$B:$C,2,0) -> #N/A | W108: =COUNTA(A49,C49,E49,G49,I49,K49,M49,O49,Q49,S49,U49,W49,Y49,A108,C108,E108,G108,I108,K108,M108,O108,Q108,S108,U108) -> 12 | X108: =COUNT(V108,T108,R108,P108,N108,L108,J108,H108,F108,D108,B108,Z49,X49,V49,T49,R49,P49,L49,J49,H49,F49,D49,B49) -> 0
A109: P19-S07a-M | B109: =VLOOKUP(A109,'Segment Abs.'!$B:$C,2,0) -> #N/A | C109: P20-S07a-O | D109: =VLOOKUP(C109,'Segment Abs.'!$B:$C,2,0) -> #N/A | I109: P23-S07a-M | J109: =VLOOKUP(I109,'Segment Abs.'!$B:$C,2,0) -> #N/A | K109: P24-S07a-O | L109: =VLOOKUP(K109,'Segment Abs.'!$B:$C,2,0) -> #N/A | Q109: P27-S07a-M | R109: =VLOOKUP(Q109,'Segment Abs.'!$B:$C,2,0) -> #N/A | S109: P28-S07a-O | T109: =VLOOKUP(S109,'Segment Abs.'!$B:$C,2,0) -> #N/A | W109: =COUNTA(A50,C50,E50,G50,I50,K50,M50,O50,Q50,S50,U50,W50,Y50,A109,C109,E109,G109,I109,K109,M109,O109,Q109,S109,U109) -> 12 | X109: =COUNT(V109,T109,R109,P109,N109,L109,J109,H109,F109,D109,B109,Z50,X50,V50,T50,R50,P50,L50,J50,H50,F50,D50,B50) -> 0
A110: P19-S06a-M | B110: =VLOOKUP(A110,'Segment Abs.'!$B:$C,2,0) -> #N/A | C110: P20-S06a-O | D110: =VLOOKUP(C110,'Segment Abs.'!$B:$C,2,0) -> #N/A | I110: P23-S06a-M | J110: =VLOOKUP(I110,'Segment Abs.'!$B:$C,2,0) -> #N/A | K110: P24-S06a-O | L110: =VLOOKUP(K110,'Segment Abs.'!$B:$C,2,0) -> #N/A | Q110: P27-S06a-M | R110: =VLOOKUP(Q110,'Segment Abs.'!$B:$C,2,0) -> #N/A | S110: P28-S06a-O | T110: =VLOOKUP(S110,'Segment Abs.'!$B:$C,2,0) -> #N/A | W110: =COUNTA(A51,C51,E51,G51,I51,K51,M51,O51,Q51,S51,U51,W51,Y51,A110,C110,E110,G110,I110,K110,M110,O110,Q110,S110,U110) -> 12 | X110: =COUNT(V110,T110,R110,P110,N110,L110,J110,H110,F110,D110,B110,Z51,X51,V51,T51,R51,P51,L51,J51,H51,F51,D51,B51) -> 0
A111: P19-S05a-M | B111: =VLOOKUP(A111,'Segment Abs.'!$B:$C,2,0) -> #N/A | C111: P20-S05a-O | D111: =VLOOKUP(C111,'Segment Abs.'!$B:$C,2,0) -> #N/A | I111: P23-S05a-M | J111: =VLOOKUP(I111,'Segment Abs.'!$B:$C,2,0) -> #N/A | K111: P24-S05a-O | L111: =VLOOKUP(K111,'Segment Abs.'!$B:$C,2,0) -> #N/A | Q111: P27-S05a-M | R111: =VLOOKUP(Q111,'Segment Abs.'!$B:$C,2,0) -> #N/A | S111: P28-S05a-O | T111: =VLOOKUP(S111,'Segment Abs.'!$B:$C,2,0) -> #N/A | W111: =COUNTA(A52,C52,E52,G52,I52,K52,M52,O52,Q52,S52,U52,W52,Y52,A111,C111,E111,G111,I111,K111,M111,O111,Q111,S111,U111) -> 12 | X111: =COUNT(V111,T111,R111,P111,N111,L111,J111,H111,F111,D111,B111,Z52,X52,V52,T52,R52,P52,L52,J52,H52,F52,D52,B52) -> 0
A112: P19-S04a-M | B112: =VLOOKUP(A112,'Segment Abs.'!$B:$C,2,0) -> #N/A | C112: P20-S04a-O | D112: =VLOOKUP(C112,'Segment Abs.'!$B:$C,2,0) -> #N/A | I112: P23-S04a-M | J112: =VLOOKUP(I112,'Segment Abs.'!$B:$C,2,0) -> #N/A | K112: P24-S04a-O | L112: =VLOOKUP(K112,'Segment Abs.'!$B:$C,2,0) -> #N/A | Q112: P27-S04a-M | R112: =VLOOKUP(Q112,'Segment Abs.'!$B:$C,2,0) -> #N/A | S112: P28-S04a-O | T112: =VLOOKUP(S112,'Segment Abs.'!$B:$C,2,0) -> #N/A | W112: =COUNTA(A53,C53,E53,G53,I53,K53,M53,O53,Q53,S53,U53,W53,Y53,A112,C112,E112,G112,I112,K112,M112,O112,Q112,S112,U112) -> 12 | X112: =COUNT(V112,T112,R112,P112,N112,L112,J112,H112,F112,D112,B112,Z53,X53,V53,T53,R53,P53,L53,J53,H53,F53,D53,B53) -> 0
A113: P19-S03a-M | B113: =VLOOKUP(A113,'Segment Abs.'!$B:$C,2,0) -> #N/A | C113: P20-S03a-O | D113: =VLOOKUP(C113,'Segment Abs.'!$B:$C,2,0) -> #N/A | I113: P23-S03a-M | J113: =VLOOKUP(I113,'Segment Abs.'!$B:$C,2,0) -> #N/A | K113: P24-S03a-O | L113: =VLOOKUP(K113,'Segment Abs.'!$B:$C,2,0) -> #N/A | Q113: P27-S03a-M | R113: =VLOOKUP(Q113,'Segment Abs.'!$B:$C,2,0) -> #N/A | S113: P28-S03a-O | T113: =VLOOKUP(S113,'Segment Abs.'!$B:$C,2,0) -> #N/A | W113: =COUNTA(A54,C54,E54,G54,I54,K54,M54,O54,Q54,S54,U54,W54,Y54,A113,C113,E113,G113,I113,K113,M113,O113,Q113,S113,U113) -> 12 | X113: =COUNT(V113,T113,R113,P113,N113,L113,J113,H113,F113,D113,B113,Z54,X54,V54,T54,R54,P54,L54,J54,H54,F54,D54,B54) -> 0
A114: P19-S02a-M | B114: =VLOOKUP(A114,'Segment Abs.'!$B:$C,2,0) -> #N/A | C114: P20-S02a-O | D114: =VLOOKUP(C114,'Segment Abs.'!$B:$C,2,0) -> #N/A | I114: P23-S02a-M | J114: =VLOOKUP(I114,'Segment Abs.'!$B:$C,2,0) -> #N/A | K114: P24-S02a-O | L114: =VLOOKUP(K114,'Segment Abs.'!$B:$C,2,0) -> #N/A | Q114: P27-S02a-M | R114: =VLOOKUP(Q114,'Segment Abs.'!$B:$C,2,0) -> #N/A | S114: P28-S02a-O | T114: =VLOOKUP(S114,'Segment Abs.'!$B:$C,2,0) -> #N/A | W114: =COUNTA(A55,C55,E55,G55,I55,K55,M55,O55,Q55,S55,U55,W55,Y55,A114,C114,E114,G114,I114,K114,M114,O114,Q114,S114,U114) -> 12 | X114: =COUNT(V114,T114,R114,P114,N114,L114,J114,H114,F114,D114,B114,Z55,X55,V55,T55,R55,P55,L55,J55,H55,F55,D55,B55) -> 0
A115: P19-S01a-M | B115: =VLOOKUP(A115,'Segment Abs.'!$B:$C,2,0) -> #N/A | C115: P20-S01a-O | D115: =VLOOKUP(C115,'Segment Abs.'!$B:$C,2,0) -> #N/A | I115: P23-S01a-M | J115: =VLOOKUP(I115,'Segment Abs.'!$B:$C,2,0) -> #N/A | K115: P24-S01a-O | L115: =VLOOKUP(K115,'Segment Abs.'!$B:$C,2,0) -> #N/A | Q115: P27-S01a-M | R115: =VLOOKUP(Q115,'Segment Abs.'!$B:$C,2,0) -> #N/A | S115: P28-S01a-O | T115: =VLOOKUP(S115,'Segment Abs.'!$B:$C,2,0) -> #N/A | W115: =COUNTA(A56,C56,E56,G56,I56,K56,M56,O56,Q56,S56,U56,W56,Y56,A115,C115,E115,G115,I115,K115,M115,O115,Q115,S115,U115) -> 12 | X115: =COUNT(V115,T115,R115,P115,N115,L115,J115,H115,F115,D115,B115,Z56,X56,V56,T56,R56,P56,L56,J56,H56,F56,D56,B56) -> 0
A116: =COUNTA(A$64:A$115) -> 52 | B116: =COUNTIF(B$64:B$115,">0") -> 0 | C116: =COUNTA(C$64:C$115) -> 52 | D116: =COUNTIF(D$64:D$115,">0") -> 0 | E116: =COUNTA(E$64:E$115) -> 41 | F116: =COUNTIF(F$64:F$115,">0") -> 0 | G116: =COUNTA(G$64:G$115) -> 41 | H116: =COUNTIF(H$64:H$115,">0") -> 0 | I116: =COUNTA(I$64:I$115) -> 52 | J116: =COUNTIF(J$64:J$115,">0") -> 0 | K116: =COUNTA(K$64:K$115) -> 52 | L116: =COUNTIF(L$64:L$115,">0") -> 0 | M116: =COUNTA(M$64:M$115) -> 41 | N116: =COUNTIF(N$64:N$115,">0") -> 0 | O116: =COUNTA(O$64:O$115) -> 41 | P116: =COUNTIF(P$64:P$115,">0") -> 0 | Q116: =COUNTA(Q$64:Q$115) -> 52 | R116: =COUNTIF(R$64:R$115,">0") -> 0 | S116: =COUNTA(S$64:S$115) -> 52 | T116: =COUNTIF(T$64:T$115,">0") -> 0 | U116: =COUNTA(U$64:U$115) -> 41 | V116: =COUNTIF(V$64:V$115,">0") -> 0 | W116: =SUM(A57,C57,E57,G57,I57,K57,M57,O57,Q57,S57,U57,W57,Y57,A116,C116,E116,G116,I116,K116,M116,O116,Q116,S116,U116) -> 1116 | X116: =SUM(V116,T116,R116,P116,N116,L116,J116,H116,F116,D116,B116,Z57,X57,V57,T57,R57,P57,L57,J57,H57,F57,D57,B57,N57) -> 0
A117: =COUNTIF(A$64:A$115,"*©*") -> 18 | B117: =COUNTIFS(A$64:A$115,"*©*",B$64:B$115,">10") -> 0 | C117: =COUNTIF(C$64:C$115,"*©*") -> 18 | D117: =COUNTIFS(C$64:C$115,"*©*",D$64:D$115,">10") -> 0 | E117: =COUNTIF(E$64:E$115,"*©*") -> 13 | F117: =COUNTIFS(E$64:E$115,"*©*",F$64:F$115,">10") -> 0 | G117: =COUNTIF(G$64:G$115,"*©*") -> 13 | H117: =COUNTIFS(G$64:G$115,"*©*",H$64:H$115,">10") -> 0 | I117: =COUNTIF(I$64:I$115,"*©*") -> 18 | J117: =COUNTIFS(I$64:I$115,"*©*",J$64:J$115,">10") -> 0 | K117: =COUNTIF(K$64:K$115,"*©*") -> 18 | L117: =COUNTIFS(K$64:K$115,"*©*",L$64:L$115,">10") -> 0 | M117: =COUNTIF(M$64:M$115,"*©*") -> 13 | N117: =COUNTIFS(M$64:M$115,"*©*",N$64:N$115,">10") -> 0 | O117: =COUNTIF(O$64:O$115,"*©*") -> 13 | P117: =COUNTIFS(O$64:O$115,"*©*",P$64:P$115,">10") -> 0 | Q117: =COUNTIF(Q$64:Q$115,"*©*") -> 18 | R117: =COUNTIFS(Q$64:Q$115,"*©*",R$64:R$115,">10") -> 0 | S117: =COUNTIF(S$64:S$115,"*©*") -> 18 | T117: =COUNTIFS(S$64:S$115,"*©*",T$64:T$115,">10") -> 0 | U117: =COUNTIF(U$64:U$115,"*©*") -> 13 | V117: =COUNTIFS(U$64:U$115,"*©*",V$64:V$115,">10") -> 0 | W117: =SUM(A58,C58,E58,G58,I58,K58,M58,O58,Q58,S58,U58,W58,Y58,A117,C117,E117,G117,I117,K117,M117,O117,Q117,S117,U117) -> 372 | X117: =SUM(V117,T117,R117,P117,N117,L117,J117,H117,F117,D117,B117,Z58,X58,V58,T58,R58,P58,L58,J58,H58,F58,D58,B58,N58) -> 0
A119: Description | D119: 45809 | E119: 45839 | F119: 45870 | G119: 45901 | H119: 45931 | I119: 45962 | J119: 45992 | K119: 46023 | L119: 46054 | M119: 46082 | N119: 46113 | O119: 46143 | P119: 46174 | Q119: 46204 | R119: 46235 | S119: 46266 | T119: 46296 | U119: 46327 | V119: 46357 | W119: 46388 | X119: 46419 | Y119: 46447 | Z119: Total
A120: Total Segments Casted | D120: =COUNTIF($A$5:$Z$56,D119)+COUNTIF($A$64:$X$115,D119) -> 0 | E120: =COUNTIF($A$5:$Z$56,E119)+COUNTIF($A$64:$X$115,E119) -> 0 | F120: =COUNTIF($A$5:$Z$56,F119)+COUNTIF($A$64:$X$115,F119) -> 0 | G120: =COUNTIF($A$5:$Z$56,G119)+COUNTIF($A$64:$X$115,G119) -> 0 | H120: =COUNTIF($A$5:$Z$56,H119)+COUNTIF($A$64:$X$115,H119) -> 0 | I120: =COUNTIF($A$5:$Z$56,I119)+COUNTIF($A$64:$X$115,I119) -> 0 | J120: =COUNTIF($A$5:$Z$56,J119)+COUNTIF($A$64:$X$115,J119) -> 0 | K120: =COUNTIF($A$5:$Z$56,K119)+COUNTIF($A$64:$X$115,K119) -> 0 | ... Y120: =COUNTIF($A$5:$Z$56,Y119)+COUNTIF($A$64:$X$115,Y119) -> 0 | Z120: =SUM(D120:Y120) -> 0
A121: Total Cable Segments Casted | D121: =COUNTIFS('Segment Abs.'!$B:$B,"*©*",'Segment Abs.'!$C:$C,'Segment Summary'!D$119,'Segment Abs.'!$C:$C,">10") -> 0 | E121: =COUNTIFS('Segment Abs.'!$B:$B,"*©*",'Segment Abs.'!$C:$C,'Segment Summary'!E$119,'Segment Abs.'!$C:$C,">10") -> 0 | F121: =COUNTIFS('Segment Abs.'!$B:$B,"*©*",'Segment Abs.'!$C:$C,'Segment Summary'!F$119,'Segment Abs.'!$C:$C,">10") -> 0 | G121: =COUNTIFS('Segment Abs.'!$B:$B,"*©*",'Segment Abs.'!$C:$C,'Segment Summary'!G$119,'Segment Abs.'!$C:$C,">10") -> 0 | H121: =COUNTIFS('Segment Abs.'!$B:$B,"*©*",'Segment Abs.'!$C:$C,'Segment Summary'!H$119,'Segment Abs.'!$C:$C,">10") -> 0 | I121: =COUNTIFS('Segment Abs.'!$B:$B,"*©*",'Segment Abs.'!$C:$C,'Segment Summary'!I$119,'Segment Abs.'!$C:$C,">10") -> 0 | J121: =COUNTIFS('Segment Abs.'!$B:$B,"*©*",'Segment Abs.'!$C:$C,'Segment Summary'!J$119,'Segment Abs.'!$C:$C,">10") -> 0 | K121: =COUNTIFS('Segment Abs.'!$B:$B,"*©*",'Segment Abs.'!$C:$C,'Segment Summary'!K$119,'Segment Abs.'!$C:$C,">10") -> 0 | ... Y121: =COUNTIFS('Segment Abs.'!$B:$B,"*©*",'Segment Abs.'!$C:$C,'Segment Summary'!Y$119,'Segment Abs.'!$C:$C,">10") -> 0 | Z121: =SUM(D121:Y121) -> 0

Sheet Schedule 4
B1: 406.a / 407.c / 408.c | C1: Precast - Box girder segments | D1: Nos. | E1: Palashbari | F1: 1 | G1: MPSB/MB/19 MPSB/Sur/1429 MPSB/MB/20 | H1: 45824 | I1: IPC - 18 | J1: P17-BP-S09a-O© | K1: 45839 | L1: Profile Check Survey Check Formwork & Concreting
B2: 406.a / 407.c | C2: Precast - Box girder segments | D2: Nos. | E2: Palashbari | F2: 1 | G2: MPSB/MB/22 MPSB/MB/25 | H2: 21-Jun-25 25-Jun-25 | I2: IPC - 18 | J2: P17-BP-S10a-O | K2: 45839
B3: 406.a / 407.c / 408.c | C3: Precast - Box girder segments | D3: Nos. | E3: Palashbari | F3: 1 | G3: MPSB/Sur/1482 MPSB/MB/0031 | H3: 2-Jul-25 2-Jul-25 | I3: IPC - 18 | J3: P17-BP-S11a-O© | K3: 45839
B4: 406.a / 407.c | C4: Precast - Box girder segments | D4: Nos. | E4: Palashbari | F4: 1 | G4: MPSB/MB/034 MPSB/Sur/1506 MPSB/MB/038 | H4: 7-Jul-25 9-Jul-25 9-Jul-25 | I4: IPC - 18 | J4: P17-BP-S12a-O | K4: 45839
B5: 406.a / 407.c / 408.c | C5: Precast - Box girder segments | D5: Nos. | E5: Palashbari | F5: 1 | G5: MPSB/MB/040 MPSB/Sur/1527 MPSB/MB/042 | H5: 11-Jul-25 15-Jul-25 15-Jul-25 | I5: IPC - 18 | J5: P17-BP-S13a-O© | K5: 45839
B6: 406.a / 407.c | C6: Precast - Box girder segments | D6: Nos. | E6: Palashbari | F6: 1 | G6: MPSB/MB/046 MPSB/Sur/1558 MPSB/MB/049 | H6: 17-Jul-25 21-Jul-25 21-Jul-25 | I6: IPC - 18 | J6: P17-BP-S14a-O | K6: 45839
B7: 406.a / 407.c / 408.c | C7: Precast - Box girder segments | D7: Nos. | E7: Palashbari | F7: 1 | G7: MPSB/MB/054 MPSB/Sur/1589 MPSB/MB/057 | H7: 25-Jul-25 26-Jul-25 28-Jul-25 | I7: IPC - 18 | J7: P17-BP-S15a-O© | K7: 45839
B8: 406.a / 407.c / 408.c | C8: Precast - Box girder segments | D8: Nos. | E8: Sualkuchi | F8: 1 | G8: MPSB/MB/033 MPSB/Sur/1508 MPSB/MB/039 | H8: 3-Jul-25 10-Jul-25 10-Jul-25 | I8: IPC - 18 | J8: P25-KS-S09-O© | K8: 45839
B9: 406.a / 407.c | C9: Precast - Box girder segments | D9: Nos. | E9: Sualkuchi | F9: 1 | G9: MPSB/MB/044 MPSB/Sur/1546 MPSB/MB/047 | H9: 16-Jul-25 19-Jul-25 19-Jul-25 | I9: IPC - 18 | J9: P25-KS-S10-O | K9: 45839
B10: 406.a / 407.c / 408.c | C10: Precast - Box girder segments | D10: Nos. | E10: Sualkuchi | F10: 1 | G10: MPSB/MB/037 MPSB/Sur/1603 MPSB/MB/059 | H10: 8-Jul-25 29-Jul-25 29-Jul-25 | I10: IPC - 18 | J10: P25-KS-S11-O© | K10: 45839
B11: 406.a / 407.c | C11: Precast - Box girder segments | D11: Nos. | E11: Palashbari | F11: 1 | G11: MPSB/MB/60 MPSB/Sur/1636 MPSB/MB/65 | H11: 30-Jul-25 1-Aug-25 1-Aug-25 | I11: IPC - 19 | J11: P17-BP-S16a-O | K11: 45870
B12: 406.a / 407.c / 408.c | C12: Precast - Box girder segments | D12: Nos. | E12: Palashbari | F12: 1 | G12: MPSB/MB/69 MPSB/Sur/1657 MPSB/MB/74 | H12: 4-Aug-25 7-Aug-25 7-Aug-25 | I12: IPC - 19 | J12: P17-BP-S17a-O© | K12: 45870
B13: 406.a / 407.c | C13: Precast - Box girder segments | D13: Nos. | E13: Palashbari | F13: 1 | G13: MPSB/MB/75 MPSB/Sur/1685 MPSB/MB/83 | H13: 7-Aug-25 12-Aug-25 12-Aug-25 | I13: IPC - 19 | J13: P17-BP-S18a-O | K13: 45870
... B496: 406.a / 407.c | C496: Precast - Box girder segments | D496: Nos. | E496: Sualkuchi | F496: 1 | G496: MPSB/MB/2237 MPSB/Sur/3815 MPSB/MB/2241 | H496: 30-Jul-26 31-Jul-26 31-Jul-26 | I496: IPC - 34 | J496: P24-KS-S04-M | K496: 46204
B497: 401.b | C497: Ground preparation and placing of Cutting Edge | D497: Nos. | E497: Palashbari | F497: 1 | G497: MPSB/Sur/357 | H497: 45681 | I497: IPC - 10 | J497: P10 | K497: P10
B498: 401.c | C498: Shuttering and Scaffolding | D498: Nos. | E498: Palashbari | F498: 1 | G498: MPSB/Sur/368 | H498: 45684 | I498: IPC - 10 | J498: P10 | K498: P10
B499: 402.a | C499: Well Steining - Casting & Sinking (Including Well curb) | D499: Rmt | E499: Palashbari | F499: 4.32 | G499: MPSB/Str/489 MPSB/Sur/426 MPSB/Str/494 MPSB/Sur/453 MPSB/Sur/454 | H499: 5-Feb-25 6-Feb-25 6-Feb-25 11-Feb-25 11-Feb-25 | I499: IPC - 11 | J499: P10 - Well Curb | K499: P10
B500: 402.a | C500: Well Steining - Casting & Sinking (Including Well curb) | D500: Rmt | E500: Palashbari | F500: 2.5 | G500: MPSB/Str/577 MPSB/Sur/508 MPSB/Str/578 MPSB/Sur/545 | H500: 19-Feb-25 19-Feb-25 19-Feb-25 24-Feb-25 | I500: IPC - 11 | J500: P10 - 1st Lift | K500: P10
B501: 402.a | C501: Well Steining - Casting & Sinking (Including Well curb) | D501: Rmt | E501: Palashbari | F501: 2.5 | G501: MPSB/Str/659 MPSB/Sur/580 MPSB/Str/660 | H501: 27-Feb-25 27-Feb-25 27-Feb-25 | I501: IPC - 11 | J501: P10 - 2nd Lift | K501: P10
B502: 402.a | C502: Well Steining - Casting & Sinking (Including Well curb) | D502: Rmt | E502: Palashbari | F502: 2.5 | G502: MPSB/Str/666 MPSB/Sur/590 MPSB/Str/667 | H502: 28-Feb-25 28-Feb-25 28-Feb-25 | I502: IPC - 11 | J502: P10 - 3rd Lift | K502: P10
B503: 402.a | C503: Well Steining - Casting & Sinking (Including Well curb) | D503: Rmt | E503: Palashbari | F503: =2.65-0.015-0.02 -> 2.615 | G503: MPSB/Str/837 MPSB/Str/838 MPSB/Sur/745 | H503: 20-Mar-25 20-Mar-25 20-Mar-25 | I503: IPC - 13 | J503: P10 - 4th Lift | K503: P10
B504: 402.a | C504: Well Steining - Casting & Sinking (Including Well curb) | D504: Rmt | E504: Palashbari | F504: 2.32 | G504: MPSB/Str/914 MPSB/Str/915 MPSB/Sur/798 | H504: 26-Mar-25 26-Mar-25 26-Mar-25 | I504: IPC - 13 | J504: P10 - 5th Lift | K504: P10
B505: 402.a | C505: Well Steining - Casting & Sinking (Including Well curb) | D505: Rmt | E505: Palashbari | F505: 2.5 | G505: MPSB/Str/991 MPSB/Str/992 MPSB/Sur/859 | H505: 31-Mar-25 31-Mar-25 31-Mar-25 | I505: IPC - 13 | J505: P10 - 6th Lift | K505: P10
B506: 402.a | C506: Well Steining - Casting & Sinking (Including Well curb) | D506: Rmt | E506: Palashbari | F506: 2.5 | G506: MPSB/Str/1102 MPSB/Sur/964 MPSB/Str/1103 MPSB/Sur/1000 | H506: 11-Apr-25 11-Apr-25 11-Apr-25 15-Apr-25 | I506: IPC - 14 | J506: P10 - 7th Lift | K506: P10
B507: 402.a | C507: Well Steining - Casting & Sinking (Including Well curb) | D507: Rmt | E507: Palashbari | F507: 0.545 | G507: MPSB/Str/1216 MPSB/Sur/1057 MPSB/Str/1217 | H507: 21-Apr-25 21-Apr-25 21-Apr-25 | I507: IPC - 14 | J507: P10 - 8th Lift | K507: P10
B508: 402.a | C508: Well Steining - Casting & Sinking (Including Well curb) | D508: Rmt | E508: Palashbari | F508: 2.81 | G508: MPSB/Str/1248 MPSB/Sur/1077 MPSB/Str/1249 | H508: 24-Apr-25 24-Apr-25 24-Apr-25 | I508: IPC - 14 | J508: P10 - 9th Lift | K508: P10
B509: 402.a | C509: Well Steining - Casting & Sinking (Including Well curb) | D509: Rmt | E509: Palashbari | F509: 2.5 | G509: MPSB/Str/1472 MPSB/Sur/1253 MPSB/Str/1473 MPSB/Sur/1291 | H509: 11-May-25 11-May-25 11-May-25 16-May-25 | I509: IPC - 15 | J509: P10 - 10th Lift | K509: P10
B510: 402.a | C510: Well Steining - Casting & Sinking (Including Well curb) | D510: Rmt | E510: Palashbari | F510: 2.5 | G510: MPSB/Str/1561 MPSB/Sur/1342 MPSB/Str/1562 | H510: 24-May-25 24-May-25 24-May-25 | I510: IPC - 15 | J510: P10 - 11th Lift | K510: P10
B511: 402.a | C511: Well Steining - Casting & Sinking (Including Well curb) | D511: Rmt | E511: Palashbari | F511: 2.2 | G511: MPSB/Str/1600 MPSB/Sur/1385 MPSB/Str/1601 | H511: 29-May-25 29-May-25 29-May-25 | I511: IPC - 15 | J511: P10 - 12th Lift | K511: P10
B512: 402.a | C512: Well Steining - Casting & Sinking (Including Well curb) | D512: Rmt | E512: Palashbari | F512: 2.8 | G512: MPSB/Str/1674 MPSB/Str/1675 MPSB/Sur/1462 | H512: 17-Jun-25 17-Jun-25 27-Jun-25 | I512: IPC - 16 | J512: P10 - 13th Lift | K512: P10
B513: 402.a | C513: Well Steining - Casting & Sinking (Including Well curb) | D513: Rmt | E513: Palashbari | F513: 2.7 | G513: MPSB/Str/1694 MPSB/Sur/1451 MPSB/Str/1695 MPSB/Sur/1462 | H513: 23-Jun-25 23-Jun-25 23-Jun-25 27-Jun-25 | I513: IPC - 16 | J513: P10 - 14th Lift | K513: P10
B514: 402.a | C514: Well Steining - Casting & Sinking (Including Well curb) | D514: Rmt | E514: Palashbari | F514: 2.5 | G514: MPSB/Str/1720 MPSB/Sur/1466 MPSB/Str/1721 | H514: 28-Jun-25 28-Jun-25 28-Jun-25 | I514: IPC - 16 | J514: P10 - 15th Lift | K514: P10
B515: 402.a | C515: Well Steining - Casting & Sinking (Including Well curb) | D515: Rmt | E515: Palashbari | F515: 2.5 | G515: MPSB/Str/1807 MPSB/Sur/1519 MPSB/Str/1808 MPSB/Sur/1550 | H515: 14-Jul-25 14-Jul-25 14-Jul-25 19-Jul-25 | I515: IPC - 18 | J515: P10 - 16th Lift | K515: P10
... B518: 402.a | C518: Well Steining - Casting & Sinking (Including Well curb) | D518: Rmt | E518: Sualkuchi | F518: 2.58 | G518: MPSB/Str/2979 MPSB/Sur/2301 MPSB/Str/2980 | H518: 29-Nov-25 29-Nov-25 29-Nov-25 | I518: IPC - 23 | J518: P10 - 19th Lift | K518: P10
B519: 401.b | C519: Ground preparation and placing of Cutting Edge | D519: Nos. | E519: Palashbari | F519: 1 | G519: MPSB/Sur/2561 | H519: 46021 | I519: IPC - 26 | J519: P11 | K519: P11
B520: 401.c | C520: Shuttering and Scaffolding | D520: Nos. | E520: Palashbari | F520: 1 | G520: MPSB/Sur/2637 | H520: 46031 | I520: IPC - 26 | J520: P11 | K520: P11
B521: 402.a | C521: Well Steining - Casting & Sinking (Including Well curb) | D521: Rmt | E521: Palashbari | F521: 6.2 | G521: MPSB/Str/3534 MPSB/Sur/2710 MPSB/Str/3567 MPSB/Sur/2782 MPSB/Sur/2793 | H521: 16-Jan-26 19-Jan-26 19-Jan-26 28-Jan-26 29-Jan-26 | I521: IPC - 26 | J521: P11 - Well Curb | K521: P11
B522: 402.a | C522: Well Steining - Casting & Sinking (Including Well curb) | D522: Rmt | E522: Palashbari | F522: 2.5 | G522: MPSB/Str/3715 MPSB/Sur/2818 MPSB/Str/3716 | H522: 31-Jan-26 31-Jan-26 31-Jan-26 | I522: IPC - 26 | J522: P11 - 1st Lift | K522: P11
B523: 402.a | C523: Well Steining - Casting & Sinking (Including Well curb) | D523: Rmt | E523: Palashbari | F523: 2.5 | G523: MPSB/Str/3809 MPSB/Sur/2894 MPSB/Str/3810 MPSB/Sur/2924 | H523: 9-Feb-26 9-Feb-26 9-Feb-26 13-Feb-26 | I523: IPC - 27 | J523: P11 - 2nd Lift | K523: P11
B524: 402.a | C524: Well Steining - Casting & Sinking (Including Well curb) | D524: Rmt | E524: Palashbari | F524: 2.5 | G524: MPSB/Str/3859 MPSB/Sur/2934 MPSB/Str/3860 MPSB/Sur/2957 | H524: 15-Feb-26 15-Feb-26 15-Feb-26 19-Feb-26 | I524: IPC - 27 | J524: P11 - 3rd Lift | K524: P11
B525: 402.a | C525: Well Steining - Casting & Sinking (Including Well curb) | D525: Rmt | E525: Palashbari | F525: 2.5 | G525: MPSB/Str/3919 MPSB/Sur/2973 MPSB/Str/3920 MPSB/Sur/3041 | H525: 21-Feb-26 21-Feb-26 21-Feb-26 28-Feb-26 | I525: IPC - 27 | J525: P11 - 4th Lift | K525: P11
B526: 402.a | C526: Well Steining - Casting & Sinking (Including Well curb) | D526: Rmt | E526: Palashbari | F526: 2.5 | G526: MPSB/Str/3960 MPSB/Sur/3009 MPSB/Str/3961 MPSB/Sur/3041 | H526: 26-Feb-26 26-Feb-26 26-Feb-26 28-Feb-26 | I526: IPC - 27 | J526: P11 - 5th Lift | K526: P11
B527: 402.a | C527: Well Steining - Casting & Sinking (Including Well curb) | D527: Rmt | E527: Palashbari | F527: 2.5 | G527: MPSB/Str/4077 MPSB/Sur/3084 MPSB/Str/4078 | H527: 10-Mar-26 10-Mar-26 10-Mar-26 | I527: IPC - 29 | J527: P11 - 6th Lift | K527: P11
B528: 402.a | C528: Well Steining - Casting & Sinking (Including Well curb) | D528: Rmt | E528: Palashbari | F528: 2.5 | G528: MPSB/Str/4120 MPSB/Sur/3123 MPSB/Str/4119 | H528: 15-Mar-26 15-Mar-26 15-Mar-26 | I528: IPC - 29 | J528: P11 - 7th Lift | K528: P11
B529: 402.a | C529: Well Steining - Casting & Sinking (Including Well curb) | D529: Rmt | E529: Palashbari | F529: 2.5 | G529: MPSB/Str/4215 MPSB/Sur/3180 MPSB/Str/4216 | H529: 27-Mar-26 27-Mar-26 27-Mar-26 | I529: IPC - 29 | J529: P11 - 8th Lift | K529: P11
B530: 402.a | C530: Well Steining - Casting & Sinking (Including Well curb) | D530: Rmt | E530: Palashbari | F530: 2.7 | G530: MPSB/Str/4345 MPSB/Sur/3255 MPSB/Str/4346 | H530: 7-Apr-26 7-Apr-26 7-Apr-26 | I530: IPC - 30 | J530: P11 - 9th Lift | K530: P11
B531: 402.a | C531: Well Steining - Casting & Sinking (Including Well curb) | D531: Rmt | E531: Palashbari | F531: 2.8 | G531: MPSB/Str/4367 MPSB/Sur/3255 MPSB/Str/4368 | H531: 11-Apr-26 7-Apr-26 11-Apr-26 | I531: IPC - 30 | J531: P11 - 10th Lift | K531: P11
B532: 402.a | C532: Well Steining - Casting & Sinking (Including Well curb) | D532: Rmt | E532: Palashbari | F532: 2.5 | G532: MPSB/Str/4473 MPSB/Sur/3344 MPSB/Str/4474 | H532: 24-Apr-26 24-Apr-26 24-Apr-26 | I532: IPC - 30 | J532: P11 - 11th Lift | K532: P11
... B536: 402.a | C536: Well Steining - Casting & Sinking (Including Well curb) | D536: Rmt | E536: Palashbari | F536: 2.5 | G536: MPSB/Str/5002 MPSB/Sur/3690 MPSB/Str/5003 | H536: 25-Jun-26 25-Jun-26 25-Jun-26 | I536: IPC - 33 | J536: P11 - 15th Lift | K536: P11
B537: 401.b | C537: Ground preparation and placing of Cutting Edge | D537: Nos. | E537: Palashbari | F537: 1 | G537: MPSB/Sur/477 | H537: 45704 | I537: IPC - 11 | J537: P12 | K537: P12
B538: 401.c | C538: Shuttering and Scaffolding | D538: Nos. | E538: Palashbari | F538: 1 | G538: MPSB/Sur/501 | H538: 45707 | I538: IPC - 11 | J538: P12 | K538: P12
B539: 402.a | C539: Well Steining - Casting & Sinking (Including Well curb) | D539: Rmt | E539: Palashbari | F539: 4.48 | G539: MPSB/Str/628 MPSB/Sur/581 MPSB/Str/661 | H539: 25-Feb-25 27-Feb-25 27-Feb-25 | I539: IPC - 11 | J539: P12 - Well Curb | K539: P12
B540: 402.a | C540: Well Steining - Casting & Sinking (Including Well curb) | D540: Rmt | E540: Palashbari | F540: =-F530 -> -2.7 | I540: IPC - 26 | J540: P12 - Well Curb | K540: P12
B541: 402.a | C541: Well Steining - Casting & Sinking (Including Well curb) | D541: Rmt | E541: Palashbari | F541: =2.5-0.025 -> 2.475 | G541: MPSB/Sur/682 MPSB/Str/771 MPSB/Str/772 MPSB/Sur/718 | H541: 10-Mar-25 10-Mar-25 10-Mar-25 15-Mar-25 | I541: IPC - 13 | J541: P12 - 1st Lift | K541: P12
B542: 402.a | C542: Well Steining - Casting & Sinking (Including Well curb) | D542: Rmt | E542: Palashbari | F542: =-F536 -> -2.5 | I542: IPC - 26 | J542: P12 - 1st Lift | K542: P12
B543: 402.a | C543: Well Steining - Casting & Sinking (Including Well curb) | D543: Rmt | E543: Palashbari | F543: 2.5 | G543: MPSB/Str/839 MPSB/Str/840 MPSB/Sur/746 MPSB/Sur/845 | H543: 20-Mar-25 20-Mar-25 20-Mar-25 28-Mar-25 | I543: IPC - 13 | J543: P12 - 2nd Lift | K543: P12
B544: 402.a | C544: Well Steining - Casting & Sinking (Including Well curb) | D544: Rmt | E544: Palashbari | F544: =-F537 -> -1 | I544: IPC - 26 | J544: P12 - 2nd Lift | K544: P12
B545: 402.a | C545: Well Steining - Casting & Sinking (Including Well curb) | D545: Rmt | E545: Palashbari | F545: 2.32 | G545: MPSB/Str/893 MPSB/Str/894 MPSB/Sur/784 MPSB/Sur/845 | H545: 25-Mar-25 25-Mar-25 25-Mar-25 29-Mar-25 | I545: IPC - 13 | J545: P12 - 3rd Lift | K545: P12
B546: 402.a | C546: Well Steining - Casting & Sinking (Including Well curb) | D546: Rmt | E546: Palashbari | F546: =-F537 -> -1 | I546: IPC - 26 | J546: P12 - 3rd Lift | K546: P12
B547: 402.a | C547: Well Steining - Casting & Sinking (Including Well curb) | D547: Rmt | E547: Palashbari | F547: 2.5 | G547: MPSB/Str/999 MPSB/Str/1000 MPSB/Sur/863 | H547: 31-Mar-25 31-Mar-25 31-Mar-25 | I547: IPC - 13 | J547: P12 - 4th Lift | K547: P12
B548: 402.a | C548: Well Steining - Casting & Sinking (Including Well curb) | D548: Rmt | E548: Palashbari | F548: =-F538 -> -1 | I548: IPC - 26 | J548: P12 - 4th Lift | K548: P12
B549: 402.a | C549: Well Steining - Casting & Sinking (Including Well curb) | D549: Rmt | E549: Palashbari | F549: 2.4 | G549: MPSB/Str/1109 MPSB/Sur/985 MPSB/Str/1110 MPSB/Sur/1022 | H549: 12-Apr-25 12-Apr-25 12-Apr-25 17-Apr-25 | I549: IPC - 14 | J549: P12 - 5th Lift | K549: P12
B550: 402.a | C550: Well Steining - Casting & Sinking (Including Well curb) | D550: Rmt | E550: Palashbari | F550: =-F544 -> 1 | I550: IPC - 26 | J550: P12 - 5th Lift | K550: P12
B551: 402.a | C551: Well Steining - Casting & Sinking (Including Well curb) | D551: Rmt | E551: Palashbari | F551: 2.6 | G551: MPSB/Str/1199 MPSB/Sur/1043 MPSB/Str/1200 MPSB/Sur/1079 | H551: 20-Apr-25 20-Apr-25 20-Apr-25 24-Apr-25 | I551: IPC - 14 | J551: P12 - 6th Lift | K551: P12
B552: 402.a | C552: Well Steining - Casting & Sinking (Including Well curb) | D552: Rmt | E552: Palashbari | F552: =-F543 -> -2.5 | I552: IPC - 26 | J552: P12 - 6th Lift | K552: P12
B553: 402.a | C553: Well Steining - Casting & Sinking (Including Well curb) | D553: Rmt | E553: Palashbari | F553: 2.5 | G553: MPSB/Str/1272 MPSB/Sur/1102 MPSB/Str/1273 | H553: 25-Apr-25 25-Apr-25 25-Apr-25 | I553: IPC - 14 | J553: P12 - 7th Lift | K553: P12
B554: 402.a | C554: Well Steining - Casting & Sinking (Including Well curb) | D554: Rmt | E554: Palashbari | F554: =-F543 -> -2.5 | I554: IPC - 26 | J554: P12 - 7th Lift | K554: P12
B555: 401.b | C555: Ground preparation and placing of Cutting Edge | D555: Nos. | E555: Palashbari | F555: 1 | G555: MPSB/Sur/2755 | H555: 46046 | I555: IPC - 33 | J555: P12(A) | K555: P12(A)
B556: 401.c | C556: Shuttering and Scaffolding | D556: Nos. | E556: Palashbari | F556: 1 | G556: MPSB/Sur/2783 | H556: 46050 | I556: IPC - 33 | J556: P12(A) | K556: P12(A)
B557: 402.a | C557: Well Steining - Casting & Sinking (Including Well curb) | D557: Rmt | E557: Palashbari | F557: 4.48 | G557: MPSB/Str/3668 MPSB/Sur/2802 MPSB/Str/3685 MPSB/Sur/2848 MPSB/Sur/2853 | H557: 29-Jan-26 30-Jan-26 30-Jan-26 3-Feb-26 4-Feb-26 | I557: IPC - 33 | J557: P12(A) - Well Curb | K557: P12(A)
B558: 402.a | C558: Well Steining - Casting & Sinking (Including Well curb) | D558: Rmt | E558: Palashbari | F558: 2.8 | G558: MPSB/Str/3784 MPSB/Sur/2881 MPSB/Str/3785 MPSB/Sur/2905 | H558: 7-Feb-26 7-Feb-26 7-Feb-26 11-Feb-26 | I558: IPC - 33 | J558: P12(A) - 1st Lift | K558: P12(A)
B559: 402.a | C559: Well Steining - Casting & Sinking (Including Well curb) | D559: Rmt | E559: Palashbari | F559: 2.8 | G559: MPSB/Str/3827 MPSB/Sur/2906 MPSB/Str/3828 MPSB/Sur/2928 | H559: 11-Feb-26 11-Feb-26 11-Feb-26 14-Feb-26 | I559: IPC - 33 | J559: P12(A) - 2nd Lift | K559: P12(A)
B560: 402.a | C560: Well Steining - Casting & Sinking (Including Well curb) | D560: Rmt | E560: Palashbari | F560: 2.8 | G560: MPSB/Str/3864 MPSB/Sur/2939 MPSB/Str/3865 MPSB/Sur/2962 | H560: 16-Feb-26 16-Feb-26 16-Feb-26 20-Feb-26 | I560: IPC - 33 | J560: P12(A) - 3rd Lift | K560: P12(A)
B561: 402.a | C561: Well Steining - Casting & Sinking (Including Well curb) | D561: Rmt | E561: Palashbari | F561: 2.8 | G561: MPSB/Str/3929 MPSB/Sur/2976 MPSB/Str/3930 MPSB/Sur/3083 | H561: 23-Feb-26 23-Feb-26 23-Feb-26 10-Mar-26 | I561: IPC - 33 | J561: P12(A) - 4th Lift | K561: P12(A)
B562: 402.a | C562: Well Steining - Casting & Sinking (Including Well curb) | D562: Rmt | E562: Palashbari | F562: 2.8 | G562: MPSB/Str/3962 MPSB/Sur/3010 MPSB/Str/3963 MPSB/Sur/3083 | H562: 26-Feb-26 26-Feb-26 26-Feb-26 10-Mar-26 | I562: IPC - 33 | J562: P12(A) - 5th Lift | K562: P12(A)
B563: 402.a | C563: Well Steining - Casting & Sinking (Including Well curb) | D563: Rmt | E563: Palashbari | F563: 2.8 | G563: MPSB/Str/4086 MPSB/Sur/3091 MPSB/Str/4087 MPSB/Sur/3118 | H563: 11-Mar-26 11-Mar-26 11-Mar-26 14-Mar-26 | I563: IPC - 33 | J563: P12(A) - 6th Lift | K563: P12(A)
B564: 402.a | C564: Well Steining - Casting & Sinking (Including Well curb) | D564: Rmt | E564: Palashbari | F564: 2.8 | G564: MPSB/Str/4153 MPSB/Sur/3145 MPSB/Str/4154 MPSB/Sur/3237 | H564: 19-Mar-26 19-Mar-26 19-Mar-26 3-Apr-26 | I564: IPC - 33 | J564: P12(A) - 7th Lift | K564: P12(A)
B565: 402.a | C565: Well Steining - Casting & Sinking (Including Well curb) | D565: Rmt | E565: Palashbari | F565: 3.45 | G565: MPSB/Str/4257 MPSB/Sur/3202 MPSB/Str/4258 MPSB/Sur/3237 | H565: 30-Mar-26 30-Mar-26 30-Mar-26 3-Apr-26 | I565: IPC - 33 | J565: P12(A) - 8th Lift | K565: P12(A)
B566: 402.a | C566: Well Steining - Casting & Sinking (Including Well curb) | D566: Rmt | E566: Palashbari | F566: 2.8 | G566: MPSB/Str/4362 MPSB/Sur/3269 MPSB/Str/4363 MPSB/Sur/3321 | H566: 10-Apr-26 10-Apr-26 10-Apr-26 17-Apr-26 | I566: IPC - 33 | J566: P12(A) - 9th Lift | K566: P12(A)
B567: 402.a | C567: Well Steining - Casting & Sinking (Including Well curb) | D567: Rmt | E567: Palashbari | F567: 2.8 | G567: MPSB/Str/4396 MPSB/Sur/3296 MPSB/Str/4397 MPSB/Sur/3321 | H567: 14-Apr-26 14-Apr-26 14-Apr-26 17-Apr-26 | I567: IPC - 33 | J567: P12(A) - 10th Lift | K567: P12(A)
B568: 402.a | C568: Well Steining - Casting & Sinking (Including Well curb) | D568: Rmt | E568: Palashbari | F568: 2.8 | G568: MPSB/Str/4525 MPSB/Sur/3381 MPSB/Str/4526 MPSB/Sur/3435 | H568: 29-Apr-26 29-Apr-26 29-Apr-26 8-May-26 | I568: IPC - 33 | J568: P12(A) - 11th Lift | K568: P12(A)
... B572: 402.a | C572: Well Steining - Casting & Sinking (Including Well curb) | D572: Rmt | E572: Palashbari | F572: 2.8 | G572: MPSB/Str/4978 MPSB/Sur/3676 MPSB/Str/4979 | H572: 22-Jun-26 22-Jun-26 22-Jun-26 | I572: IPC - 33 | J572: P12(A) - 15th Lift | K572: P12(A)
B573: 401.b | C573: Ground preparation and placing of Cutting Edge | D573: Nos. | E573: Palashbari | F573: 1 | G573: MPSB/Sur/2645 | H573: 46032 | I573: IPC - 26 | J573: P13 | K573: P13
B574: 401.c | C574: Shuttering and Scaffolding | D574: Nos. | E574: Palashbari | F574: 1 | G574: MPSB/Sur/2686 | H574: 46038 | I574: IPC - 26 | J574: P13 | K574: P13
B575: 402.a | C575: Well Steining - Casting & Sinking (Including Well curb) | D575: Rmt | E575: Palashbari | F575: 6.2 | G575: MPSB/Str/3607 MPSB/Sur/2756 MPSB/Str/3637 MPSB/Sur/2819 | H575: 22-Jan-26 24-Jan-26 24-Jan-26 31-Jan-26 | I575: IPC - 26 | J575: P13 - Well Curb | K575: P13
B576: 402.a | C576: Well Steining - Casting & Sinking (Including Well curb) | D576: Rmt | E576: Palashbari | F576: 2.5 | G576: MPSB/Str/3771 MPSB/Sur/2866 MPSB/Str/3772 MPSB/Sur/2908 | H576: 6-Feb-26 6-Feb-26 6-Feb-26 11-Feb-26 | I576: IPC - 27 | J576: P13 - 1st Lift | K576: P13
B577: 402.a | C577: Well Steining - Casting & Sinking (Including Well curb) | D577: Rmt | E577: Palashbari | F577: 2.5 | G577: MPSB/Str/3848 MPSB/Sur/2922 MPSB/Str/3849 MPSB/Sur/2948 | H577: 13-Feb-26 13-Feb-26 13-Feb-26 17-Feb-26 | I577: IPC - 27 | J577: P13 - 2nd Lift | K577: P13
B578: 402.a | C578: Well Steining - Casting & Sinking (Including Well curb) | D578: Rmt | E578: Palashbari | F578: 2.5 | G578: MPSB/Str/3894 MPSB/Sur/2955 MPSB/Str/3895 MPSB/Sur/2978 | H578: 19-Feb-26 19-Feb-26 19-Feb-26 23-Feb-26 | I578: IPC - 27 | J578: P13 - 3rd Lift | K578: P13
B579: 402.a | C579: Well Steining - Casting & Sinking (Including Well curb) | D579: Rmt | E579: Palashbari | F579: 2.5 | G579: MPSB/Str/3979 MPSB/Sur/3019 MPSB/Str/3980 | H579: 27-Feb-26 27-Feb-26 27-Feb-26 | I579: IPC - 27 | J579: P13 - 4th Lift | K579: P13
B580: 402.a | C580: Well Steining - Casting & Sinking (Including Well curb) | D580: Rmt | E580: Palashbari | F580: 2.5 | G580: MPSB/Str/4056 MPSB/Sur/3069 MPSB/Str/4057 | H580: 7-Mar-26 7-Mar-26 7-Mar-26 | I580: IPC - 29 | J580: P13 - 5th Lift | K580: P13
B581: 402.a | C581: Well Steining - Casting & Sinking (Including Well curb) | D581: Rmt | E581: Palashbari | F581: 2.5 | G581: MPSB/Str/4143 MPSB/Sur/3142 MPSB/Str/4144 | H581: 18-Mar-26 18-Mar-26 18-Mar-26 | I581: IPC - 29 | J581: P13 - 6th Lift | K581: P13
B582: 402.a | C582: Well Steining - Casting & Sinking (Including Well curb) | D582: Rmt | E582: Palashbari | F582: 2.5 | G582: MPSB/Str/4191 MPSB/Sur/3164 MPSB/Str/4192 | H582: 24-Mar-26 24-Mar-26 24-Mar-26 | I582: IPC - 29 | J582: P13 - 7th Lift | K582: P13
B583: 402.a | C583: Well Steining - Casting & Sinking (Including Well curb) | D583: Rmt | E583: Palashbari | F583: 2.5 | G583: MPSB/Str/4272 MPSB/Sur/3209 MPSB/Str/4273 | H583: 31-Mar-26 31-Mar-26 31-Mar-26 | I583: IPC - 29 | J583: P13 - 8th Lift | K583: P13
B584: 402.a | C584: Well Steining - Casting & Sinking (Including Well curb) | D584: Rmt | E584: Palashbari | F584: 2.5 | G584: MPSB/Str/4359 MPSB/Sur/3264 MPSB/Str/4360 | H584: 10-Apr-26 10-Apr-26 10-Apr-26 | I584: IPC - 30 | J584: P13 - 9th Lift | K584: P13
B585: 402.a | C585: Well Steining - Casting & Sinking (Including Well curb) | D585: Rmt | E585: Palashbari | F585: 2.5 | G585: MPSB/Str/4416 MPSB/Sur/3307 MPSB/Str/4417 | H585: 16-Apr-26 16-Apr-26 16-Apr-26 | I585: IPC - 30 | J585: P13 - 10th Lift | K585: P13
B586: 402.a | C586: Well Steining - Casting & Sinking (Including Well curb) | D586: Rmt | E586: Palashbari | F586: 2.7 | G586: MPSB/Str/4527 MPSB/Sur/3382 MPSB/Str/4528 | H586: 29-Apr-26 29-Apr-26 29-Apr-26 | I586: IPC - 30 | J586: P13 - 11th Lift | K586: P13
... B589: 402.a | C589: Well Steining - Casting & Sinking (Including Well curb) | D589: Rmt | E589: Palashbari | F589: 2.5 | G589: MPSB/Str/4943 MPSB/Sur/3664 MPSB/Str/4944 | H589: 18-Jun-26 18-Jun-26 18-Jun-26 | I589: IPC - 33 | J589: P13 - 14th Lift | K589: P13
B590: 401.b | C590: Ground preparation and placing of Cutting Edge | D590: Nos. | E590: Palashbari | F590: 1 | G590: MPSB/Sur/441 | H590: 45696 | I590: IPC - 11 | J590: P14 | K590: P14
B591: 401.c | C591: Shuttering and Scaffolding | D591: Nos. | E591: Palashbari | F591: 1 | G591: MPSB/Sur/460 | H591: 45700 | I591: IPC - 11 | J591: P14 | K591: P14
B592: 402.a | C592: Well Steining - Casting & Sinking (Including Well curb) | D592: Rmt | E592: Palashbari | F592: 4.32 | G592: MPSB/Str/566 MPSB/Sur/500 MPSB/Str/592 MPSB/Sur/551 MPSB/Sur/552 | H592: 18-Feb-25 19-Feb-25 21-Feb-25 25-Feb-25 25-Feb-25 | I592: IPC - 11 | J592: P14 - Well Curb | K592: P14
...

Sheet Well Cal.
B1: Construction of 4-lane Extra-dosed PSC Bridge over river Brahmaputra connecting Palashbari and Sualkuchi including Viaduct, Approaches and River Training works etc on EPC mode
B2: Well Reconciliation Statement
B3: Well ID | C3: Well Depth | D3: Length Executed | E3: Lift | F3: IPC - 08 | G3: IPC - 09 | H3: IPC - 10 | I3: IPC - 11 | J3: IPC - 13 | K3: IPC - 14 | L3: IPC - 15 | M3: IPC - 16 | N3: IPC - 18 | O3: IPC - 19 | P3: IPC - 20 | Q3: IPC - 22 | R3: IPC - 23 | S3: IPC - 25 | T3: IPC - 26 | U3: IPC - 27 | V3: IPC - 29 | W3: IPC - 30 | X3: IPC - 31 | Y3: IPC - 33 | Z3: IPC - 34 | AB3: Total | AC3: Check | AE3: Component | AF3: Height | AK3: No. of Locations | AL3: Total Length | AM3: Locations
AF4: Well Curb | AG4: Below Transition | AH4: Transition | AI4: Above Transition | AJ4: Total
B5: P4 | C5: 50.55 | D5: =SUMIFS('Schedule 5'!$F$506:$F$544,'Schedule 5'!K506:K544,'Well Cal.'!$B$5) -> 48.7 | E5: P4 - Well Curb | F5: =SUMIFS('Schedule 5'!$F$506:$F$544,'Schedule 5'!$I$506:$I$544,'Well Cal.'!F$3,'Schedule 5'!$J$506:$J$544,'Well Cal.'!$E5) -> 0 | G5: =SUMIFS('Schedule 5'!$F$506:$F$544,'Schedule 5'!$I$506:$I$544,'Well Cal.'!G$3,'Schedule 5'!$J$506:$J$544,'Well Cal.'!$E5) -> 0 | H5: =SUMIFS('Schedule 5'!$F$506:$F$544,'Schedule 5'!$I$506:$I$544,'Well Cal.'!H$3,'Schedule 5'!$J$506:$J$544,'Well Cal.'!$E5) -> 0 | I5: =SUMIFS('Schedule 5'!$F$506:$F$544,'Schedule 5'!$I$506:$I$544,'Well Cal.'!I$3,'Schedule 5'!$J$506:$J$544,'Well Cal.'!$E5) -> 0 | J5: =SUMIFS('Schedule 5'!$F$506:$F$544,'Schedule 5'!$I$506:$I$544,'Well Cal.'!J$3,'Schedule 5'!$J$506:$J$544,'Well Cal.'!$E5) -> 0 | K5: =SUMIFS('Schedule 5'!$F$506:$F$544,'Schedule 5'!$I$506:$I$544,'Well Cal.'!K$3,'Schedule 5'!$J$506:$J$544,'Well Cal.'!$E5) -> 0 | L5: =SUMIFS('Schedule 5'!$F$506:$F$544,'Schedule 5'!$I$506:$I$544,'Well Cal.'!L$3,'Schedule 5'!$J$506:$J$544,'Well Cal.'!$E5) -> 0 | M5: =SUMIFS('Schedule 5'!$F$506:$F$544,'Schedule 5'!$I$506:$I$544,'Well Cal.'!M$3,'Schedule 5'!$J$506:$J$544,'Well Cal.'!$E5) -> 0 | ... Z5: =SUMIFS('Schedule 5'!$F$506:$F$544,'Schedule 5'!$I$506:$I$544,'Well Cal.'!Z$3,'Schedule 5'!$J$506:$J$544,'Well Cal.'!$E5) -> 0 | AB5: =SUM(F5:AA24) -> 48.7 | AC5: =D5-AB5 -> 0
E6: P4 - 1st Lift | F6: =SUMIFS('Schedule 5'!$F$506:$F$544,'Schedule 5'!$I$506:$I$544,'Well Cal.'!F$3,'Schedule 5'!$J$506:$J$544,'Well Cal.'!$E6) -> 0 | G6: =SUMIFS('Schedule 5'!$F$506:$F$544,'Schedule 5'!$I$506:$I$544,'Well Cal.'!G$3,'Schedule 5'!$J$506:$J$544,'Well Cal.'!$E6) -> 0 | H6: =SUMIFS('Schedule 5'!$F$506:$F$544,'Schedule 5'!$I$506:$I$544,'Well Cal.'!H$3,'Schedule 5'!$J$506:$J$544,'Well Cal.'!$E6) -> 0 | I6: =SUMIFS('Schedule 5'!$F$506:$F$544,'Schedule 5'!$I$506:$I$544,'Well Cal.'!I$3,'Schedule 5'!$J$506:$J$544,'Well Cal.'!$E6) -> 0 | J6: =SUMIFS('Schedule 5'!$F$506:$F$544,'Schedule 5'!$I$506:$I$544,'Well Cal.'!J$3,'Schedule 5'!$J$506:$J$544,'Well Cal.'!$E6) -> 0 | K6: =SUMIFS('Schedule 5'!$F$506:$F$544,'Schedule 5'!$I$506:$I$544,'Well Cal.'!K$3,'Schedule 5'!$J$506:$J$544,'Well Cal.'!$E6) -> 0 | L6: =SUMIFS('Schedule 5'!$F$506:$F$544,'Schedule 5'!$I$506:$I$544,'Well Cal.'!L$3,'Schedule 5'!$J$506:$J$544,'Well Cal.'!$E6) -> 0 | M6: =SUMIFS('Schedule 5'!$F$506:$F$544,'Schedule 5'!$I$506:$I$544,'Well Cal.'!M$3,'Schedule 5'!$J$506:$J$544,'Well Cal.'!$E6) -> 0 | ... Z6: =SUMIFS('Schedule 5'!$F$506:$F$544,'Schedule 5'!$I$506:$I$544,'Well Cal.'!Z$3,'Schedule 5'!$J$506:$J$544,'Well Cal.'!$E6) -> 0 | AE6: Middle Pylon | AF6: 4.32 | AG6: 30.53 | AH6: 2.7 | AI6: 16.5 | AJ6: =SUM(AF6:AI6) -> 54.05 | AK6: 6 | AL6: =AJ6*AK6 -> 324.3 | AM6: P8 / P12 / P16 / P20 / P24 / P28
E7: P4 - 2nd Lift | F7: =SUMIFS('Schedule 5'!$F$506:$F$544,'Schedule 5'!$I$506:$I$544,'Well Cal.'!F$3,'Schedule 5'!$J$506:$J$544,'Well Cal.'!$E7) -> 0 | G7: =SUMIFS('Schedule 5'!$F$506:$F$544,'Schedule 5'!$I$506:$I$544,'Well Cal.'!G$3,'Schedule 5'!$J$506:$J$544,'Well Cal.'!$E7) -> 0 | H7: =SUMIFS('Schedule 5'!$F$506:$F$544,'Schedule 5'!$I$506:$I$544,'Well Cal.'!H$3,'Schedule 5'!$J$506:$J$544,'Well Cal.'!$E7) -> 0 | I7: =SUMIFS('Schedule 5'!$F$506:$F$544,'Schedule 5'!$I$506:$I$544,'Well Cal.'!I$3,'Schedule 5'!$J$506:$J$544,'Well Cal.'!$E7) -> 0 | J7: =SUMIFS('Schedule 5'!$F$506:$F$544,'Schedule 5'!$I$506:$I$544,'Well Cal.'!J$3,'Schedule 5'!$J$506:$J$544,'Well Cal.'!$E7) -> 0 | K7: =SUMIFS('Schedule 5'!$F$506:$F$544,'Schedule 5'!$I$506:$I$544,'Well Cal.'!K$3,'Schedule 5'!$J$506:$J$544,'Well Cal.'!$E7) -> 0 | L7: =SUMIFS('Schedule 5'!$F$506:$F$544,'Schedule 5'!$I$506:$I$544,'Well Cal.'!L$3,'Schedule 5'!$J$506:$J$544,'Well Cal.'!$E7) -> 0 | M7: =SUMIFS('Schedule 5'!$F$506:$F$544,'Schedule 5'!$I$506:$I$544,'Well Cal.'!M$3,'Schedule 5'!$J$506:$J$544,'Well Cal.'!$E7) -> 0 | ... Z7: =SUMIFS('Schedule 5'!$F$506:$F$544,'Schedule 5'!$I$506:$I$544,'Well Cal.'!Z$3,'Schedule 5'!$J$506:$J$544,'Well Cal.'!$E7) -> 0 | AE7: EJ Pier | AF7: 4.32 | AG7: 17.98 | AH7: 2.7 | AI7: 25.55 | AJ7: =SUM(AF7:AI7) -> 50.55 | AK7: 7 | AL7: =AJ7*AK7 -> 353.85 | AM7: P6 / P10 / P14 / P18 / P22 / P26 / P30
E8: P4 - 3rd Lift | F8: =SUMIFS('Schedule 5'!$F$506:$F$544,'Schedule 5'!$I$506:$I$544,'Well Cal.'!F$3,'Schedule 5'!$J$506:$J$544,'Well Cal.'!$E8) -> 0 | G8: =SUMIFS('Schedule 5'!$F$506:$F$544,'Schedule 5'!$I$506:$I$544,'Well Cal.'!G$3,'Schedule 5'!$J$506:$J$544,'Well Cal.'!$E8) -> 0 | H8: =SUMIFS('Schedule 5'!$F$506:$F$544,'Schedule 5'!$I$506:$I$544,'Well Cal.'!H$3,'Schedule 5'!$J$506:$J$544,'Well Cal.'!$E8) -> 0 | I8: =SUMIFS('Schedule 5'!$F$506:$F$544,'Schedule 5'!$I$506:$I$544,'Well Cal.'!I$3,'Schedule 5'!$J$506:$J$544,'Well Cal.'!$E8) -> 0 | J8: =SUMIFS('Schedule 5'!$F$506:$F$544,'Schedule 5'!$I$506:$I$544,'Well Cal.'!J$3,'Schedule 5'!$J$506:$J$544,'Well Cal.'!$E8) -> 0 | K8: =SUMIFS('Schedule 5'!$F$506:$F$544,'Schedule 5'!$I$506:$I$544,'Well Cal.'!K$3,'Schedule 5'!$J$506:$J$544,'Well Cal.'!$E8) -> 0 | L8: =SUMIFS('Schedule 5'!$F$506:$F$544,'Schedule 5'!$I$506:$I$544,'Well Cal.'!L$3,'Schedule 5'!$J$506:$J$544,'Well Cal.'!$E8) -> 0 | M8: =SUMIFS('Schedule 5'!$F$506:$F$544,'Schedule 5'!$I$506:$I$544,'Well Cal.'!M$3,'Schedule 5'!$J$506:$J$544,'Well Cal.'!$E8) -> 0 | ... Z8: =SUMIFS('Schedule 5'!$F$506:$F$544,'Schedule 5'!$I$506:$I$544,'Well Cal.'!Z$3,'Schedule 5'!$J$506:$J$544,'Well Cal.'!$E8) -> 0 | AE8: Outer Pylon | AF8: 6.04 | AG8: 19.76 | AH8: 4.8 | AI8: 23.45 | AJ8: =SUM(AF8:AI8) -> 54.05 | AK8: 12 | AL8: =AJ8*AK8 -> 648.6 | AM8: P7 / P9 / P11 / P13 / P15 / P17 / P19 / P21 / P23 / P25 / P27 / P29
E9: P4 - 4th Lift | F9: =SUMIFS('Schedule 5'!$F$506:$F$544,'Schedule 5'!$I$506:$I$544,'Well Cal.'!F$3,'Schedule 5'!$J$506:$J$544,'Well Cal.'!$E9) -> 0 | G9: =SUMIFS('Schedule 5'!$F$506:$F$544,'Schedule 5'!$I$506:$I$544,'Well Cal.'!G$3,'Schedule 5'!$J$506:$J$544,'Well Cal.'!$E9) -> 0 | H9: =SUMIFS('Schedule 5'!$F$506:$F$544,'Schedule 5'!$I$506:$I$544,'Well Cal.'!H$3,'Schedule 5'!$J$506:$J$544,'Well Cal.'!$E9) -> 0 | I9: =SUMIFS('Schedule 5'!$F$506:$F$544,'Schedule 5'!$I$506:$I$544,'Well Cal.'!I$3,'Schedule 5'!$J$506:$J$544,'Well Cal.'!$E9) -> 0 | J9: =SUMIFS('Schedule 5'!$F$506:$F$544,'Schedule 5'!$I$506:$I$544,'Well Cal.'!J$3,'Schedule 5'!$J$506:$J$544,'Well Cal.'!$E9) -> 0 | K9: =SUMIFS('Schedule 5'!$F$506:$F$544,'Schedule 5'!$I$506:$I$544,'Well Cal.'!K$3,'Schedule 5'!$J$506:$J$544,'Well Cal.'!$E9) -> 0 | L9: =SUMIFS('Schedule 5'!$F$506:$F$544,'Schedule 5'!$I$506:$I$544,'Well Cal.'!L$3,'Schedule 5'!$J$506:$J$544,'Well Cal.'!$E9) -> 0 | M9: =SUMIFS('Schedule 5'!$F$506:$F$544,'Schedule 5'!$I$506:$I$544,'Well Cal.'!M$3,'Schedule 5'!$J$506:$J$544,'Well Cal.'!$E9) -> 0 | ... Z9: =SUMIFS('Schedule 5'!$F$506:$F$544,'Schedule 5'!$I$506:$I$544,'Well Cal.'!Z$3,'Schedule 5'!$J$506:$J$544,'Well Cal.'!$E9) -> 0
E10: P4 - 5th Lift | F10: =SUMIFS('Schedule 5'!$F$506:$F$544,'Schedule 5'!$I$506:$I$544,'Well Cal.'!F$3,'Schedule 5'!$J$506:$J$544,'Well Cal.'!$E10) -> 0 | G10: =SUMIFS('Schedule 5'!$F$506:$F$544,'Schedule 5'!$I$506:$I$544,'Well Cal.'!G$3,'Schedule 5'!$J$506:$J$544,'Well Cal.'!$E10) -> 0 | H10: =SUMIFS('Schedule 5'!$F$506:$F$544,'Schedule 5'!$I$506:$I$544,'Well Cal.'!H$3,'Schedule 5'!$J$506:$J$544,'Well Cal.'!$E10) -> 0 | I10: =SUMIFS('Schedule 5'!$F$506:$F$544,'Schedule 5'!$I$506:$I$544,'Well Cal.'!I$3,'Schedule 5'!$J$506:$J$544,'Well Cal.'!$E10) -> 0 | J10: =SUMIFS('Schedule 5'!$F$506:$F$544,'Schedule 5'!$I$506:$I$544,'Well Cal.'!J$3,'Schedule 5'!$J$506:$J$544,'Well Cal.'!$E10) -> 0 | K10: =SUMIFS('Schedule 5'!$F$506:$F$544,'Schedule 5'!$I$506:$I$544,'Well Cal.'!K$3,'Schedule 5'!$J$506:$J$544,'Well Cal.'!$E10) -> 0 | L10: =SUMIFS('Schedule 5'!$F$506:$F$544,'Schedule 5'!$I$506:$I$544,'Well Cal.'!L$3,'Schedule 5'!$J$506:$J$544,'Well Cal.'!$E10) -> 0 | M10: =SUMIFS('Schedule 5'!$F$506:$F$544,'Schedule 5'!$I$506:$I$544,'Well Cal.'!M$3,'Schedule 5'!$J$506:$J$544,'Well Cal.'!$E10) -> 0 | ... Z10: =SUMIFS('Schedule 5'!$F$506:$F$544,'Schedule 5'!$I$506:$I$544,'Well Cal.'!Z$3,'Schedule 5'!$J$506:$J$544,'Well Cal.'!$E10) -> 0
E11: P4 - 6th Lift | F11: =SUMIFS('Schedule 5'!$F$506:$F$544,'Schedule 5'!$I$506:$I$544,'Well Cal.'!F$3,'Schedule 5'!$J$506:$J$544,'Well Cal.'!$E11) -> 0 | G11: =SUMIFS('Schedule 5'!$F$506:$F$544,'Schedule 5'!$I$506:$I$544,'Well Cal.'!G$3,'Schedule 5'!$J$506:$J$544,'Well Cal.'!$E11) -> 0 | H11: =SUMIFS('Schedule 5'!$F$506:$F$544,'Schedule 5'!$I$506:$I$544,'Well Cal.'!H$3,'Schedule 5'!$J$506:$J$544,'Well Cal.'!$E11) -> 0 | I11: =SUMIFS('Schedule 5'!$F$506:$F$544,'Schedule 5'!$I$506:$I$544,'Well Cal.'!I$3,'Schedule 5'!$J$506:$J$544,'Well Cal.'!$E11) -> 0 | J11: =SUMIFS('Schedule 5'!$F$506:$F$544,'Schedule 5'!$I$506:$I$544,'Well Cal.'!J$3,'Schedule 5'!$J$506:$J$544,'Well Cal.'!$E11) -> 0 | K11: =SUMIFS('Schedule 5'!$F$506:$F$544,'Schedule 5'!$I$506:$I$544,'Well Cal.'!K$3,'Schedule 5'!$J$506:$J$544,'Well Cal.'!$E11) -> 0 | L11: =SUMIFS('Schedule 5'!$F$506:$F$544,'Schedule 5'!$I$506:$I$544,'Well Cal.'!L$3,'Schedule 5'!$J$506:$J$544,'Well Cal.'!$E11) -> 0 | M11: =SUMIFS('Schedule 5'!$F$506:$F$544,'Schedule 5'!$I$506:$I$544,'Well Cal.'!M$3,'Schedule 5'!$J$506:$J$544,'Well Cal.'!$E11) -> 0 | ... Z11: =SUMIFS('Schedule 5'!$F$506:$F$544,'Schedule 5'!$I$506:$I$544,'Well Cal.'!Z$3,'Schedule 5'!$J$506:$J$544,'Well Cal.'!$E11) -> 0 | AE11: Package 1 | AF11: P10 to P18
E12: P4 - 7th Lift | F12: =SUMIFS('Schedule 5'!$F$506:$F$544,'Schedule 5'!$I$506:$I$544,'Well Cal.'!F$3,'Schedule 5'!$J$506:$J$544,'Well Cal.'!$E12) -> 0 | G12: =SUMIFS('Schedule 5'!$F$506:$F$544,'Schedule 5'!$I$506:$I$544,'Well Cal.'!G$3,'Schedule 5'!$J$506:$J$544,'Well Cal.'!$E12) -> 0 | H12: =SUMIFS('Schedule 5'!$F$506:$F$544,'Schedule 5'!$I$506:$I$544,'Well Cal.'!H$3,'Schedule 5'!$J$506:$J$544,'Well Cal.'!$E12) -> 0 | I12: =SUMIFS('Schedule 5'!$F$506:$F$544,'Schedule 5'!$I$506:$I$544,'Well Cal.'!I$3,'Schedule 5'!$J$506:$J$544,'Well Cal.'!$E12) -> 0 | J12: =SUMIFS('Schedule 5'!$F$506:$F$544,'Schedule 5'!$I$506:$I$544,'Well Cal.'!J$3,'Schedule 5'!$J$506:$J$544,'Well Cal.'!$E12) -> 0 | K12: =SUMIFS('Schedule 5'!$F$506:$F$544,'Schedule 5'!$I$506:$I$544,'Well Cal.'!K$3,'Schedule 5'!$J$506:$J$544,'Well Cal.'!$E12) -> 0 | L12: =SUMIFS('Schedule 5'!$F$506:$F$544,'Schedule 5'!$I$506:$I$544,'Well Cal.'!L$3,'Schedule 5'!$J$506:$J$544,'Well Cal.'!$E12) -> 0 | M12: =SUMIFS('Schedule 5'!$F$506:$F$544,'Schedule 5'!$I$506:$I$544,'Well Cal.'!M$3,'Schedule 5'!$J$506:$J$544,'Well Cal.'!$E12) -> 0 | ... Z12: =SUMIFS('Schedule 5'!$F$506:$F$544,'Schedule 5'!$I$506:$I$544,'Well Cal.'!Z$3,'Schedule 5'!$J$506:$J$544,'Well Cal.'!$E12) -> 0 | AE12: Package 2 | AF12: P19 to P26
E13: P4 - 8th Lift | F13: =SUMIFS('Schedule 5'!$F$506:$F$544,'Schedule 5'!$I$506:$I$544,'Well Cal.'!F$3,'Schedule 5'!$J$506:$J$544,'Well Cal.'!$E13) -> 0 | G13: =SUMIFS('Schedule 5'!$F$506:$F$544,'Schedule 5'!$I$506:$I$544,'Well Cal.'!G$3,'Schedule 5'!$J$506:$J$544,'Well Cal.'!$E13) -> 0 | H13: =SUMIFS('Schedule 5'!$F$506:$F$544,'Schedule 5'!$I$506:$I$544,'Well Cal.'!H$3,'Schedule 5'!$J$506:$J$544,'Well Cal.'!$E13) -> 0 | I13: =SUMIFS('Schedule 5'!$F$506:$F$544,'Schedule 5'!$I$506:$I$544,'Well Cal.'!I$3,'Schedule 5'!$J$506:$J$544,'Well Cal.'!$E13) -> 0 | J13: =SUMIFS('Schedule 5'!$F$506:$F$544,'Schedule 5'!$I$506:$I$544,'Well Cal.'!J$3,'Schedule 5'!$J$506:$J$544,'Well Cal.'!$E13) -> 0 | K13: =SUMIFS('Schedule 5'!$F$506:$F$544,'Schedule 5'!$I$506:$I$544,'Well Cal.'!K$3,'Schedule 5'!$J$506:$J$544,'Well Cal.'!$E13) -> 0 | L13: =SUMIFS('Schedule 5'!$F$506:$F$544,'Schedule 5'!$I$506:$I$544,'Well Cal.'!L$3,'Schedule 5'!$J$506:$J$544,'Well Cal.'!$E13) -> 0 | M13: =SUMIFS('Schedule 5'!$F$506:$F$544,'Schedule 5'!$I$506:$I$544,'Well Cal.'!M$3,'Schedule 5'!$J$506:$J$544,'Well Cal.'!$E13) -> 0 | ... Z13: =SUMIFS('Schedule 5'!$F$506:$F$544,'Schedule 5'!$I$506:$I$544,'Well Cal.'!Z$3,'Schedule 5'!$J$506:$J$544,'Well Cal.'!$E13) -> 0 | AE13: Package 3 | AF13: P6 to P9
E14: P4 - 9th Lift | F14: =SUMIFS('Schedule 5'!$F$506:$F$544,'Schedule 5'!$I$506:$I$544,'Well Cal.'!F$3,'Schedule 5'!$J$506:$J$544,'Well Cal.'!$E14) -> 0 | G14: =SUMIFS('Schedule 5'!$F$506:$F$544,'Schedule 5'!$I$506:$I$544,'Well Cal.'!G$3,'Schedule 5'!$J$506:$J$544,'Well Cal.'!$E14) -> 0 | H14: =SUMIFS('Schedule 5'!$F$506:$F$544,'Schedule 5'!$I$506:$I$544,'Well Cal.'!H$3,'Schedule 5'!$J$506:$J$544,'Well Cal.'!$E14) -> 0 | I14: =SUMIFS('Schedule 5'!$F$506:$F$544,'Schedule 5'!$I$506:$I$544,'Well Cal.'!I$3,'Schedule 5'!$J$506:$J$544,'Well Cal.'!$E14) -> 0 | J14: =SUMIFS('Schedule 5'!$F$506:$F$544,'Schedule 5'!$I$506:$I$544,'Well Cal.'!J$3,'Schedule 5'!$J$506:$J$544,'Well Cal.'!$E14) -> 0 | K14: =SUMIFS('Schedule 5'!$F$506:$F$544,'Schedule 5'!$I$506:$I$544,'Well Cal.'!K$3,'Schedule 5'!$J$506:$J$544,'Well Cal.'!$E14) -> 0 | L14: =SUMIFS('Schedule 5'!$F$506:$F$544,'Schedule 5'!$I$506:$I$544,'Well Cal.'!L$3,'Schedule 5'!$J$506:$J$544,'Well Cal.'!$E14) -> 0 | M14: =SUMIFS('Schedule 5'!$F$506:$F$544,'Schedule 5'!$I$506:$I$544,'Well Cal.'!M$3,'Schedule 5'!$J$506:$J$544,'Well Cal.'!$E14) -> 0 | ... Z14: =SUMIFS('Schedule 5'!$F$506:$F$544,'Schedule 5'!$I$506:$I$544,'Well Cal.'!Z$3,'Schedule 5'!$J$506:$J$544,'Well Cal.'!$E14) -> 0 | AE14: Package 4 | AF14: P27 to P30
E15: P4 - 10th Lift | F15: =SUMIFS('Schedule 5'!$F$506:$F$544,'Schedule 5'!$I$506:$I$544,'Well Cal.'!F$3,'Schedule 5'!$J$506:$J$544,'Well Cal.'!$E15) -> 0 | G15: =SUMIFS('Schedule 5'!$F$506:$F$544,'Schedule 5'!$I$506:$I$544,'Well Cal.'!G$3,'Schedule 5'!$J$506:$J$544,'Well Cal.'!$E15) -> 0 | H15: =SUMIFS('Schedule 5'!$F$506:$F$544,'Schedule 5'!$I$506:$I$544,'Well Cal.'!H$3,'Schedule 5'!$J$506:$J$544,'Well Cal.'!$E15) -> 0 | I15: =SUMIFS('Schedule 5'!$F$506:$F$544,'Schedule 5'!$I$506:$I$544,'Well Cal.'!I$3,'Schedule 5'!$J$506:$J$544,'Well Cal.'!$E15) -> 0 | J15: =SUMIFS('Schedule 5'!$F$506:$F$544,'Schedule 5'!$I$506:$I$544,'Well Cal.'!J$3,'Schedule 5'!$J$506:$J$544,'Well Cal.'!$E15) -> 0 | K15: =SUMIFS('Schedule 5'!$F$506:$F$544,'Schedule 5'!$I$506:$I$544,'Well Cal.'!K$3,'Schedule 5'!$J$506:$J$544,'Well Cal.'!$E15) -> 0 | L15: =SUMIFS('Schedule 5'!$F$506:$F$544,'Schedule 5'!$I$506:$I$544,'Well Cal.'!L$3,'Schedule 5'!$J$506:$J$544,'Well Cal.'!$E15) -> 0 | M15: =SUMIFS('Schedule 5'!$F$506:$F$544,'Schedule 5'!$I$506:$I$544,'Well Cal.'!M$3,'Schedule 5'!$J$506:$J$544,'Well Cal.'!$E15) -> 0 | ... Z15: =SUMIFS('Schedule 5'!$F$506:$F$544,'Schedule 5'!$I$506:$I$544,'Well Cal.'!Z$3,'Schedule 5'!$J$506:$J$544,'Well Cal.'!$E15) -> 0
E16: P4 - 11th Lift | F16: =SUMIFS('Schedule 5'!$F$506:$F$544,'Schedule 5'!$I$506:$I$544,'Well Cal.'!F$3,'Schedule 5'!$J$506:$J$544,'Well Cal.'!$E16) -> 0 | G16: =SUMIFS('Schedule 5'!$F$506:$F$544,'Schedule 5'!$I$506:$I$544,'Well Cal.'!G$3,'Schedule 5'!$J$506:$J$544,'Well Cal.'!$E16) -> 0 | H16: =SUMIFS('Schedule 5'!$F$506:$F$544,'Schedule 5'!$I$506:$I$544,'Well Cal.'!H$3,'Schedule 5'!$J$506:$J$544,'Well Cal.'!$E16) -> 0 | I16: =SUMIFS('Schedule 5'!$F$506:$F$544,'Schedule 5'!$I$506:$I$544,'Well Cal.'!I$3,'Schedule 5'!$J$506:$J$544,'Well Cal.'!$E16) -> 0 | J16: =SUMIFS('Schedule 5'!$F$506:$F$544,'Schedule 5'!$I$506:$I$544,'Well Cal.'!J$3,'Schedule 5'!$J$506:$J$544,'Well Cal.'!$E16) -> 0 | K16: =SUMIFS('Schedule 5'!$F$506:$F$544,'Schedule 5'!$I$506:$I$544,'Well Cal.'!K$3,'Schedule 5'!$J$506:$J$544,'Well Cal.'!$E16) -> 0 | L16: =SUMIFS('Schedule 5'!$F$506:$F$544,'Schedule 5'!$I$506:$I$544,'Well Cal.'!L$3,'Schedule 5'!$J$506:$J$544,'Well Cal.'!$E16) -> 0 | M16: =SUMIFS('Schedule 5'!$F$506:$F$544,'Schedule 5'!$I$506:$I$544,'Well Cal.'!M$3,'Schedule 5'!$J$506:$J$544,'Well Cal.'!$E16) -> 0 | ... Z16: =SUMIFS('Schedule 5'!$F$506:$F$544,'Schedule 5'!$I$506:$I$544,'Well Cal.'!Z$3,'Schedule 5'!$J$506:$J$544,'Well Cal.'!$E16) -> 0
E17: P4 - 12th Lift | F17: =SUMIFS('Schedule 5'!$F$506:$F$544,'Schedule 5'!$I$506:$I$544,'Well Cal.'!F$3,'Schedule 5'!$J$506:$J$544,'Well Cal.'!$E17) -> 0 | G17: =SUMIFS('Schedule 5'!$F$506:$F$544,'Schedule 5'!$I$506:$I$544,'Well Cal.'!G$3,'Schedule 5'!$J$506:$J$544,'Well Cal.'!$E17) -> 0 | H17: =SUMIFS('Schedule 5'!$F$506:$F$544,'Schedule 5'!$I$506:$I$544,'Well Cal.'!H$3,'Schedule 5'!$J$506:$J$544,'Well Cal.'!$E17) -> 0 | I17: =SUMIFS('Schedule 5'!$F$506:$F$544,'Schedule 5'!$I$506:$I$544,'Well Cal.'!I$3,'Schedule 5'!$J$506:$J$544,'Well Cal.'!$E17) -> 0 | J17: =SUMIFS('Schedule 5'!$F$506:$F$544,'Schedule 5'!$I$506:$I$544,'Well Cal.'!J$3,'Schedule 5'!$J$506:$J$544,'Well Cal.'!$E17) -> 0 | K17: =SUMIFS('Schedule 5'!$F$506:$F$544,'Schedule 5'!$I$506:$I$544,'Well Cal.'!K$3,'Schedule 5'!$J$506:$J$544,'Well Cal.'!$E17) -> 0 | L17: =SUMIFS('Schedule 5'!$F$506:$F$544,'Schedule 5'!$I$506:$I$544,'Well Cal.'!L$3,'Schedule 5'!$J$506:$J$544,'Well Cal.'!$E17) -> 0 | M17: =SUMIFS('Schedule 5'!$F$506:$F$544,'Schedule 5'!$I$506:$I$544,'Well Cal.'!M$3,'Schedule 5'!$J$506:$J$544,'Well Cal.'!$E17) -> 0 | ... Z17: =SUMIFS('Schedule 5'!$F$506:$F$544,'Schedule 5'!$I$506:$I$544,'Well Cal.'!Z$3,'Schedule 5'!$J$506:$J$544,'Well Cal.'!$E17) -> 0
E18: P4 - 13th Lift | F18: =SUMIFS('Schedule 5'!$F$506:$F$544,'Schedule 5'!$I$506:$I$544,'Well Cal.'!F$3,'Schedule 5'!$J$506:$J$544,'Well Cal.'!$E18) -> 0 | G18: =SUMIFS('Schedule 5'!$F$506:$F$544,'Schedule 5'!$I$506:$I$544,'Well Cal.'!G$3,'Schedule 5'!$J$506:$J$544,'Well Cal.'!$E18) -> 0 | H18: =SUMIFS('Schedule 5'!$F$506:$F$544,'Schedule 5'!$I$506:$I$544,'Well Cal.'!H$3,'Schedule 5'!$J$506:$J$544,'Well Cal.'!$E18) -> 0 | I18: =SUMIFS('Schedule 5'!$F$506:$F$544,'Schedule 5'!$I$506:$I$544,'Well Cal.'!I$3,'Schedule 5'!$J$506:$J$544,'Well Cal.'!$E18) -> 0 | J18: =SUMIFS('Schedule 5'!$F$506:$F$544,'Schedule 5'!$I$506:$I$544,'Well Cal.'!J$3,'Schedule 5'!$J$506:$J$544,'Well Cal.'!$E18) -> 0 | K18: =SUMIFS('Schedule 5'!$F$506:$F$544,'Schedule 5'!$I$506:$I$544,'Well Cal.'!K$3,'Schedule 5'!$J$506:$J$544,'Well Cal.'!$E18) -> 0 | L18: =SUMIFS('Schedule 5'!$F$506:$F$544,'Schedule 5'!$I$506:$I$544,'Well Cal.'!L$3,'Schedule 5'!$J$506:$J$544,'Well Cal.'!$E18) -> 0 | M18: =SUMIFS('Schedule 5'!$F$506:$F$544,'Schedule 5'!$I$506:$I$544,'Well Cal.'!M$3,'Schedule 5'!$J$506:$J$544,'Well Cal.'!$E18) -> 0 | ... Z18: =SUMIFS('Schedule 5'!$F$506:$F$544,'Schedule 5'!$I$506:$I$544,'Well Cal.'!Z$3,'Schedule 5'!$J$506:$J$544,'Well Cal.'!$E18) -> 0
E19: P4 - 14th Lift | F19: =SUMIFS('Schedule 5'!$F$506:$F$544,'Schedule 5'!$I$506:$I$544,'Well Cal.'!F$3,'Schedule 5'!$J$506:$J$544,'Well Cal.'!$E19) -> 0 | G19: =SUMIFS('Schedule 5'!$F$506:$F$544,'Schedule 5'!$I$506:$I$544,'Well Cal.'!G$3,'Schedule 5'!$J$506:$J$544,'Well Cal.'!$E19) -> 0 | H19: =SUMIFS('Schedule 5'!$F$506:$F$544,'Schedule 5'!$I$506:$I$544,'Well Cal.'!H$3,'Schedule 5'!$J$506:$J$544,'Well Cal.'!$E19) -> 0 | I19: =SUMIFS('Schedule 5'!$F$506:$F$544,'Schedule 5'!$I$506:$I$544,'Well Cal.'!I$3,'Schedule 5'!$J$506:$J$544,'Well Cal.'!$E19) -> 0 | J19: =SUMIFS('Schedule 5'!$F$506:$F$544,'Schedule 5'!$I$506:$I$544,'Well Cal.'!J$3,'Schedule 5'!$J$506:$J$544,'Well Cal.'!$E19) -> 0 | K19: =SUMIFS('Schedule 5'!$F$506:$F$544,'Schedule 5'!$I$506:$I$544,'Well Cal.'!K$3,'Schedule 5'!$J$506:$J$544,'Well Cal.'!$E19) -> 0 | L19: =SUMIFS('Schedule 5'!$F$506:$F$544,'Schedule 5'!$I$506:$I$544,'Well Cal.'!L$3,'Schedule 5'!$J$506:$J$544,'Well Cal.'!$E19) -> 0 | M19: =SUMIFS('Schedule 5'!$F$506:$F$544,'Schedule 5'!$I$506:$I$544,'Well Cal.'!M$3,'Schedule 5'!$J$506:$J$544,'Well Cal.'!$E19) -> 0 | ... Z19: =SUMIFS('Schedule 5'!$F$506:$F$544,'Schedule 5'!$I$506:$I$544,'Well Cal.'!Z$3,'Schedule 5'!$J$506:$J$544,'Well Cal.'!$E19) -> 0
E20: P4 - 15th Lift | F20: =SUMIFS('Schedule 5'!$F$506:$F$544,'Schedule 5'!$I$506:$I$544,'Well Cal.'!F$3,'Schedule 5'!$J$506:$J$544,'Well Cal.'!$E20) -> 0 | G20: =SUMIFS('Schedule 5'!$F$506:$F$544,'Schedule 5'!$I$506:$I$544,'Well Cal.'!G$3,'Schedule 5'!$J$506:$J$544,'Well Cal.'!$E20) -> 0 | H20: =SUMIFS('Schedule 5'!$F$506:$F$544,'Schedule 5'!$I$506:$I$544,'Well Cal.'!H$3,'Schedule 5'!$J$506:$J$544,'Well Cal.'!$E20) -> 0 | I20: =SUMIFS('Schedule 5'!$F$506:$F$544,'Schedule 5'!$I$506:$I$544,'Well Cal.'!I$3,'Schedule 5'!$J$506:$J$544,'Well Cal.'!$E20) -> 0 | J20: =SUMIFS('Schedule 5'!$F$506:$F$544,'Schedule 5'!$I$506:$I$544,'Well Cal.'!J$3,'Schedule 5'!$J$506:$J$544,'Well Cal.'!$E20) -> 0 | K20: =SUMIFS('Schedule 5'!$F$506:$F$544,'Schedule 5'!$I$506:$I$544,'Well Cal.'!K$3,'Schedule 5'!$J$506:$J$544,'Well Cal.'!$E20) -> 0 | L20: =SUMIFS('Schedule 5'!$F$506:$F$544,'Schedule 5'!$I$506:$I$544,'Well Cal.'!L$3,'Schedule 5'!$J$506:$J$544,'Well Cal.'!$E20) -> 0 | M20: =SUMIFS('Schedule 5'!$F$506:$F$544,'Schedule 5'!$I$506:$I$544,'Well Cal.'!M$3,'Schedule 5'!$J$506:$J$544,'Well Cal.'!$E20) -> 0 | ... Z20: =SUMIFS('Schedule 5'!$F$506:$F$544,'Schedule 5'!$I$506:$I$544,'Well Cal.'!Z$3,'Schedule 5'!$J$506:$J$544,'Well Cal.'!$E20) -> 0
